Workbook

Sheet Release Desk Theme
A1: RELEASE DESK — WHAT IT IS AND WHY IT EXISTS
A2: The guiding idea behind the product. Written in plain language so anyone can understand it.
A4: IN ONE SENTENCE | B4: Release Desk pulls together up-to-date information about a release from all the other systems a company already uses, puts it in one place for the Release Manager, and adds AI insights on top to help them understand and manage the release.
A6: WHAT IT IS | B6: A Release Manager's single pane of glass. Today the information a Release Manager needs is scattered — blockers sit in Jira, incidents in ServiceNow, alerts in Grafana, leave in the HR system, infrastructure state in the cloud and IaC tools. Nobody has the full picture in one place, so people chase updates in meetings, emails and spreadsheets. Release Desk connects to all of those systems, brings the information in, and shows one joined-up view of the release — both a high-level "is this release healthy?" summary and the full detail underneath.
A8: HOW IT WORKS — FOUR STEPS | B8: 1. CONNECT — we integrate with the source systems (Jira, ServiceNow, Grafana, HR, cloud / IaC, CMDB). 2. COLLECT — we pull the information in as frequently as is possible and practical, so what you see is current. 3. COMBINE — we link it all to the release it affects, so one screen answers "what is the state of this release?" 4. ADVISE — AI insights read across everything and give the Release Manager insights, suggestions, direction and pointers on what needs attention.
A10: THE GOLDEN RULE — WE READ, WE DO NOT WRITE | B10: Release Desk does not control or change the source systems. If a blocker lives in Jira, Jira stays the master. We read it, we show it, and when it changes in Jira the change flows back into Release Desk and the release view updates by itself. We never push changes into Jira (or ServiceNow, or Grafana, or HR) from Release Desk. Why: the source system already owns the permissions, the workflow and the audit trail. Writing from a second system creates conflicting updates, permission problems, and an unclear history of who really changed what.
A12: WHAT WE OWN vs WHAT WE ONLY READ
A13: Release Desk owns it (created and closed here) | B13: The Release itself, CAB Approvals, Sign-offs, Dependencies between releases, Conflicts — plus any Blocker or Risk a Release Manager raises directly in Release Desk when there is no external ticket for it. These we manage end to end.
A14: We only read it (the source system stays master) | B14: Jira blockers and work items, ServiceNow incidents, Grafana alerts, HR leave, cloud / IaC drift, CMDB records. Shown read-only, with a link out to the source system if someone needs to change it.
A16: EXAMPLE — A JIRA BLOCKER | B16: 1. A Jira ticket is raised that blocks the release. 2. Release Desk picks it up on the next sync and shows it on the release as a blocker. 3. The team works the ticket and closes it — in Jira. 4. The next sync brings that update in, and Release Desk updates the release by itself; the blocker clears. 5. At no point did Release Desk change the Jira ticket.
A18: AI INSIGHTS ON TOP | B18: Because everything sits in one place, AI can look across the whole picture and tell the Release Manager things no single tool can. For example: • "This release is at risk — two hard dependencies are still open and the CAB date is in two days." • "Configuration drift appeared in PROD twenty minutes after the last deployment." • "The approver you need is on leave on the CAB date — here is a delegate." The AI gives insights, suggestions and pointers. The Release Manager stays in control and makes the decisions.
A20: WHAT RELEASE DESK IS NOT | B20: • Not a replacement for Jira, ServiceNow, Grafana or the HR system. • Not a place to edit those systems' records. • Not the system of record for anything it did not create. • Not a rigid gatekeeper — it warns and advises, and lets the Release Manager decide, with the reason recorded.
A22: HOW THIS SHAPES THE RULES | B22: This theme is the reason the rules are written the way they are: • Every entity has an Origin — Native (ours, we manage it fully, start to finish) or External (theirs, we only read it). • External records are read-only in Release Desk, with a deep-link out; sync is one-way and inbound only — Release Desk never writes back into Jira, ServiceNow, or any other outside system. Release Desk always displays exactly what the source system currently reports — there is no local override or provisional status held against an external record. • Governance gates warn rather than hard-block wherever a real business judgement call exists, and the Release Manager can override with a recorded reason. Only a small number of true invariants stay hard rules — mainly where the code is already live in production (Deploying, Deployed) or a formal decision has already been made (an Approval or Sign-off once granted). • A record that has reached its own terminal status (Closed, Resolved, Accepted, and so on) is naturally read-only — that's what terminal means. If someone needs to act on it again, they clone it forward, attachments and comments included, rather than reopening old history.
A24: CUSTOMISATION — EVERY CLIENT CONFIGURES THEIR OWN RELEASE DESK | B24: No two clients run releases the same way. One client's lifecycle might have fifteen stages (Draft → Planning → Testing → UAT → Pending CAB → ... → Closed); another just wants four (Draft, In Progress, Deployed, Blocked). One calls it "Risk"; another calls the exact same thing "Impediment". So nothing about the process itself — the stage names, the order they happen in, what counts as high risk, which fields are mandatory — is fixed in the product. It is all configuration that each client sets up for themselves, not code we change per client.
A26: WHAT IS CONFIGURABLE | B26: • Lifecycle stages & transitions for every entity (Release, Risk, Blocker, Approval, Sign-off, Dependency, Conflict, Drift, Incident, Alert) — a client can shrink our 15-stage Release lifecycle to 4 stages, rename any stage, or reorder the recommended path. • Terminology — every entity and field label ("Risk" → "Impediment", "CAB" → "Change Board", "Sign-off" → "Attestation") without touching a line of code. • Risk model — the scoring scale (1-25 grid vs a 1-5 weighted score), the severity breakpoints, the risk factors that feed the weighted score, and each factor's weight. • Field rules — which fields are required, read-only, or hidden at each stage (our §1/§2/§3 rules become per-client data, not hardcoded checks). • Reference lists — Departments, Environments, Priorities, Approval Types, Sign-off Types, Roles — every list in our Reference Data sheet is a client-editable table, not a fixed set of values. • Governance thresholds — CAB lead times, freeze windows, SLA targets, override friction (warn vs hard-block) per rule.
A28: WHAT STAYS FIXED (THE ENGINE, NOT THE CONFIG) | B28: The rule PATTERNS stay the same even though the values inside them are configurable. For example, "a release cannot skip its final pre-deployment stage" (CFG-06) is a fixed engine behaviour — but WHICH stage is the final pre-deployment stage ("Ready", or a client's renamed equivalent) is configuration. Similarly "risks above a severity threshold need a mitigation plan before the gate" (VR-27) is a fixed pattern — but the threshold, the severity labels, and the gate it applies to are all configurable per client.
A30: SEE ALSO | B30: The "Notes for Development" sheet sets out how our developers should actually build this — the data model, the rule engine approach, and specific guidance for working with AI-assisted ("vibe coding") development so customisation stays data-driven instead of quietly turning back into hardcoded, client-specific code.

Sheet Notes for Development
A1: NOTES FOR DEVELOPMENT — BUILDING A FULLY CONFIGURABLE RELEASE DESK
A2: How to architect client-specific customisation (lifecycle stages, terminology, risk model, field rules) so it stays configuration, not per-client code. Written for AI-assisted ("vibe coding") development.
A4: 1. CORE PRINCIPLE — CONFIGURATION AS DATA, NOT CODE | B4: Every place this workbook models a fixed list or a status name — Reference Data's code tables, Entity Classification's lifecycles, the Status Lifecycles / LC_ sheets, Rules Specification's thresholds — must become a row in a database table per client ("tenant"), never a string literal, enum, or switch-statement branch in application code. If a developer (or an AI coding assistant) writes if (status === "Draft") or a hardcoded list of risk factors, that is the bug this section exists to prevent. The test: could a client rename, reorder, or delete this value from a settings screen without a code change and a redeploy? If not, it is not actually configurable yet.
A6: 2. WHAT MUST BE CONFIGURABLE (SUMMARY) | B6: See the "Release Desk Theme" sheet's new "Customisation" section for the client-facing explanation. In short: lifecycle stages & transitions per entity, terminology/labels per entity and field, the risk model (scale, breakpoints, factors, weights), field requirement rules per status, every reference list (Departments, Environments, Priorities, Approval/Sign-off types, Roles), and governance thresholds (CAB lead times, freeze windows, SLAs, override friction). The sections below cover how to build each of these so they behave that way in practice.
A8: 3. RECOMMENDED DATA MODEL
A9: Table | B9: Key Columns & Purpose
A10: tenants | B10: tenant_id, name, template_source. One row per client. Every other config table below is scoped by tenant_id.
A11: entity_types | B11: entity_key (e.g. "release", "risk"), has_lifecycle. The fixed list of entity kinds the engine knows about — this list itself is NOT tenant-configurable, only what each entity is called and how it behaves is.
A12: label_dictionary | B12: tenant_id, entity_key, field_key, display_label. Every user-facing word ("Risk", "CAB", "Sign-off", a field name) is looked up here by key at render time — never hardcoded in a UI component or generated document.
A13: workflow_definitions | B13: tenant_id, entity_key, status_code, display_label, sequence, is_terminal, is_initial. Replaces our Status Lifecycles / LC_ sheets — one row per status a client has configured for a given entity.
A14: workflow_transitions | B14: tenant_id, entity_key, from_status_code, to_status_code, is_recommended. Replaces the "Next Possible Status" column — drives the CFG-07 warn-if-off-path behaviour, not a hard block, per entity per tenant.
A15: field_rules | B15: tenant_id, entity_key, field_key, status_code, requirement (required / optional / read_only / hidden). Replaces the §1/§2/§3 rule sections — one row per field per status per tenant.
A16: risk_factor_weights | B16: tenant_id, factor_key, category, weight_pct. Replaces Reference Data's "Risk Factor Weights by Category" — must sum to 100% per tenant (validate on save, mirroring the live =SUM check in Reference Data).
A17: severity_bands | B17: tenant_id, entity_key, scale_type (e.g. "probability_impact" or "weighted_score"), min_value, max_value, severity_label, color, approval_level. Replaces the Risk Scoring Matrix / Risk Score Thresholds tables — lets a tenant pick their own scale and breakpoints.
A18: rule_configs | B18: tenant_id, rule_id (e.g. "VR-27"), enabled, severity (warn/block/off), threshold_value, threshold_ref (which status_code or severity_label it points at). The rule PATTERN (see §4 below) reads this row instead of a hardcoded constant.
A19: reference_lists | B19: tenant_id, list_key (e.g. "department", "environment", "priority", "approval_type"), code, display_label, sort_order. One generic table for every simple picklist in Reference Data, instead of a bespoke table per list.
A21: 4. HOW THE RULE ENGINE SHOULD WORK | B21: Split every rule into a fixed PATTERN (code) and a variable CONFIGURATION (data, from rule_configs/severity_bands above). Example — VR-27 "Risks above a severity threshold need a mitigation plan before the gate": the pattern is generic ("IF linked entity's severity_label >= rule_configs.threshold_value AND status = rule_configs.threshold_ref THEN require field X"); the specific threshold ("High"), the gate it applies to ("Ready"), and whether it's a warn or a hard block are all pulled from config at evaluation time. Write the engine so a new rule pattern is added rarely (it's a code change and a release), but every rule's threshold, severity, and enforcement level is edited by an admin, per tenant, with no deploy. Rule IDs (VR-27, CASC-01, etc.) stay stable identifiers across tenants even when the tenant's own label for the thing the rule governs changes — the rule engine works on keys, the UI shows labels.
... A29: 8. MIGRATION & AUDIT | B29: Config changes are themselves governed events, not silent edits — mirror CFG-03 (Configurable Severity: changes restricted to admins, audited, effective-dated) and CFG-04 (Override Audit) from Rules Specification. Every write to workflow_definitions, field_rules, risk_factor_weights, or rule_configs should record who changed it, when, and the before/after value, and should be effective-dated so an in-flight release started under the old configuration doesn't retroactively break. Changing a lifecycle out from under records currently sitting in a status that no longer exists needs an explicit migration path (e.g. map removed statuses to a nearest-equivalent surviving one), not a silent data integrity failure.
A31: Notes for Development v1.0 | Companion to Release Desk Theme's "Customisation" section | 06-Aug-2026

Sheet Signal Classification
A1: 🎯 SIGNAL CLASSIFICATION — Two-Polarity Model
A2: My thoughts on collapsing every release parameter into 2 classes, and handling org-to-org differences. Suggestion only — nothing else changed.
A4: 1 · THE CORE IDEA
A5: Every parameter that touches a release does one of two things: it HELPS the release advance, or it HOLDS it back. So model them all as one thing — a "Signal" — and give each a Polarity. That's the only hard classification you need.
A6: ENABLER (+) | B6: Must be PRESENT / COMPLETE to proceed | C6: e.g. Approvals, Sign-offs, Rollback plan ready, Go-live checklist, Test pass
A7: IMPEDIMENT (−) | B7: Must be ABSENT / CLEARED to proceed | C7: e.g. Blockers, Risks, Drift, Conflicts, Incidents, Alerts, Freeze, blocked Dependencies
A9: 🔑 The unifier: both classes reduce to ONE question — "Is this gate satisfied?" An enabler is satisfied when it is PRESENT; an impediment is satisfied when it is CLEARED. Your engine only ever asks that one boolean, whatever the parameter.
A11: 2 · POLARITY MAP (your current entities)
A12: Parameter | B12: Polarity | C12: "Satisfied" means…
A13: Approvals | B13: Enabler (+) | C13: Approved
A14: Sign-Offs | B14: Enabler (+) | C14: Signed off
A15: Rollback Plan | B15: Enabler (+) | C15: Ready
A16: Go-Live Checklist | B16: Enabler (+) | C16: Complete (100%)
A17: Blockers | B17: Impediment (−) | C17: Resolved / Closed
A18: Risks | B18: Impediment (−) | C18: Closed / Accepted
A19: Drift | B19: Impediment (−) | C19: Resolved
A20: Conflicts | B20: Impediment (−) | C20: Resolved
A21: Incidents | B21: Impediment (−) | C21: Resolved / Closed
A22: Alerts | B22: Impediment (−) | C22: Resolved
A23: Change Freeze | B23: Impediment (−) | C23: Outside freeze, or exemption granted
... A25: Dependencies | B25: Contextual ⇄ | C25: Satisfied when clear; becomes an impediment when blocked — polarity follows the STATE, not the label
A26: 💡 Note: a few parameters flip polarity by state (a dependency helps when satisfied, hurts when blocked). That's fine — it reinforces that polarity is really a property of the current gate check, not a fixed tag.
A28: 3 · PROBLEM 1 — same thing, different names (Risk vs Issue)
A29: Fix: an ALIAS layer. Keep one canonical/internal name; let each org set its own display label. The engine references the canonical name; the UI shows the org's word. No logic changes.
A30: Canonical (internal) | B30: Polarity | C30: Example labels different orgs use
A31: IMP_RISK | B31: Impediment | C31: Risk / Issue / Concern / Threat
A32: IMP_BLOCKER | B32: Impediment | C32: Blocker / Impediment / Showstopper
A33: ENA_APPROVAL | B33: Enabler | C33: Approval / Sign-off / Gate / Authorisation
A35: 4 · PROBLEM 2 — same thing, different number of statuses (2 vs 4)
A36: Fix: STATUS NORMALIZATION. However many custom statuses an org has, each one maps to a tiny fixed set of canonical states. App logic runs on the canonical state + a single 'satisfies gate?' flag — never on the org's raw status text.
A37: Minimal universal set (drives go/no-go): OPEN → CLOSED. Optional richer set for reporting: NOT STARTED → IN PROGRESS → RESOLVED → CLOSED.
A39: Org status (their words) | B39: Maps to canonical | C39: Satisfies gate? | D39: Terminal / immutable?
A40: Org A — 4-status Risk
A41: Open | B41: OPEN | C41: No | D41: No
A42: Mitigating | B42: IN PROGRESS | C42: No | D42: No
A43: Accepted | B43: CLOSED | C43: Yes | D43: Yes
A44: Closed | B44: CLOSED | C44: Yes | D44: Yes
A45: Org B — 2-status Risk
A46: Open | B46: OPEN | C46: No | D46: No
A47: Closed | B47: CLOSED | C47: Yes | D47: Yes
A48: → Both orgs feed the SAME engine, which only sees 'satisfies gate? Yes/No'. Depth of workflow becomes a config choice, not a code change.
A50: 5 · NET RECOMMENDATION
A51: Make the whole system org-agnostic with 3 small config layers. Only the first is fixed by you; the other two are filled per-org at onboarding.
A52: Layer | B52: What it defines | C52: Set by
A53: 1. Polarity | B53: Enabler vs Impediment — the only hard classification. Tiny, fixed list. | C53: You (product)
A54: 2. Alias map | B54: Canonical name → the org's own word (Risk = Issue). | C54: Per org
A55: 3. Status map | B55: Org's custom statuses → canonical state + 'satisfies gate?' flag + terminal flag. | C55: Per org
A57: Release readiness (works for any org):
A58: READY = ( every ENABLER gate satisfied ) AND ( no OPEN IMPEDIMENT gate )
A60: Payoff: onboarding a new org = fill 2 small tables (alias + status map). No schema change, no new sheets per parameter, no code branching. The 10 LC_ lifecycle sheets you already have effectively become one generic, config-driven lifecycle.
A62: Signal Classification v1.0 | Thought-starter, not a spec |

Sheet Change Log
A1: CHANGE LOG — HOW WE ENDED UP AT EACH RULE
A2: A running history of every major decision made in this workbook, in the order they happened, so anyone can see why a rule is the way it is without having to ask. Add a new row here every time a rule-level decision is made — don't delete old rows. For the detailed backlog of what's built vs still pending, see 'RD Functional improvements'.
A4: # | B4: What changed | C4: Why (in plain words) | D4: Decided by | E4: Where to look for detail
A5: 1 | B5: Reviewed all 13 test suites and added colour-coded 'Review Findings' columns. | C5: Needed a systematic check for accuracy — invalid statuses, wrong or fabricated rule IDs, and outright contradictions between tests — before any of it could be trusted. | D5: My analysis, at the user's request | E5: Each test suite tab, column K
A6: 2 | B6: Deleted §1-12 (Incident Reference Format) and its two tests. | C6: Reference numbers are created and managed by external systems, not typed in by hand — so a rule validating their format by hand didn't make sense. | D6: User decision | E6: Rules Specification; Incident Test Suite
A7: 3 | B7: Split CASC-12 into CASC-12 (Circular Dependency Block) and CASC-13 (Cancellation Cascade). Fixed VR-32, §4-17, and several rule descriptions that had been copy-pasted from the wrong neighbouring rule. | C7: One rule ID was doing two unrelated jobs at once, and a handful of rules had the right name but the wrong explanation underneath. | D7: My analysis, user approved | E7: Rules Specification
A8: 4 | B8: Introduced the Native vs External Origin model, the Provisional Status Override + Reconciliation, Verified vs Projected Readiness, Link/Unlink rules, and rewrote the cancellation cascade so external entities are unlinked (not cancelled). | C8: This is the foundation of the Release Desk Theme: read external systems, never write to them, and give the RM a way to reflect reality ahead of a slow-to-update source. | D8: User decision (Release Desk Theme) | E8: FI-01, FI-04, FI-05, FI-06, FI-08, FI-09 in 'RD Functional improvements'
A9: 5 | B9: Changed 14 governance gates from hard BLOCK to WARN + audited override. Added a Blocking/Advisory Impact flag to Blockers. | C9: Too many hard blocks were getting in the Release Manager's way for things that are really business judgement calls, not physical impossibilities. | D9: User decision | E9: FI-11 in 'RD Functional improvements'
A10: 6 | B10: Resolved all 52 open items in the Rule Gap Register: added 20 new rules, amended 10 existing ones. | C10: A full backlog clear-out, using the Release Desk Theme and the rigid/flexible principle as the decision rule for each item. | D10: My analysis, guided by the user's stated principles | E10: FI-16 in 'RD Functional improvements'
A11: 7 | B11: Renamed the release status 'Approved' to 'CAB Approved' everywhere. | C11: Approved' meant three different things at once — the release status, an Approval's decision, and a Sign-off's decision — and it was causing real confusion. | D11: User decision | E11: FI-15 in 'RD Functional improvements'
A12: 8 | B12: Flipped §4 transition rules (01-13, 16) from BLOCK to WARN + override. Added CFG-06/CFG-07. | C12: Most status changes are business decisions that differ by organisation. Only a release actually running in production, or one that's Closed/Cancelled, is a genuine invariant. | D12: User decision | E12: FI-12 in 'RD Functional improvements'
A13: 9 | B13: Reverted §4-08 and §4-09 back to hard BLOCK. Expanded CFG-06. | C13: The user caught that 'Deploying can only become Deployed/Rolled Back/Blocked' has no real alternative anywhere — it should never have been made flexible. | D13: User caught this | E13: Rules Specification, CFG-06
A14: 10 | B14: Made Incidents, Sign-Offs, Dependencies, Conflicts, and Drift Records all dual-origin (Native or External), matching Blockers/Risks/Approvals/Alerts. | C14: The user pointed out any of these could come from an external tool, or be created directly in Release Desk, and the rules should say so consistently — not just for some entities. | D14: User decision | E14: Entity Classification
A15: 11 | B15: Rewrote the 'RELATED ENTITY LOCK RULES' section in Release Fields: added the VR-39 blanket rule, reframed §3-22, added CLONE-02. | C15: The user identified that 'make it read-only once the release reaches a certain status' was solving a problem that didn't exist — an item is already read-only once IT reaches its own terminal state, and the entry gates already force that by the time it matters. | D15: User caught this | E15: Release Fields; Rules Specification VR-39, §3-22, CLONE-02
A16: 12 | B16: Rewrote SYNC-01/02/03/10 to one-way inbound sync only. Fixed a missed 'Approved' in Reference Data. Added an 'Enforcement' column to Status Lifecycles. | C16: Checked a ChatGPT-authored gap review before trusting it. Two of its findings were real — these sync rules genuinely described Release Desk writing into Jira/ServiceNow, breaking the core promise. Also caught a rename we'd missed, and added a good documentation suggestion. | D16: External review (ChatGPT), verified before acting | E16: FI-17 in 'RD Functional improvements'
... A23: 19 | B23: Removed Provisional Status Override + Reconciliation entirely (OVR-01 to OVR-05). External entities now always display exactly what the source system reports, with no local override capability at all. | C23: Reconfirmed as unwanted: the feature was previously introduced (#4) as part of finalising the Theme, but on review the decision is that Release Desk should never hold any local override against an external record, even temporarily — just display the source as-is. | D23: User decision | E23: Rules Specification (deleted OVR-01..05 + legend row; fixed LNK-03, §2-02); Release Desk Theme; Status Lifecycles (deleted Provisional Override Lifecycle section); RD Functional improvements (FI-04/05/06/07 marked Reversed, FI-19 added); deleted 'Override Reconciliation Tests' sheet

Sheet RD Functional improvements
A1: Release Desk — Functional Improvements (Change Register)
A2: Origin-based ownership of operational entities (Blockers, Risks, Alerts, Leaves) and the supporting Link/Unlink model. Work through one item (FI-xx) at a time: define full scope → validate → apply to Rules → apply to Test Suites.
A4: Core principle: every entity has ONE System of Record (SoR). If it originates in Release Desk it is NATIVE (RD owns full lifecycle). If it mirrors an external system (Jira / ServiceNow / Grafana / HR) it is EXTERNAL (read-only source; RD always displays exactly what the source reports, with no local override).
A6: ID | B6: Improvement | C6: Decision / Description | D6: Entities in scope | E6: Rules impact | F6: Test-suite impact | G6: Seq | H6: Status
A7: FI-01 | B7: Origin-based ownership (Native vs External) | C7: Every linkable operational entity carries an Origin attribute. Native = created in RD (SoR = RD). External = mirrored from an SoR. Origin drives editability, permissions, and sync direction. | D7: Blocker (N/E), Risk (N/E), Alert (E only*), Leave (E only) | E7: Entity Classification: add Origin + SoR columns. New rule: 'Origin determines ownership'. | F7: New: origin flag set on create; Leave/Alert always External; Native vs External branching. | G7: 1 | H7: Done (rules + tests)
A8: FI-02 | B8: Native entity full lifecycle in RD | C8: For Native entities RD is the SoR: full create → resolve → close managed entirely in RD. No external sync, no Provisional Override. | D8: Blocker, Risk (Native) | E8: Confirm Blocker/Risk lifecycles apply to Native; RM/owner create & manage permissions. | F8: Native create→close; native edit allowed; existing lifecycle tests re-scoped to Native. | G8: 2 | H8: Done (rules + tests)
A9: FI-03 | B9: External entity = read-only mirror | C9: External source record is read-only in RD; RD never writes to the SoR. Show source status + 'source' badge + last-synced; deep-link to SoR for real edits. | D9: Blocker, Risk, Alert, Leave (External) | E9: New rule: external source read-only in RD; inbound one-way sync; deep-link out. | F9: Cannot edit external source; deep-link present; sync updates status. | G9: 3 | H9: Done (rules + tests)
A10: FI-04 | B10: Provisional Override + Pending Reconciliation | C10: RM sets an RD-local provisional status on an External entity. Effective status = provisional ≠ null ? provisional : source. New 'Pending Reconciliation' state. Never writes to SoR. | D10: External Blocker, Risk, Alert | E10: New lifecycle (Pending Reconciliation); effective-status resolution rule; RM/owner permission; audit. | F10: Set/clear override; effective status; provisional badge; permission; audit. | G10: 4 | H10: REVERSED 06-Aug-2026 (see FI-19)
A11: FI-05 | B11: Reconciliation on sync + outcomes | C11: Each sync compares source vs provisional: Match → Reconciled (clear override); Source still behind → hold (timer runs); Source diverged (e.g. reopened) → Conflict (drop override, alert RM). Reuses the Drift model. | D11: External Blocker, Risk, Alert | E11: New AV rule (reconciliation job); conflict handling; audit of each outcome. | F11: Reconciled / behind / diverged paths; conflict alert. | G11: 5 | H11: REVERSED 06-Aug-2026 (see FI-19)
A12: FI-06 | B12: Verified vs Projected readiness + hard gate | C12: Two readiness figures: Verified (source status only) and Projected (includes overrides). Final Ready → Deploying requires all overrides reconciled (Verified == Effective) — cannot deploy on a promise. | D12: Release (readiness), all External entities | E12: Update §2-02 / AV-20 readiness calc; new hard-gate rule requiring reconciliation before Deploying. | F12: Readiness split shown; gate blocks on unreconciled override. | G12: 6 | H12: REVERSED 06-Aug-2026 (see FI-19)
A13: FI-07 | B13: Reconciliation follow-up / escalation | C13: Unreconciled overrides nag the RM; escalate as CAB / Go-Live approaches; overrides expire if never reconciled. | D13: External Blocker, Risk, Alert | E13: New AV + NOTIF rules (nudge, escalate, expire). | F13: Nudge at T-minus; escalation near gate; expiry. | G13: 7 | H13: REVERSED 06-Aug-2026 (see FI-19)
A14: FI-08 | B14: Manual Link / Unlink rules | C14: Govern linking and manual unlinking of entities to a release. Permission (RM/owner); status-based lock (generalise VR-36 to all linked types); origin-based outcome — External → detach only; Native → no orphan (delete or reassign); audit. | D14: Blocker, Risk, Alert, Sign-off, Dependency | E14: New Link rule; new Unlink rule; generalise VR-36; audit rule. | F14: Link dedup; unlink per origin; lock after Ready; audit. | G14: 8 | H14: Done (rules + tests)
A15: FI-09 | B15: Cancellation cascade = unlink (external) / cancel (native) | C15: On release cancellation: unlink ALL children; cancel only Approvals, Dependencies. External Entities — unlinked, never cancelled/updated. | D15: All child entities | E15: CASC-13 rewritten; glossary updated. | F15: Cancellation tests flipped to unlink for Blockers/Risks/Alerts. | G15: — | H15: DONE (this session)
A16: FI-10 | B16: Alert & notification rule gaps (from external Alerts suite) | C16: Incorporate genuine rule gaps surfaced by the ChatGPT-authored Alerts suite: blocker-resolved & environment-booking notifications, quiet-hours + subscription preferences, maintenance-mode sync suspension + sync audit logging, Change Manager cross-release alert visibility. Did NOT import the ~180 duplicate/UI-level tests. | D16: Alerts, Notifications, Sync, Change Manager role | E16: New rules NOTIF-13..16, SYNC-11/12, ROLE-11 (Section 14); fixed corrupted NOTIF-12 & SEC-01/03/04 descriptions; renumbered ownership section 10→13; legend counts updated. | F16: New 'Alert Rule Gap Tests' suite (15 tests). | G16: 9 | H16: Done (rules + tests)
A17: FI-11 | B17: Warn + audited override for governance gates (configurable) | C17: 14 governance gates changed from hard BLOCK to WARN: the RM/owner may proceed by entering a mandatory audited reason. Conscious-override friction is proportional to impact (reason; + maths/type-to-confirm near go-live; no CAPTCHA). Severity is configurable per org (raise back to BLOCK / turn OFF); hard invariants stay locked. Blockers gain an Impact flag (Blocking/Advisory) so only Blocking blockers gate transitions. | D17: Governance gates (VR-02/14/15/16/18/24/27/28/29/30/31/32/33/34); Blockers | E17: Section 15 CFG-01..05; 14 VR gates BLOCK→WARN + Overridable?/Friction columns; Blocker Impact flag in Entity Classification | F17: Update affected gate tests to warn+override; add Override & Config test suite | G17: 10 | H17: Done (rules + tests)
A18: FI-12 | B18: Flexible Transitions — denylist model instead of whitelist (in progress) | C18: Currently every lifecycle (Releases, Blockers, Approvals, Sign-Offs, Risks, Incidents, Dependencies, Conflicts, Drift, Alerts) uses a whitelist of allowed next-statuses, and all 16 release transition rules (§4-01..§4-16) are hard BLOCK with no override. Agreed direction: flip this to a short denylist of true invariants (things that genuinely cannot be undone, e.g. a Deployed release cannot go back to Draft) plus everything else becomes warn-and-proceed, with a friction level attached (plain reason, or reason + typing the release name and your own name for the higher-stakes moves). | D18: Phase A: draft the T0 invariant list for approval (done — see 'Need to be resolved' tab, item NR-03). Phase B: update Rules Specification (§4 transition rules + new flexible-transition rule). Phase C: update Status Lifecycles (rename 'Next Possible Status' to 'Recommended', add a 'Hard-blocked' column, fix the Approvals/Sign-Offs over-use of FINAL — e.g. Deferred approval wrongly immutable). Phase D: update the ~111 existing test cases that currently assert these transitions are rejected. | E18: §4 transition rules, all 11 status lifecycles, CFG-02 (friction tiers) | F18: IMPORTANT — Phase D (rewriting ~111 test cases) is DELIBERATELY DEFERRED until Phases A-C are finalised and approved, so the test rewrite isn't done twice if the invariant list changes. This is a standing reminder that Phase D work is still owed. | G18: 11 | H18: Rules DONE (Section 16: CFG-06/07 + §4-01..13,16 flipped to WARN+override; Section 17: 20 supporting rules). Tests (Phase D, ~111 cases) still pending.
A19: FI-13 | B19: Release Cloning (copy a Cancelled/any release into a new one) | C19: Resolved via NR-03 borderline (A): a Cancelled release stays permanently immutable and is NOT reopenable — that decision stands as originally drafted. Instead, add a Clone / Copy Release action: the user picks an existing release (cancelled or otherwise) and creates a brand-new release pre-populated from it, with the option to carry over Approvals, Attachments, Blockers, and other linked records rather than starting from a blank form. | D19: Release, Approvals, Attachments, Blockers (confirm whether Sign-offs, Dependencies and Risks should also be carry-over candidates, or just the three named) | E19: Design question to resolve before building: should cloned Approvals/Sign-offs carry over AS ALREADY APPROVED for the new release, or only as reference copies with the new release required to obtain fresh approvals? Carrying them over as already-approved would let a new release skip real governance, which conflicts with the CAB/sign-off gates — my recommendation is fresh approvals required, old ones copied for reference only, but this needs your confirmation. | F19: New rule defining clone behaviour + what carries over by default vs. opt-in; new test coverage | G19: 12 | H19: Rules DONE (CLONE-01 added: fresh Approvals/Sign-offs required on clone, old ones copied as reference only). Tests pending.
A20: FI-14 | B20: Dependency "Met" reversal when the predecessor is rolled back | C20: SUPERSEDED by FI-18 below: no longer a silent automatic revert. AV-26 now flags the dependency At Risk and requires the RM to consciously acknowledge (type release name + their own name) before cloning or creating a new dependency to resolve it. | D20: Dependencies, Releases (Rolled Back transition) | E20: See FI-18 — AV-26 rewritten | F20: New rule pairing with AV-04/CASC-04 (the reversal path); new test coverage | G20: 12 | H20: Superseded by FI-18 (design changed per Deepseek review)
A21: FI-15 | B21: Rename release status 'Approved' → 'CAB Approved' (disambiguation) | C21: The word 'Approved' was overloaded three ways: the release status, an Approval record's decision, and a Sign-off's decision. Renamed the release status specifically to 'CAB Approved' so it can never be confused with the other two again. Also corrected Entity Classification: the CAB approval may be Native (a manually-tracked approval, when there's no external CAB system) or External (linked read-only to a ServiceNow/Jira CAB ticket, auto-synced, no internal lifecycle needed for that record). | D21: Done: Rules Specification (§4-05, §4-06, §4-16, VR-21), Status Lifecycles (Releases block), Release Fields (status column header), Entity Classification (Approvals Origin). | E21: Still open: 42 test cells across 10 suites (Release 22, Sign-Off 4, Drift 3, CAB Approvals 3, Risk 2, Incident 2, Alerts 2, Blockers 2, Conflicts 1, Dependencies 1) still say bare 'Approved' meaning the release status. Needs careful per-cell review, not a blind find/replace, since 'Approved' also correctly appears as a Sign-off/Approval decision value in the same suites. | F21: Test suites (see column E for breakdown) | G21: 13 | H21: Rules DONE (CAB Approved rename complete). Test-suite ripple (42 cells) still pending.
A22: FI-16 | B22: Rule Gap Register full resolution (all 52 open items closed) | C22: Went through every open item in the Rule Gap Register and resolved it, guided by the Release Desk Theme (read-not-write, one source of truth, configurable per org) and the rigid/flexible principle (lock only true invariants; make everything else configurable with sensible defaults, warn-and-override where it's a judgment call). | D22: All 13 test suites; Release Fields; Rules Specification Sections 16 & 17 | E22: 20 new rules added (Section 17): §1-16/17/18, §2-13/14, §3-23, ROLE-12/13/14, NOTIF-17, DRIFT-01, VR-38/39, SYNC-13/14, SEC-13..17. Plus 10 existing rules amended for configurability/clarity (VR-03, VR-11, VR-12, VR-27, AV-02, AV-04, AV-07, AV-09, AV-22, §1-04). | F22: Register: all 52 items now Closed with resolution notes. Tests: none of the 20 new rules have test coverage yet — that's new work, not part of the original Phase D backlog. | G22: 14 | H22: Rules DONE. Test coverage for the 20 new rules is a new, not-yet-started item.
A23: FI-17 | B23: Gap Review (ChatGPT) checked and resolved — see GR2 tab | C23: A ChatGPT-authored 'Gap Review' tab raised 10 findings. Checked every one against the real sheets before trusting any of it. 3 were real theme violations/gaps, 1 was factually wrong (would have re-broken the CAB Approved fix), 5 were already-known test-case work, 1 was a good documentation suggestion. Found 2 more real issues of the same kind while checking. Full reasoning is in the GR2 tab. | D23: Rules Specification (SYNC-01/02/03/10), Reference Data, Status Lifecycles | E23: SYNC-01/02/03/10 rewritten to one-way inbound-only sync (they previously described Release Desk writing into Jira/ServiceNow, breaking the Golden Rule). Reference Data 'Approved' → 'CAB Approved' (a miss from FI-15). New 'Enforcement' column added to Status Lifecycles (Required vs Flexible vs Automated) across all 11 lifecycles. | F23: No test impact — these were spec-only corrections and a new documentation column, not new testable behaviour beyond what FI-11/FI-12 already require. | G23: 15 | H23: Done (rules fixed + documentation added)
A24: FI-18 | B24: Deepseek review acted on — conscious alerts (release name + your name) | C24: A 'Deepseek review' tab proposed 5 ideas. Checked each one (see the now-deleted 'response to deepseek' tab for the full reasoning). Acted on 3 of them, all using a new 'conscious alert' pattern: the person must type the release name and their own name before proceeding, not just click a button. One idea (external data shown as-is) already matched our design. One idea (auto-revert dependencies) directly contradicted an earlier explicit decision, so it replaced that decision only because the user re-confirmed it after seeing the conflict. | D24: Dependencies (AV-26), Incidents (AV-06, CASC-03), Link/Unlink (new LNK-04), Status Lifecycles (Dependency Met enforcement note) | E24: LNK-04 added (unlink watchlist + conscious CAB acknowledgment). AV-06 + CASC-03 rewritten (Critical incident no longer auto-blocks; RM alerted and decides, with conscious alert). AV-26 rewritten (dependency rollback now alerts + flags At Risk, RM resolves manually via clone/new dependency, conscious alert required) — this replaces FI-14's original automatic-revert design. | F24: New test coverage needed for all three (watchlist behaviour, incident alert choice, dependency rollback alert) — not yet written. | G24: 16 | H24: Rules DONE. Tests not yet started.
A25: FI-19 | B25: Provisional Override + Reconciliation removed entirely | C25: Reconfirmed as unwanted: for External entities, Release Desk always displays exactly what the source system currently reports — no local provisional status, no effective-status split, no reconciliation-on-sync logic. This reverses FI-04, FI-05, FI-06, and FI-07 in full. | D25: External Blocker, Risk, Alert; Release readiness | E25: Rules Specification: deleted OVR-01..OVR-05 and the OVR-xx legend row; simplified LNK-03 (no longer clears an override); simplified §2-02 (single Readiness % figure, no Verified/Projected split). | F25: Deleted 'Override Reconciliation Tests' suite entirely. No other suite had override-specific tests. | G25: — | H25: REVERSED (this session) — see Change Log
A26: Notes / open decisions
A27: * RESOLVED: all nine transactional entities (Blockers, Incidents, Approvals, Sign-Offs, Risks, Dependencies, Conflicts, Alerts, Drift Records) now support both Native and External origin — the user confirmed this generalisation directly. Only Leave stays External-only (HR-sourced), correctly.
A28: Workflow per item: (1) determine full scope across all rules + suites, (2) validate, (3) apply to Rules Specification / Status Lifecycles / Entity Classification, (4) apply to the affected Test Suites. Update Status column as each completes.
A29: Sequencing rationale: FI-01 (ownership flag) is the foundation everything branches on, so it goes first; readiness/gate (FI-06) depends on the override model (FI-04/05); link/unlink (FI-08) can follow independently.

Sheet Missing Edge Cases
A1: TC ID | B1: Description | C1: Type | D1: Related Rule | E1: Preconditions (Given) | F1: Steps (When) | G1: Expected Result (Then) | H1: Expected Message | I1: Suite/Priority | J1: Section
A2: EDGE-TC-01 | B2: Concurrent status transitions on same release | C2: E | D2: Concurrency | E2: Two users open the same release simultaneously. | F2: Both click transition buttons at the same time. | G2: Only one transition succeeds. Second user gets stale-data warning. | H2: Your copy is out of date — reload before proceeding. | I2: Regression · P1 | J2: Concurrency & Race Conditions
A3: EDGE-TC-02 | B3: Concurrent environment booking | C3: E | D3: Concurrency | E3: Two releases try to book the same env slot simultaneously. | F3: Both click Book at the same time. | G3: One succeeds. Other gets conflict notification. | H3: Environment just booked by another release — select different slot. | I3: Regression · P1 | J3: Concurrency & Race Conditions
A4: EDGE-TC-03 | B4: Concurrent sign-off and cancellation | C4: E | D4: Concurrency | E4: User A signs off while User B cancels the release. | F4: Both actions submitted simultaneously. | G4: Deterministic outcome. Cancellation takes precedence. | H4: Release cancelled — sign-off not applied. | I4: Regression · P2 | J4: Concurrency & Race Conditions
A5: EDGE-TC-04 | B5: Exactly at CAB deadline time | C5: E | D5: BV-Time | E5: CAB deadline is 5:00 PM exactly. | F5: Submit at exactly 5:00:00 PM. | G5: Accepted (at boundary). | H5: — | I5: Regression · P2 | J5: Boundary Values - Time
A6: EDGE-TC-05 | B6: One second past CAB deadline | C6: N | D6: BV-Time | E6: CAB deadline is 5:00 PM exactly. | F6: Submit at 5:00:01 PM. | G6: Blocked. Past deadline. | H6: CAB submission deadline has passed. | I6: Regression · P2 | J6: Boundary Values - Time
A7: EDGE-TC-06 | B7: Deploy window ends at midnight boundary | C7: E | D7: BV-Time | E7: Deploy window ends at 23:59:59. | F7: Complete deployment at 23:59:59. | G7: Accepted (at boundary). | H7: — | I7: Regression · P2 | J7: Boundary Values - Time
A8: EDGE-TC-07 | B8: Release spanning year boundary | C8: E | D8: BV-Date | E8: Release starts 31 Dec, ends 2 Jan. | F8: Save release dates. | G8: Accepted. Duration calculated correctly across year. | H8: — | I8: Regression · P2 | J8: Boundary Values - Date
A9: EDGE-TC-08 | B9: Leap year date handling (29 Feb) | C9: E | D9: BV-Date | E9: Release scheduled for 29 Feb in a leap year. | F9: Save release. | G9: Accepted. Date stored correctly. | H9: — | I9: Regression · P2 | J9: Boundary Values - Date
A10: EDGE-TC-09 | B10: Partial save failure recovery | C10: E | D10: Error Recovery | E10: Save operation fails mid-way (e.g., network drop). | F10: Network restored. User retries save. | G10: Previous partial changes rolled back. Clean save allowed. | H10: Previous save failed — changes rolled back. Please save again. | I10: Regression · P1 | J10: Error Recovery
A11: EDGE-TC-10 | B11: Sync job failure does not corrupt data | C11: E | D11: Error Recovery | E11: External sync job fails during data import. | F11: Admin restarts sync. | G11: No duplicate records. Sync resumes from checkpoint. | H11: Sync resumed from last checkpoint. | I11: Regression · P1 | J11: Error Recovery
A12: EDGE-TC-11 | B12: Recovery from database timeout | C12: E | D12: Error Recovery | E12: Database times out during read operation. | F12: User refreshes page. | G12: Page loads with latest data. No stale cache. | H12: — | I12: Regression · P2 | J12: Error Recovery
... A31: EDGE-TC-30 | B31: API backward compatibility | C31: E | D31: API | E31: Client uses deprecated API version. | F31: Make API call with old version. | G31: Request succeeds with deprecation warning. | H31: (warn) API version deprecated — upgrade by {date}. | I31: Regression · P2 | J31: API Edge Cases

Sheet Rule Gap Register
A1: RULE GAP & LOGIC DECISION REGISTER
A2: Central view of unresolved rule gaps and business-logic decisions collected from all workbook sheets. Update Owner and Status here; source locations identify the original item.
A4: Metric | B4: Count
A5: All Open Items | B5: =COUNTIF(RuleGapRegisterTable[Status],"Open") -> 0
A6: Rule Gaps | B6: =COUNTIF(RuleGapRegisterTable[Category],"Rule Gap") -> 35
A7: Logic Decisions | B7: =COUNTIF(RuleGapRegisterTable[Category],"Logic Decision") -> 28
A8: Minor Spec Gaps | B8: =COUNTIF(RuleGapRegisterTable[Category],"Minor Spec Gap") -> 6
A9: ID Gaps | B9: =COUNTIF(RuleGapRegisterTable[Category],"ID Gap") -> 1
K10: Resolution / FI Ref
A11: Category | B11: Source Location | C11: Record / Test ID | D11: Title / Condition | E11: Current Rule Ref | F11: Finding / Decision Needed | G11: Priority | H11: Owner | I11: Status | J11: My Comments | K11: Column1
A12: ID Gap | B12: Incident Test Suite!K164 | C12: INC-TC-165 | D12: Rapid status transitions (state machine stress) | E12: Status Lifecycle | F12: [ID GAP] INC-TC-164 is missing; sequence jumps from INC-TC-163 to INC-TC-165. | G12: P2 | I12: Closed | J12: Ignore this
A13: Logic Decision | B13: Alerts Test Suite!K85 | C13: ALT-TC-084 | D13: Critical drift auto-escalates | E13: AV-13 | F13: [CONFIRM] Critical drift "auto-escalates" — same tension as the Drift suite: the lifecycle reaches Escalated only from Investigating (Detected→Escalated is invalid per TC-076). Reconcile a sanctioned system auto-escalate path. | G13: P1 | I13: Closed
A14: Logic Decision | B14: Blockers Test Suite!K46 | C14: BLK-TC-045 | D14: Open blocker blocks UAT transition | E14: AV-01, VR-15 | F14: [CONFIRM] "Open blocker blocks UAT transition" — no transition rule gates Testing→UAT on blockers. AV-01 is a nightly background auto-block, and VR-15 is Ready-specific. Confirm whether the UAT transition is actually blocker-gated. | G14: P1 | I14: Closed | K14: Resolved by FI-11 — VR-15 now WARN+override; blocker gating uses Impact (Advisory/Blocking) per CFG-05.
A15: Logic Decision | B15: Blockers Test Suite!K67 | C15: BLK-TC-066 | D15: Blockers lock when release reaches Deploying | E15: VR-35 | F15: [CONFIRM] VR-35 only prevents new blocker CREATION after Deploying. Making existing blockers read-only at Deploying (this test) extends the rule. Confirm intended. | G15: P1 | I15: Closed | K15: FI-11 decision — VR-35 kept HARD (blocker creation lock); existing-blocker read-only at Deploying is a deliberate deployment-integrity lock. Confirmed intended.
A16: Logic Decision | B16: CAB Approvals Test Suite!K38 | C16: CAB-TC-037 | D16: CAB Date in past (blocked) | E16: VR-03 | F16: [CONFIRM] "CAB Date cannot be in past" cites VR-03, but VR-03 only requires CAB before Go-Live. No rule blocks a past CAB Date. Add a rule or fix the citation. | G16: P1 | I16: Closed | K16: Resolved — VR-03 updated: a past CAB Date now triggers a WARNING (not a block), matching VR-04's back-dated Start Date precedent; RM must enter a reason to proceed.
A17: Logic Decision | B17: Conflicts Test Suite!K68 | C17: CON-TC-067 | D17: Booking creates conflict record on overlap attempt | E17: CASC-07 | F17: [CONFIRM] Env double-booking behaviour is inconsistent across the suite: some tests BLOCK the booking (AV-07: TC-054, TC-060–064), others ALLOW it and auto-create a Conflict record (CASC-07: this test, TC-089). AV-07 and CASC-07 themselves conflict. Decide block vs allow-with-record. | G17: P1 | I17: Closed | K17: Resolved — AV-07 softened to match CASC-07: an overlapping booking is now ALLOWED and a Conflict record is auto-created for review, rather than blocked. The two rules no longer conflict.
A18: Logic Decision | B18: Dependencies Test Suite!K15 | C18: DEP-TC-014 | D18: Dependency on Closed release allowed | E18: Entity | F18: [CONFIRM] Met is system-assigned here (predecessor already Deployed/Closed). Make explicit to avoid apparent conflict with DEP-TC-047 (cannot manually create Met). | G18: P1 | I18: Closed | K18: Resolved — AV-04 clarified: Met is always system-assigned, whether the predecessor was already Deployed/Closed at creation (this case) or becomes so later. Never user-settable.
A19: Logic Decision | B19: Dependencies Test Suite!K16 | C19: DEP-TC-015 | D19: Dependency on Deployed release allowed | E19: Entity | F19: [CONFIRM] Met is system-assigned here (predecessor already Deployed). Same note as DEP-TC-015. | G19: P1 | I19: Closed | K19: Resolved — same clarification as DEP-TC-014 (AV-04): Met is always system-assigned.
A20: Logic Decision | B20: Dependencies Test Suite!K48 | C20: DEP-TC-047 | D20: Cannot manually create Met dependency | E20: Entity | F20: [CONFIRM] Cross-ref DEP-TC-015/016: distinguish user-set Met (blocked, this test) vs system-set Met (allowed). | G20: P1 | I20: Closed | K20: Resolved — AV-04 clarified: user-set Met is correctly blocked (this test stands); system-set Met (on creation or predecessor deploy) is the only path.
A21: Logic Decision | B21: Dependencies Test Suite!K78 | C21: DEP-TC-077 | D21: Cannot waive dependency at Deploying | E21: VR-36 | F21: [CONFIRM] VR-36 literally freezes add/remove only. Blocking a WAIVE extends the rule. Confirm the product actually locks waivers at Deploying. | G21: P1 | I21: Closed | K21: FI-11 decision — VR-36 (dependency modification lock) kept HARD; waive lock at Deploying is intended.
A22: Logic Decision | B22: Dependencies Test Suite!K87 | C22: DEP-TC-086 | D22: At Risk transition still allowed when locked | E22: VR-36 | F22: [CONFIRM] VR-36 extension: blocks At Risk transition when locked. Confirm intent (rule text covers add/remove only). | G22: P2 | I22: Closed | K22: FI-11 decision — VR-36 kept HARD; At Risk transition lock at Deploying is intended.
A23: Logic Decision | B23: Dependencies Test Suite!K88 | C23: DEP-TC-087 | D23: Notes editing blocked when locked | E23: VR-36 | F23: [CONFIRM] VR-36 extension: blocks notes editing when locked. Confirm intent (rule text covers add/remove only). | G23: P2 | I23: Closed | K23: FI-11 decision — VR-36 kept HARD; notes-edit lock at Deploying is intended.
A24: Logic Decision | B24: Drift Test Suite!K66 | C24: DFT-TC-065 | D24: Baseline established after successful deployment | E24: Baseline | F24: [CONFIRM] The Baseline Management section (TC-065–080) has no governing rule in the spec — establish/update/lock/mask-secrets/rollback behaviours are all unbacked (cited only as "Baseline"). Add baseline rules or mark these as design assumptions. | G24: P1 | I24: Closed | K24: Resolved — added DRIFT-01 (Baseline Establishment & Management), formalising establish/update/lock/revert/mask-secrets behaviour.
A25: Logic Decision | B25: Incident Test Suite!K101 | C25: INC-TC-101 | D25: PIR required for Critical incidents | E25: VR-34 (analog) | F25: [CONFIRM] The whole PIR section is built on "VR-34 (analog)". VR-34 governs RELEASE closure (Large or Rolled Back), not incidents. No incident-PIR rule exists — the triggers (Critical, >4-hr outage), 5-business-day completion, and manager approval are all invented. Add incident-PIR rules or mark as design assumptions. | G25: P1 | I25: Closed | K25: Resolved — added VR-38 (Incident Post-Implementation Review): Critical incidents with an outage over a configurable threshold require PIR before Closed, with a configurable completion window; now WARN+override, not invented-and-unbacked.
... A57: Rule Gap | B57: Incident Test Suite!K9 | C57: INC-TC-009 | D57: Incident Description minimum length (10 chars) | E57: RULE GAP | F57: [RULE GAP] §1-12 is absent from Rules Specification; define/remap incident minimum description length. | G57: P2 | I57: Closed | K57: Resolved — §1-16: Description minimum length is 10 characters (configurable).
A58: Rule Gap | B58: Release Fields!C57 | C58: Blocker | D58: Release Status ≥ Deploying | E58: RULE GAP | F58: No current rule makes all existing blockers read-only at Deploying; VR-35 only blocks new blocker creation. | I58: Closed | K58: Resolved — added VR-39 (Deployment-Time Lock Extension): existing Blockers become read-only from Ready onward, a deliberate deployment-integrity lock, not overridable — matching the VR-35/36 precedent.
A59: Rule Gap | B59: Release Fields!C64 | C59: Risk | D59: Mitigation = Complete | E59: RULE GAP | F59: No current rule prevents a completed risk mitigation from being reversed. | I59: Closed | K59: Resolved — VR-27 amended: a completed Mitigation CAN be reversed by the Risk Owner/RM with a mandatory reason — flexible (WARN), not a hard lock, since no audit fact prevents reconsideration.
A60: Rule Gap | B60: Release Fields!C68 | C60: Conflict | D60: Release Status ≥ Deploying | E60: RULE GAP | F60: No current rule makes all conflict records read-only once deployment starts. | I60: Closed | K60: Resolved — VR-39 also covers Conflict records: read-only from Ready onward, deployment-integrity lock, not overridable.
A61: Rule Gap | B61: Release Fields!C70 | C61: Environment Booking | D61: Booking confirmed | E61: RULE GAP | F61: No current rule makes a confirmed booking immutable; ROLE-03 only governs override/cancellation authority. | I61: Closed | K61: Resolved — decision: a confirmed booking stays reschedulable with a warning (AV-07/CASC-08 already handle overlap detection and conflict auto-resolution on date change) — flexible by default, not a hard immutability rule.
A62: Rule Gap | B62: Release Fields!C71 | C62: Work Item (Jira/ServiceNow) | D62: Release Status ≥ Ready | E62: RULE GAP | F62: No current rule freezes work-item linkages at Ready; VR-28/29 only require completion. | I62: Closed | K62: Resolved — VR-39 also covers Work Item links: frozen (no new links, no unlinking) from Ready onward, deployment-integrity lock, not overridable.
A63: Rule Gap | B63: Release Fields!D106 | C63: Deployed | D63: Validation | E63: RULE GAP | F63: Post-deployment validation is not defined by a current VR rule. | I63: Closed | K63: Resolved — decision: no new hard-blocking rule; post-deployment validation is covered by VR-33 (open incidents block closure) and VR-34 (PIR before closure), both already WARN+override — no separate mandatory checklist rule needed.
A64: Rule Gap | B64: Release Fields!D117 | C64: Business Sign-Off | D64: Yes (if required) | E64: RULE GAP | F64: No current rule makes Business Sign-Off mandatory before Pending CAB. | I64: Closed | K64: Resolved by NR-01: sign-off types configurable per org (default Dev/Test/UAT mandatory).
A65: Rule Gap | B65: Release Fields!D80 | C65: Testing | D65: Field | E65: RULE GAP | F65: Start Date is required before Testing, but no explicit rule currently defines this gate. | I65: Closed | K65: Resolved — §1-04 amended: Start Date is now explicitly required before transitioning to Testing, alongside the existing Size-before-Planning requirement.
A66: Rule Gap | B66: Release Fields!D83 | C66: UAT | D66: Impediment | E66: RULE GAP | F66: No direct rule blocks Testing → UAT for an open blocker; AV-01 is a nightly auto-block check. | I66: Closed | K66: Resolved by FI-11 — VR-15 softened to WARN+override; only Blocking-impact blockers gate Testing→UAT (CFG-05).
A67: Rule Gap | B67: Release Fields!D90 | C67: Pending CAB | D67: Risk | E67: RULE GAP | F67: VR-27 requires mitigation before Ready, not before Pending CAB. | I67: Closed | K67: Resolved — VR-27 amended: an earlier, non-blocking warning is now shown at Pending CAB if a High risk lacks mitigation, ahead of the existing (now WARN+override) Ready-stage requirement.
A68: Rule Gap | B68: Release Test Suite!K201 | C68: REL-TC-200 | D68: Critical risk notification | E68: RULE GAP | F68: [RULE GAP] Critical-risk immediate notification is not defined by NOTIF-01–16; AV-02 covers unmitigated High risks after 3 days. | G68: P1 | I68: Closed | K68: Resolved by NR-02: covered by AV-02 risk escalation; no dedicated critical-risk rule.
A69: Rule Gap | B69: Release Test Suite!K202 | C69: REL-TC-201 | D69: Deployment started notification | E69: RULE GAP | F69: [RULE GAP] Deployment-start notification is not defined by NOTIF-01–16. | G69: P1 | I69: Closed | K69: Resolved by NR-02: covered by NOTIF-01 status-change; no dedicated deployment rule.
A70: Rule Gap | B70: Release Test Suite!K222 | C70: REL-TC-221 | D70: Polling fallback when webhook unavailable | E70: RULE GAP | F70: [RULE GAP] Five-minute polling fallback when webhooks are unavailable is not defined by SYNC-01–12. | G70: P2 | I70: Closed | K70: Resolved — added SYNC-13 (Polling Fallback): 5-minute polling when webhooks are unavailable, configurable interval.
A71: Rule Gap | B71: Release Test Suite!K231 | C71: REL-TC-230 | D71: Sync admin can trigger manual sync | E71: RULE GAP | F71: [RULE GAP] Manual sync permission/behavior is not defined; ROLE-04 governs cascade delete, not sync administration. | G71: P2 | I71: Closed | K71: Resolved — added ROLE-14 (Sync Administration): only Sync Administrators may manually trigger an out-of-cycle sync.
A72: Rule Gap | B72: Release Test Suite!K232 | C72: REL-TC-231 | D72: Sync disabled for archived releases | E72: RULE GAP | F72: [RULE GAP] Skipping sync for archived releases is not defined by SYNC-01–12. | G72: P3 | I72: Closed | K72: Resolved — added SYNC-14 (Sync Suspended for Archived Releases): archived releases are excluded from ongoing sync polling.
A73: Rule Gap | B73: Release Test Suite!K234 | C73: REL-TC-233 | D73: Release Manager can edit all releases in scope | E73: RULE GAP | F73: [RULE GAP] Release Manager app-scope edit authority is not defined by ROLE-01–11. | G73: P1 | I73: Closed | K73: Resolved — added ROLE-13 (Release Manager App-Scope Edit Authority): RM can edit releases within their assigned Application scope; outside it requires Admin.
A74: Rule Gap | B74: Release Test Suite!K240 | C74: REL-TC-239 | D74: Sync Admin can trigger manual sync | E74: RULE GAP | F74: [RULE GAP] Sync Admin manual-trigger permission is not defined; ROLE-04 governs cascade delete. | G74: P2 | I74: Closed | K74: Resolved — duplicate of REL-TC-230; same fix, ROLE-14 (Sync Administration).
A75: Rule Gap | B75: Release Test Suite!K254 | C75: REL-TC-253 | D75: Rollback increments version/attempt counter | E75: RULE GAP | F75: [RULE GAP] Rollback attempt/version counter is not defined; §2-03 governs Duration Days. | G75: P2 | I75: Closed | K75: Resolved — decision: rollback attempt/version counter is a minor UI/reporting detail, not a rule — tracked as a computed display field alongside §2-03 (Duration Days); no new rule required.
A76: Rule Gap | B76: Release Test Suite!K274 | C76: REL-TC-273 | D76: File upload validation | E76: RULE GAP | F76: [RULE GAP] File-upload type validation is not defined by SEC-01–12; prior SEC-12 is Encryption in Transit. | G76: P1 | I76: Closed | K76: Resolved — added SEC-13 (File Upload Validation): file type/size validated on upload, hard block if disallowed.
A77: Rule Gap | B77: Release Test Suite!K277 | C77: REL-TC-276 | D77: Authorization checked on every request | E77: RULE GAP | F77: [RULE GAP] Per-request object-level authorization is not explicitly defined by SEC-01–12. | G77: P1 | I77: Closed | K77: Resolved — added SEC-14 (Per-Request Authorization): every request checks current permissions, not cached from login.
A78: Rule Gap | B78: Release Test Suite!K278 | C78: REL-TC-277 | D78: Multi-factor authentication enforcement | E78: RULE GAP | F78: [RULE GAP] MFA enforcement is not defined by SEC-01–12. | G78: P1 | I78: Closed | K78: Resolved — added SEC-15 (Multi-Factor Authentication): enforced for all logins, configurable minimum for Admin/CCB.
A79: Rule Gap | B79: Release Test Suite!K279 | C79: REL-TC-278 | D79: API token expiry and rotation | E79: RULE GAP | F79: [RULE GAP] API token 90-day expiry/rotation is not defined; SEC-09 only covers API authentication. | G79: P2 | I79: Closed | K79: Resolved — added SEC-16 (API Token Expiry & Rotation): 90-day expiry, configurable, rejected on use if expired.
... A81: Rule Gap | B81: Release Test Suite!K9 | C81: REL-TC-008 | D81: Verify Release ID is auto-generated and read-only | E81: RULE GAP | F81: [RULE GAP] Release ID generation/read-only behavior has no explicit rule ID; §2-04 is Created Date. | G81: P1 | I81: Closed | K81: Resolved — added §2-14 (Release ID): auto-generated at creation, read-only, matching the §2 computed-field pattern.

Sheet Rules Specification
A1: RELEASE MANAGEMENT RULES SPECIFICATION - COMPLETE REFERENCE
A2: This document is self-contained. All referenced entities, statuses, and relationships are defined in companion sheets.
A4: COMPANION SHEETS - Quick Reference
A5: Sheet | B5: Contents | C5: Use When...
A6: Entity Classification | B6: All 36 system entities with classifications (TXN, REF, OPS, AUD, DRV, CFG), lifecycles, key fields | C6: You need to know what entities exist, their relationships, or which have status lifecycles
A7: Reference Data | B7: Status codes, release sizes, priorities, environments, risk scoring matrix, departments, approval types | C7: You need valid values for picklists, thresholds, or classification options
A8: Status Lifecycles | B8: Complete state machines for Releases, Blockers, Approvals, Sign-Offs, Risks, Incidents, Dependencies, Conflicts, Drift, Alerts | C8: You need to understand allowed transitions, gate requirements, or cascade effects
A9: Release Fields | B9: Field lock matrix (45 fields by status), related entity locks, progression blockers, enablers | C9: You need to know which fields lock at each status, what blocks transitions, or enabler requirements
A10: RULE ID LEGEND
A11: Prefix | B11: Category | C11: Count | D11: Description | E11: Primary Entity
A12: §1-xx | C12: 17 | D12: Input validation, required fields, format rules | E12: All entities
A13: §2-xx | B13: Read-Only Fields | C13: 14 | D13: Computed/system-managed fields that cannot be edited | E13: All entities
A14: §3-xx | B14: Field Locks | C14: 23 | D14: Status-based field locking (immutability rules) | E14: Releases, Approvals
A15: §4-xx | B15: Status Transitions | C15: 16 | D15: Allowed state changes in release lifecycle | E15: Releases
A16: VR-xx | B16: Validation Rules | C16: 37 | D16: User-triggered validations (real-time checks) | E16: Releases, Blockers, Risks
A17: AV-xx | B17: Auto-Validation | C17: 26 | D17: Background/scheduled system checks | E17: All entities
A18: ROLE-xx | B18: Permissions | C18: 14 | D18: Role-based access control rules | E18: Users, Roles
A19: CASC-xx | B19: Cascades | C19: 14 | D19: Cross-entity relationship rules and propagation | E19: All entities
A20: SYNC-xx | B20: Integration | C20: 14 | D20: External system sync rules (Jira, ServiceNow) | E20: External Systems
A21: AUDIT-xx | B21: Audit/Compliance | C21: 10 | D21: Traceability, retention, compliance requirements | E21: Audit Trail
A22: NOTIF-xx | B22: Notifications | C22: 17 | D22: Alert and communication trigger rules | E22: Users, Alerts
A23: SEC-xx | B23: Security | C23: 17 | D23: Input sanitization, authentication, encryption | E23: All entities
A24: OWN/LNK-xx | B24: Ownership & Linking | C24: 7 | D24: Origin-based ownership; entity link/unlink governance (FI-01, FI-08)
A25: CFG-xx | B25: Override & Configuration | C25: 7 | D25: Warn+override default, conscious-override friction, configurable severity, override audit, blocker impact gating (FI-11)
A26: CLONE-xx | B26: Release Cloning | C26: 2 | D26: Cloning a release (FI-13) or any terminal entity (CLONE-02) into a new record, with fresh Approvals/Sign-offs required for releases
A27: DRIFT-xx | B27: Baseline Management | C27: 1 | D27: Baseline establishment, update, lock, and revert behaviour for Drift
A28: WARN | B28: Soft Warning | C28: Operation allowed after acknowledgment | D28: Warning displayed; user can proceed after confirmation or entering reason
A29: AUTO | B29: Automatic | C29: System performs action without user input | D29: User notified of automated action; no action required
A30: ALLOW | B30: Permitted | C30: No restriction; explicitly permitted | D30: Normal operation; no special message
A31: KEY TERMS GLOSSARY
A32: Term | B32: Definition
A33: CAB (Change Advisory Board) | B33: A governance group that reviews and approves releases before deployment. Typically includes technical leads, business stakeholders, and management representatives.
A34: Release Manager (RM) | B34: The person responsible for managing a release from creation through deployment. Has authority to make decisions and is accountable for the release's success.
A35: Working Days | B35: Monday through Friday, excluding public holidays as defined in the system's holiday calendar. Used for calculating lead times and deadlines.
A36: Freeze Window | B36: A company-wide period during which deployments are restricted (e.g., year-end, major business events). Only Regulatory releases with VP exemption can deploy during freeze windows.
A37: Sign-Off | B37: Formal approval from a responsible party indicating their area is ready. Three types: Dev Sign-Off (development complete), Test Sign-Off (testing passed), UAT Sign-Off (user acceptance confirmed).
A38: Blocker | B38: An issue or obstacle that prevents a release from progressing. Must be resolved before the release can continue to the next stage.
A39: Rollback Plan | B39: A documented procedure for reversing a deployment if issues are discovered after go-live. Required for all releases before deployment.
A40: Dress Rehearsal | B40: A practice deployment performed in a pre-production environment to validate deployment procedures before actual go-live.
A41: Gate | B41: A checkpoint in the release lifecycle where specific requirements must be met before proceeding. Examples: sign-offs complete, no open blockers.
A42: Health Indicator | B42: A traffic-light status showing overall release health: GREEN Green (healthy), YELLOW Yellow (at risk), RED Red (critical issues).
A43: Cascade | B43: Automatic propagation of an action to related records. Example: cancelling a release unlinks all its child records; Approvals, Dependencies, and Sign-offs are also cancelled, while Blockers, Risks, and Alerts (external inputs) are only unlinked — never cancelled.
... A52: Audit Trail | B52: Immutable record of all changes made to a release, including who, what, and when. Cannot be edited or deleted.
A56: Rule ID | B56: Rule Name | C56: Description / Condition | D56: Trigger / When | E56: Action / Result | F56: Severity | G56: Overridable? | H56: Override Friction
A58: SECTION 1: STATUS TRANSITION RULES (§4)
A60: §4-01 | B60: Draft Allowed Transitions | C60: From Draft, the release may ONLY transition to: Planning OR Cancelled. No other transitions are permitted. | D60: User attempts status change from Draft | E60: Warn if target is off the recommended path; allow with reason (see CFG-07). Exception: cannot jump directly to Deploying/Deployed except via Ready (see CFG-06). | F60: WARN | G60: Yes | H60: Reason
A61: §4-02 | B61: Planning Allowed Transitions | C61: From Planning, the release may transition to: Testing, Blocked, OR Cancelled. | D61: User attempts status change from Planning | E61: Warn if target is off the recommended path; allow with reason (see CFG-07). Exception: cannot jump directly to Deploying/Deployed except via Ready (see CFG-06). | F61: WARN | G61: Yes | H61: Reason
A62: §4-03 | B62: Testing Allowed Transitions | C62: From Testing, the release may transition to: UAT, Blocked, OR Cancelled. CANNOT skip directly to Deploying. | D62: User attempts status change from Testing | E62: Warn if target is off the recommended path; allow with reason (see CFG-07). Exception: cannot jump directly to Deploying/Deployed except via Ready (see CFG-06). | F62: WARN | G62: Yes | H62: Reason
A63: §4-04 | B63: UAT Allowed Transitions | C63: From UAT, the release may transition to: Pending CAB (successful UAT), Testing (rework needed), Blocked, OR Cancelled. | D63: User attempts status change from UAT | E63: Warn if target is off the recommended path; allow with reason (see CFG-07). Exception: cannot jump directly to Deploying/Deployed except via Ready (see CFG-06). | F63: WARN | G63: Yes | H63: Reason
A64: §4-05 | B64: Pending CAB Allowed Transitions | C64: From Pending CAB, the release may transition to: CAB Approved, Deferred, Rejected, Blocked, OR Cancelled. | D64: CAB decision or user action | E64: Warn if target is off the recommended path; allow with reason + confirmation (see CFG-07). Exception: cannot jump directly to Deploying/Deployed except via Ready (see CFG-06). | F64: WARN | G64: Yes | H64: Reason + confirmation
A65: §4-06 | B65: CAB Approved Allowed Transitions | C65: From CAB Approved, the release may transition to: Ready, Pending CAB (scope change), Blocked, OR Cancelled. | D65: User attempts status change from CAB Approved | E65: Warn if target is off the recommended path; allow with reason + confirmation (see CFG-07). Exception: cannot jump directly to Deploying/Deployed except via Ready (see CFG-06). | F65: WARN | G65: Yes | H65: Reason + confirmation
A66: §4-07 | B66: Ready Allowed Transitions | C66: From Ready, the release may transition to: Deploying, Blocked, OR Cancelled. CANNOT skip directly to Deployed. | D66: User attempts status change from Ready | E66: Warn if target is off the recommended path; allow with reason (see CFG-07). Cannot skip Ready itself (see CFG-06). | F66: WARN | G66: Yes | H66: Reason
A67: §4-08 | B67: Deploying Allowed Transitions | C67: From Deploying, the release may transition to: Deployed, Rolled Back, OR Blocked. | D67: Deployment outcome | E67: Block if target is not Deployed, Rolled Back, or Blocked. No override — see CFG-06. | F67: BLOCK | G67: No | H67: — (no override)
A68: §4-09 | B68: Deployed Allowed Transitions | C68: From Deployed, the release may transition to: Closed, Rolled Back. | D68: Post-deployment action | E68: Block if target is not Closed or Rolled Back. No override — see CFG-06. | F68: BLOCK | G68: No | H68: — (no override)
A69: §4-10 | B69: Rolled Back Rework Path | C69: From Rolled Back, the release re-enters Testing for rework. Requires root cause documentation. | D69: User initiates rework | E69: Warn if target is off the recommended path; allow with reason (see CFG-07). | F69: WARN | G69: Yes | H69: Reason
A70: §4-11 | B70: Deferred Reactivation | C70: From Deferred, the release may be reactivated to Pending CAB or Cancelled. | D70: User reactivates deferred release | E70: Warn if target is off the recommended path; allow with reason (see CFG-07). | F70: WARN | G70: Yes | H70: Reason
A71: §4-12 | B71: Rejected Rework Path | C71: From Rejected, the release must return to Planning for rework. All gate fields are re-opened for editing. | D71: User initiates rework | E71: Warn if target is off the recommended path; allow with reason (see CFG-07). | F71: WARN | G71: Yes | H71: Reason
A72: §4-13 | B72: Blocked Resolution | C72: From Blocked, the release may return to its previous status OR transition to Cancelled. | D72: Blocker resolved or cancelled | E72: Warn if target is off the recommended path; allow with reason (see CFG-07). | F72: WARN | G72: Yes | H72: Reason
A73: §4-14 | B73: Closed Terminal State | C73: Closed is a terminal state. No further transitions are allowed. Record becomes immutable. | D73: Any attempted transition | E73: Block all transitions; record is read-only | F73: BLOCK
A74: §4-15 | B74: Cancelled Terminal State | C74: Cancelled is a terminal state. No further transitions are allowed. | D74: Any attempted transition | E74: Block all transitions | F74: BLOCK
A75: §4-16 | B75: No Stage Skipping | C75: Releases are RECOMMENDED to traverse the full path (Draft → Planning → Testing → UAT → Pending CAB → CAB Approved → Ready → Deploying → Deployed → Closed), and skipping intermediate stages now only warns and requires a reason (see CFG-07) rather than being blocked — provided each stage's own gate (sign-offs, CAB approval, dependency completion, etc.) is either met or consciously overridden along the way. The ONE exception is CFG-06: a release can never jump directly to Deploying or Deployed except from Ready — that specific stage-skip remains a hard block with no override, because Ready's own gate (rollback plan, checklist, no open impediments) is the last safety check before code goes live. | D75: User attempts to skip stages in the release lifecycle | E75: Warn; allow with reason, except direct jump to Deploying/Deployed bypassing Ready (blocked, see CFG-06) | F75: WARN | G75: Yes | H75: Reason (blocked entirely if the target is Deploying/Deployed and Ready was skipped)
A77: SECTION 2: VALIDATION RULES (VR) - User-Triggered Validations
A79: VR-01 | B79: End Date After Start Date | C79: End Date MUST be on or after Start Date. If End Date < Start Date, block save with inline error. | D79: User saves release with dates | E79: Block save; show: 'End Date cannot be before Start Date' | F79: BLOCK
A80: VR-02 | B80: CAB Lead Time by Size | C80: CAB Date must be at least a minimum number of working days (Monday-Friday, excluding public holidays) before Go-Live Date. Minimum lead time by release size: Small = 2 working days, Medium = 2 working days, Large = 3 working days. | D80: User sets CAB Date | E80: Warn if insufficient lead time; RM may override with audited reason | F80: WARN | G80: Yes | H80: Reason
A81: VR-03 | B81: CAB Before Go-Live | C81: CAB Date MUST be before Go-Live Date. CAB cannot occur after deployment begins. A CAB Date in the past triggers a WARNING (not a block), similar to VR-04's back-dated Start Date handling — the RM must enter a reason to proceed. | D81: User sets CAB Date | E81: Block save; show: 'CAB must be before Go-Live' | F81: BLOCK
A82: VR-04 | B82: Back-Dated Start Date | C82: If Start Date is in the past, display WARNING. Save allowed only after user enters a reason. Reason logged to audit. | D82: User sets past Start Date | E82: Warn; require reason to proceed | F82: WARN
A83: VR-05 | B83: Deploy in Freeze Window | C83: Deployment dates falling within a Freeze Window (company-wide no-deployment periods, typically year-end or major events) are BLOCKED unless BOTH conditions are met: (1) Release is marked as Regulatory (mandatory compliance release), AND (2) A VP-level exemption approval exists on record. | D83: User sets Deploy Date in freeze | E83: Block unless exemption; log approver if exemption used | F83: BLOCK
A84: VR-06 | B84: Go-Live Before End Date | C84: Go-Live Date MUST be on or before End Date. | D84: User sets Go-Live Date | E84: Block if Go-Live > End Date | F84: BLOCK
A85: VR-07 | B85: Deploy Date in Release Window | C85: Deploy Date must fall within Start Date to End Date range. | D85: User sets Deploy Date | E85: Block if outside release window | F85: BLOCK
A86: VR-10 | B86: Owner On Leave During Release | C86: If assigned Release Owner is on approved leave during the release window (Start to End), display WARNING. Suggest backup owner. | D86: User assigns owner | E86: Warn; suggest backup owner | F86: WARN
A87: VR-11 | B87: Approver On Leave at CAB | C87: If required CAB approver is on leave at CAB Date, display WARNING. Suggest delegate approver. Organisations may optionally designate approvers as Required or Optional; only Required-approver leave triggers this warning. | D87: User sets CAB Date or approver | E87: Warn; suggest delegate approver | F87: WARN
A88: VR-12 | B88: Environment Owner On Leave | C88: If environment owner is on leave during booked slot, display WARNING. Suggest escalation contact. This is a flat WARNING by default; organisations may optionally configure severity scaling by leave duration or type via CFG-03. | D88: User books environment | E88: Warn; suggest escalation contact | F88: WARN
A89: VR-13 | B89: Incident Owner Unassigned | C89: If an incident has Severity = Critical and no owner assigned, escalate immediately. | D89: Incident saved without owner | E89: Auto-escalate to default owner | F89: WARN
A90: VR-14 | B90: Sign-Off Gate Requirements | C90: Before transitioning to Pending CAB, all sign-offs configured as MANDATORY must be 'Yes'. Available sign-off types: Dev, Test, UAT, Security, Business, Ops. Default mandatory set = Dev, Test, UAT; each organisation may make Security, Business or Ops mandatory or optional (configurable per CFG-03). A missing mandatory sign-off warns and is overridable (see FI-11). | D90: User moves to Pending CAB | E90: Warn; list missing sign-offs; RM may override with reason + confirmation | F90: WARN | G90: Yes | H90: Reason + confirmation
A91: VR-15 | B91: Blocker Before Ready | C91: If ANY active blocker exists (Status ≠ Resolved/Closed), transition to Ready is BLOCKED. | D91: User moves to Ready | E91: Warn; list active blockers; RM may override with audited reason | F91: WARN | G91: Yes | H91: Reason
A92: VR-16 | B92: Ready Gate Check | C92: Transition to Ready requires ALL of the following: (1) Rollback Plan field = 'Ready' (documented plan to reverse deployment), (2) Deployment Checklist = 'Complete' (all pre-deployment tasks verified), (3) No open impediments (unresolved blockers, unmet dependencies, or active conflicts). | D92: User moves to Ready | E92: Warn if a gate requirement is missing; RM may override with reason + confirmation | F92: WARN | G92: Yes | H92: Reason + confirmation
A93: VR-17 | B93: Readiness Threshold Check | C93: If the computed Readiness Percentage is below 75% and the CAB Date is within 2 days, display a WARNING to the Release Manager (RM) showing a list of gaps (incomplete sign-offs, open blockers, unmet dependencies, missing checklist items). | D93: System T-minus check | E93: Warn; surface gap list to RM | F93: WARN
A94: VR-18 | B94: Dependency Completion | C94: All releases marked as dependencies with Dependency Type = 'Hard' (must-have, blocking) must have reached Deployed or Closed status before this release can transition to Deploying. 'Soft' dependencies (nice-to-have) do not block. See Reference Data sheet for dependency type definitions. | D94: User moves to Deploying | E94: Warn if hard dependencies incomplete; RM may override with reason + confirmation | F94: WARN | G94: Yes | H94: Reason + confirmation
A95: VR-19 | B95: Environment Availability | C95: Cannot transition to Deploying unless a booked environment slot exists for Deploy Date. | D95: User moves to Deploying | E95: Block; require environment booking | F95: BLOCK
A96: VR-20 | B96: Conflict Window Check | C96: If the release Deploy Date overlaps with a conflicting release's deploy window (same app or environment), display WARNING. | D96: User sets Deploy Date | E96: Warn; show conflicting release(s) | F96: WARN
A97: VR-21 | B97: Scope Change After CAB Approved | C97: If any scope-affecting field (Priority, Size, or Scope text field) is changed while the release Status = CAB Approved, the system automatically reverts the status back to Pending CAB and sends a notification to CAB members that re-approval is required. | D97: User edits scope-affecting field | E97: Auto-revert status; notify CAB | F97: WARN
A98: VR-22 | B98: Scope Change Lock After Deploying | C98: Once Status = Deploying, scope fields (Priority, Size, Scope) become read-only. | D98: User attempts edit after Deploying | E98: Block field edit | F98: BLOCK
A99: VR-23 | B99: Duplicate Release Name | C99: Release names must be unique within the same Application. Duplicate names trigger WARNING with option to link or rename. | D99: User saves duplicate name | E99: Warn; prompt to rename or link | F99: WARN
A100: VR-24 | B100: CAB Submission Completeness | C100: Cannot transition to Pending CAB unless ALL of the following are complete: (1) All required sign-offs (Dev, Test, UAT) = 'Yes', (2) No open blockers (all blockers in Resolved or Closed status), (3) Minimum documentation present (Rollback Plan is not blank, Release Notes field is not blank). | D100: User moves to Pending CAB | E100: Warn; list incomplete items; RM may override with reason + confirmation | F100: WARN | G100: Yes | H100: Reason + confirmation
A101: VR-25 | B101: Concurrent Edit Protection | C101: If two users edit the same release at the same time and User B tries to save after User A has already saved changes, User B's save is blocked. The system shows what changed since User B loaded the record and requires User B to reload the page before making changes. | D101: Concurrent edit detected | E101: Block save; show diff; require reload | F101: BLOCK
A102: VR-26 | B102: Dress Rehearsal for Large Releases | C102: For releases with Size = Large, when transitioning to Ready status, if the Dress Rehearsal field is not set to 'Done', a WARNING is displayed (but transition is not blocked). A dress rehearsal is a practice deployment in a pre-production environment. Completing it before go-live is recommended but not mandatory. | D102: User moves Large release to Ready | E102: Warn; recommend completing rehearsal | F102: WARN
A103: VR-27 | B103: Risk Mitigation Required | C103: Risks with Severity = High MUST have a Mitigation Plan before release can transition to Ready (now WARN + override, per FI-11). An earlier, non-blocking WARNING is also shown at Pending CAB if a High-severity risk still lacks a mitigation plan, giving the RM advance notice before the Ready gate. A completed Mitigation may be reversed by the Risk Owner or RM with a mandatory reason if circumstances change (e.g. the control is later found ineffective) — this is a WARN, not a hard lock, since no audit or physical fact prevents reconsideration. | D103: User moves to Ready | E103: Warn if High risk lacks mitigation; RM may override with reason + confirmation | F103: WARN | G103: Yes | H103: Reason + confirmation
A104: VR-28 | B104: Work Items Complete Before Ready | C104: All work items (Jira tickets, ServiceNow tasks) linked to the release must have Status = Done or Closed before transitioning to Ready. Open work items indicate incomplete development. | D104: User moves to Ready | E104: Warn; list open work items; RM may override with reason + confirmation | F104: WARN | G104: Yes | H104: Reason + confirmation
A105: VR-29 | B105: Work Items Complete Before Deploying | C105: All linked work items must be Done/Closed before transitioning to Deploying. This is the final check before deployment begins. | D105: User moves to Deploying | E105: Warn; list incomplete work items; RM may override with reason + confirmation | F105: WARN | G105: Yes | H105: Reason + confirmation
A106: VR-30 | B106: Test Sign-Off Before UAT | C106: Test Sign-Off must be 'Yes' before a release can transition from Testing to UAT. Ensures testing phase is formally complete. | D106: User moves to UAT | E106: Warn; require test sign-off or override with audited reason | F106: WARN | G106: Yes | H106: Reason
A107: VR-31 | B107: Ops Sign-Off Before Ready | C107: Ops Sign-Off (operations readiness confirmation) must be 'Yes' before transitioning to Ready. Ensures infrastructure and support teams are prepared. | D107: User moves to Ready | E107: Warn; require ops sign-off or override with audited reason | F107: WARN | G107: Yes | H107: Reason
A108: VR-32 | B108: Unresolved Conflicts Block Ready | C108: If any Conflict record linked to the release has Status = Detected or Under Review (i.e., not Resolved or Dismissed), transition to Ready is blocked. Schedule conflicts must be addressed. | D108: User moves to Ready | E108: Warn; list open conflicts; RM may override with reason + confirmation | F108: WARN | G108: Yes | H108: Reason + confirmation
A109: VR-33 | B109: Open Incidents Block Closure | C109: Release cannot transition to Closed if any linked Incident has Status = Open. All post-deployment issues must be resolved or delinked. | D109: User moves to Closed | E109: Warn; list open incidents; RM may override with audited reason | F109: WARN | G109: Yes | H109: Reason
A110: VR-34 | B110: PIR Required Before Closure | C110: For releases with Size = Large or any release that was Rolled Back, Post-Implementation Review (PIR) field must be 'Complete' before transitioning to Closed. | D110: User moves to Closed | E110: Warn if PIR incomplete; RM may override with audited reason | F110: WARN | G110: Yes | H110: Reason
A111: VR-35 | B111: Blocker Creation Lock After Deploying | C111: New blockers cannot be created for a release once Status >= Deploying. Issues found during deployment should be logged as Incidents instead. | D111: User attempts to create blocker | E111: Block; suggest create Incident instead | F111: BLOCK
A112: VR-36 | B112: Dependency Modification Lock | C112: Dependency records cannot be added or removed once release Status >= Ready. Dependency structure is frozen for deployment. | D112: User attempts dependency change | E112: Block; dependencies frozen | F112: BLOCK
A113: VR-37 | B113: Security Sign-Off Required | C113: If the release affects security-sensitive systems (Security Flag = Yes), Security Sign-Off must be 'Yes' before transitioning to Pending CAB. | D113: User moves to Pending CAB | E113: Block if security-sensitive without sign-off | F113: BLOCK
A115: SECTION 3: AUTO-VALIDATION RULES (AV) - Background / Scheduled System Checks
C116: A scheduled job runs every night and scans all releases in Testing or UAT status. If ANY blocker linked to the release has a status other than Resolved or Closed, the system automatically sets the Release Status to Blocked and sends a notification to the Release Manager (the person assigned as Release Owner).
A117: AV-01 | B117: Open Blocker Detection | C117: Nightly job scans releases in Testing/UAT. If ANY linked blocker has Status ≠ Resolved/Closed, auto-set Release Status = Blocked. | D117: Nightly batch job | E117: Auto-set status to Blocked; notify RM | F117: AUTO
...

Sheet Entity Classification
A1: 📊 ENTITY CLASSIFICATION — Data Type Taxonomy
A2: Classification of all Release Desk entities by data behavior and lifecycle characteristics
A4: CLASSIFICATION LEGEND
A5: Code | B5: Full Name | C5: Description | D5: Characteristics | E5: Examples
A6: TXN | B6: Transactional | C6: Records with workflow/state transitions requiring lifecycle management | D6: Status changes, approvals, escalations; Has defined lifecycle; Requires audit trail | E6: Releases, Incidents, Risks
A7: REF | B7: Reference/Master | C7: Lookup and master data tables for entity relationships | D7: Maintained by admins; Used as FK in other tables; Slow-changing dimension | E7: Applications, Users, Departments
A8: OPS | B8: Operational | C8: Day-to-day scheduling and resource management (CRUD without workflow) | D8: Create, Update, Delete; No workflow states; Time-bound records | E8: Env Bookings, Leave, Maintenance
A9: AUD | B9: Audit/Log | C9: Immutable system-generated records for compliance | D9: System-generated; Immutable after creation; Append-only | E9: Versions, Change History
A10: DRV | B10: Derived/Calculated | C10: Computed metrics displayed but not directly editable | D10: Formulas, aggregations, KPIs; Refreshed on demand | E10: Dashboard, Risk Scores
A11: CFG | B11: Configuration | C11: System settings and business rule definitions | D11: Admin-managed; Drives business rules; Version-controlled | E11: Risk Factors, Reference Data
A13: ENTITY CLASSIFICATION MATRIX
A14: Entity Name | B14: Classification | C14: Description | D14: Has Lifecycle | E14: Lifecycle Sheet | F14: Data Sheet | G14: Key Fields | H14: Related Rules | I14: Origin / System of Record | J14: Notes
A15: Releases | B15: TXN | C15: Core record tracking software releases through deployment lifecycle | D15: Yes | E15: LC_Releases | F15: Releases | G15: Release Name, Application, Status, Go-Live Date, Owner | H15: §4 Status Transitions, VR, AV rules | I15: Native — Release Desk | J15: Core workflow: Draft → Planning → Testing → UAT → Pending CAB → Approved → Deployed
A16: Blockers | B16: TXN | C16: Issues preventing release progress | D16: Yes | E16: LC_Blockers | F16: Blockers | G16: Description, Severity, Status, Owner, Release Link, Impact (Blocking/Advisory), Origin (Native/External) | H16: VR-15, VR-16, AV-01, AV-03, CASC-01, CASC-02, CFG-05, OWN-01 | I16: Native (RD) or External (Jira) | J16: Impediment tracking: Open → In Progress → Resolved → Closed
A17: Incidents | B17: TXN | C17: Production issues linked to releases | D17: Yes | E17: LC_Incidents | F17: Incidents | G17: Reference, Severity, Status, Owner, Origin (Native/External) | H17: VR-13, §1-12, AV-06, CASC-03, ROLE-07 | I17: Native (RD) for an incident logged directly with no external ticketing system; External (ServiceNow/Jira) when incidents are managed there — linked and auto-synced, read-only in RD | J17: ITIL workflow: Active → Investigating → Resolved → Closed
A18: Approvals (CAB Approvals) | B18: TXN | C18: Any approval a release needs (a CAB decision, or any other approval such as a named security/legal/etc. approval), created by the user and tracked through the Approvals lifecycle. The CAB approval specifically may instead be linked to an external ticket (e.g. ServiceNow, Jira) when the organisation manages CAB there — in that case Release Desk reads the linked ticket's status rather than running its own lifecycle for it. | D18: Yes | E18: LC_Approvals | F18: Approvals | G18: Type, Decision, Approver, Release Link, External Reference (SoR ticket ID/URL when CAB-linked) | H18: VR-14, VR-24, ROLE-02, ROLE-09, §3-10, AV-22 | I18: Native (RD) for a manually-tracked approval (e.g. a named 'XYZ' approval with no external system); External (ServiceNow/Jira CAB ticket) when the organisation's CAB is managed in an external system — linked and auto-synced, no internal lifecycle needed for that record | J18: Immutable decisions: Pending → Approved/Rejected (FINAL)
A19: Sign-Offs | B19: TXN | C19: Stakeholder confirmations for release gates | D19: Yes | E19: LC_Sign-Offs | F19: Sign-Offs | G19: Type, Status, Signatory, Release Link, Origin (Native/External) | H19: VR-14, VR-24, ROLE-01, §3-05 | I19: Native (RD) for a sign-off tracked directly in Release Desk (the default); External when an organisation's formal sign-off process runs in another system (e.g. an e-signature/compliance tool) — linked and auto-synced, read-only in RD | J19: Pre-CAB approvals: Pending → Approved/Rejected (FINAL)
A20: Risks | B20: TXN | C20: Risk records associated with releases | D20: Yes | E20: LC_Risk | F20: Risks | G20: Description, Probability, Impact, Mitigation, Status | H20: VR-27, §1-10, §1-11, §2-08, AV-02 | I20: Native (RD) or External (GRC / risk tool) | J20: Risk workflow: Open → Mitigating → Accepted → Closed
A21: Dependencies | B21: TXN | C21: Inter-release dependency tracking | D21: Yes | E21: LC_Dependency | F21: Dependencies | G21: Type, Dependent Release, Status, Origin (Native/External) | H21: VR-18, AV-04, CASC-04, CASC-12 | I21: Native (RD) for a dependency between two releases tracked directly in Release Desk (the default); External when the dependency is on something tracked in another system (e.g. a third-party vendor delivery tracked in an external ticketing tool) — linked and auto-synced, read-only in RD | J21: Dependency tracking: Clear → At Risk → Blocked → Resolved
A22: Conflicts | B22: TXN | C22: Scheduling/resource conflicts between releases | D22: Yes | E22: LC_Conflict | F22: Conflicts | G22: Type, Conflicting Release, Status, Origin (Native/External) | H22: VR-20, AV-05, §2-07, CASC-07, CASC-08 | I22: Native (RD) for a conflict auto-detected by Release Desk itself (the default); External when conflict information is sourced from another scheduling/CMDB system — linked and auto-synced, read-only in RD | J22: Resource conflict: Open → In Progress → Resolved
A23: Alerts | B23: TXN | C23: System notifications and escalations | D23: Yes | E23: LC_Alerts | F23: Alerts | G23: Type, Severity, Status, Target User | H23: AV rules, Notification Throttling | I23: Native (RD-generated) or External (monitoring, e.g. Grafana) | J23: Monitoring workflow: Active → Acknowledged → Resolved
A24: Drift Records | B24: TXN | C24: Configuration drift detection records | D24: Yes | E24: LC_Drift | F24: Drift | G24: Baseline, Current, Delta, Status, Origin (Native/External) | H24: AV-13, AV-14 | I24: Native (RD) if Release Desk performs its own config scan; External (Terraform, Spacelift, AWS Config, etc.) when a dedicated IaC/CSPM tool is the source (recommended) — linked and auto-synced, read-only in RD | J24: Deviation tracking: Open → In Progress → Resolved → Closed
A25: Applications | B25: REF | C25: Master list of applications in release scope | D25: No | E25: N/A | F25: Applications | G25: App Name, Owner, Tier, Status | H25: §1-03, CASC-06 | I25: External — CMDB / config | J25: Master app registry by department/environment
A26: Users | B26: REF | C26: User profiles for assignment and permissions | D26: No | E26: N/A | F26: Users | G26: Name, Role, Department, Email | H26: ROLE rules, VR-10 to VR-13 | J26: User directory with roles and access levels
A27: Departments | B27: REF | C27: Organizational units | D27: No | E27: N/A | F27: Reference Data | G27: Department Name, Manager | H27: Reporting, escalation paths | J27: 8 departments (Finance, IT, HR, etc.)
A28: Environments | B28: REF | C28: Deployment target environments | D28: No | E28: N/A | F28: Reference Data | G28: Env Name, Type, Owner | H28: VR-19, ROLE-03, AV-07, AV-08 | J28: 6 environments (Dev → Prod → DR)
A29: Freeze Windows | B29: REF | C29: Deployment blackout periods | D29: No | E29: N/A | F29: — | G29: Start, End, Reason, Exemption Rules | H29: VR-05, AV-16, ROLE-05, CASC-11
A30: Release Managers | B30: REF | C30: Authorized release managers | D30: No | E30: N/A | F30: Release Managers
A31: Super Admins | B31: REF | C31: System administrators | D31: No | E31: N/A | F31: Super Admins
A32: Maintenance Windows | B32: OPS | C32: Scheduled maintenance periods | D32: No | E32: N/A | F32: Maintenance | G32: Start, End, Affected Systems | H32: AV-09, CASC-10 | J32: CRUD: Scheduled outage windows
A33: Environment Bookings | B33: OPS | C33: Time-slot reservations for environments | D33: No | E33: N/A | F33: Env Booking | G33: Environment, Release, Start, End | H33: §1-08, VR-19, AV-07, AV-08, ROLE-03 | J33: CRUD: Create/update/delete bookings; auto-conflict detection
A34: Leave Records | B34: OPS | C34: Staff absence tracking from HR sync | D34: No | E34: N/A | F34: Leave Calendar | G34: User, Start, End, Type | H34: VR-10 to VR-12, AV-12, CASC-09 | J34: CRUD: HR-managed staff availability
A35: Calendars (Calendar Events) | B35: OPS | C35: Release calendar and scheduling | D35: No | E35: N/A | F35: Calendar | G35: Date, Events, Conflicts | H35: Scheduling validations | J35: CRUD: CAB meetings, milestones display
A36: Checklists | B36: OPS | C36: Pre-deployment task lists | D36: No | E36: N/A | F36: — | G36: Task, Status, Owner | H36: VR-16, AV-20
A37: Audit Trail | B37: AUD | C37: Immutable log of all changes | D37: No | E37: Append-only | F37: — | G37: Timestamp, User, Action, Before, After | H37: §2-05, ROLE-08, AV-24
A38: Sync Logs | B38: AUD | C38: External system sync records | D38: No | E38: Append-only | F38: — | G38: Timestamp, System, Status, Details | H38: SYNC rules, AV-18, §2-09
A39: Versions | B39: AUD | C39: Auto-populated deployment version history | D39: No | E39: Append-only | F39: Versions | J39: Read-only: Auto-populated deployment history
A40: App Status | B40: AUD | C40: Point-in-time application health snapshots | D40: No | E40: Append-only | F40: App Status
A41: Release Health | B41: DRV | C41: Computed health indicator (GREEN/YELLOW/RED) | D41: No | E41: Computed | F41: — | G41: Based on: status, gates, conflicts, blockers, risks | H41: §2-01, AV-19
A42: Readiness % | B42: DRV | C42: Computed readiness percentage | D42: No | E42: Computed | F42: — | G42: Based on: sign-offs, blockers, dependencies, checklist | H42: §2-02, VR-17, AV-20
A43: Dashboard | B43: DRV | C43: KPIs and metrics aggregated from other sheets | D43: No | E43: Computed | F43: Dashboard
A44: Risk Scores | B44: DRV | C44: Calculated from Risk Factors weightings | D44: No | E44: Computed | F44: Risks (Score column)
A45: Validation Rules | B45: CFG | C45: Business rule definitions | D45: No | E45: N/A | F45: — | G45: Rule ID, Condition, Action, Severity | H45: Rules Specification sheet
A46: Field Permissions | B46: CFG | C46: Role-based field access control | D46: No | E46: N/A | F46: — | G46: Field, Role, Permission Level | H46: §3 Lock rules, ROLE rules
A47: Sync Mappings | B47: CFG | C47: External system field mappings | D47: No | E47: N/A | F47: — | G47: Local Field, External Field, Transform | H47: SYNC rules, AV-17
A48: Risk Factors | B48: CFG | C48: 44+ weighted factors for risk scoring | D48: No | E48: N/A | F48: Risk Factors
A49: Reference Data | B49: CFG | C49: Status codes, thresholds, lookups | D49: No | E49: N/A | F49: Reference Data
A50: Technical Specs | B50: CFG | C50: Data dictionary, FK/PK definitions | D50: No | E50: N/A | F50: Technical Specifications
A52: SUMMARY BY CLASSIFICATION
A53: Classification | B53: Count
A54: Transactional (TXN) | B54: =COUNTIF($B$15:$B$50,"TXN") -> 10
A55: Reference/Master (REF) | B55: =COUNTIF($B$15:$B$50,"REF") -> 7
A56: Operational (OPS) | B56: =COUNTIF($B$15:$B$50,"OPS") -> 5
A57: Audit/Log (AUD) | B57: =COUNTIF($B$15:$B$50,"AUD") -> 4
A58: Derived/Calculated (DRV) | B58: =COUNTIF($B$15:$B$50,"DRV") -> 4
A59: Configuration (CFG) | B59: =COUNTIF($B$15:$B$50,"CFG") -> 6
A60: TOTAL | B60: =SUM(B54:B59) -> 36
A62: Entity Classification (Merged) v1.0 | Data taxonomy for Release Desk | Consolidated: 06-Aug-2026

Sheet Reference Data
A1: RELEASE DESK — REFERENCE DATA CATALOG
A2: Consolidated lookup tables, status codes, thresholds, and configuration data (merged from Reference Data + Reference Data (2))
A3: Version 2.0 (Merged) | Consolidated: 06-Aug-2026
A5: WORKBOOK STATISTICS
A6: Metric | B6: Value | C6: Source
A7: Total Departments | B7: 8 | C7: Departments sheet
A8: Total Applications | B8: 84 | C8: Applications sheet
A9: Total Releases | B9: 80 | C9: Releases sheet
A10: Total Users | B10: 100+ | C10: Users, Release Managers, Super Admins
A11: Risk Factors | B11: 44-46 | C11: Risk Factors sheet
A13: 1. DEPARTMENTS
A14: Department Name
A15: Finance
A16: Logistics
A17: CRM
A18: Manufacturing
A19: IT
A20: HR
A21: Legal
A22: Security
A24: 2. ENVIRONMENTS
A25: Environment Name | B25: Code | C25: Legacy Code | D25: Description | E25: Availability | F25: Promotion Order | G25: Booking Required
A26: Development | B26: DEV | C26: DEV | D26: Developer sandbox environment | E26: 24/7 | F26: 1 | G26: No
A27: Testing | B27: TEST | C27: SIT | D27: QA and integration testing | E27: Business Hours | F27: 2 | G27: Yes
A28: User Acceptance | B28: UAT | C28: UAT | D28: Business validation environment | E28: Business Hours | F28: 3 | G28: Yes
A29: Pre-Production | B29: PREPROD | C29: STG | D29: Production mirror for final validation | E29: Business Hours | F29: 4 | G29: Yes
A30: Production | B30: PROD | C30: PRD | D30: Live production environment | E30: 24/7 | F30: 5 | G30: Yes (via Deploy Date)
A31: Disaster Recovery | B31: DR | C31: DR | D31: Business continuity failover | E31: 24/7 | F31: 6 | G31: Yes
A33: 3. RELEASE SIZES
A34: Size | B34: Code | C34: Test Days | D34: UAT Days | E34: Pre-Prod Days | F34: Total Lead Time | G34: Min CAB Lead Time | H34: Requirements | I34: Examples
A35: Small | B35: S | C35: 3 | D35: 2 | E35: 1 | F35: ~8 days | G35: 2 working days | H35: Standard sign-offs only | I35: Bug fixes, minor UI changes
A36: Medium | B36: M | C36: 5 | D36: 3 | E36: 2 | F36: ~12 days | G36: 2 working days | H36: Standard sign-offs + Business Review | I36: Feature enhancements, integrations
A37: Large | B37: L | C37: 10 | D37: 5 | E37: 4 | F37: ~22 days | G37: 3 working days | H37: All sign-offs + Dress Rehearsal recommended | I37: Major releases, platform upgrades
A39: 4. IMPACT LEVELS
A40: Level | B40: Code | C40: Description | D40: Examples
A41: High | B41: H | C41: Critical business impact | D41: Core ERP, Payment Systems
A42: Medium | B42: M | C42: Moderate impact, workarounds exist | D42: Reporting, Secondary CRM
A43: Low | B43: L | C43: Minimal impact, easily recoverable | D43: UI changes, Minor enhancements
A45: 5. PRIORITY LEVELS
A46: Priority | B46: Code | C46: Description | D46: Response Time | E46: Escalation | F46: SLA Notes
A47: Critical | B47: P1 | C47: Business-stopping issues, security breaches | D47: Immediate | E47: CIO/VP Level | F47: Expedited CAB review, exemption eligible
A48: High | B48: P2 | C48: Major degradation, customer impacting | D48: 4 hours | E48: Director Level | F48: Priority scheduling
A49: Medium | B49: P3 | C49: Important but not urgent issues | D49: 1 business day | E49: Manager Level | F49: Normal scheduling
A50: Low | B50: P4 | C50: Minor issues, enhancements | D50: 5 business days | E50: Standard | F50: Flexible scheduling
A52: 6. RELEASE STATUS CODES
A53: Status | B53: Type | C53: Description | D53: Allowed Transitions
A54: Draft | B54: Initial | C54: Initial state for new releases | D54: Planning, Cancelled
A55: Planning | B55: Active | C55: Release scope and planning phase | D55: Testing, Blocked, Cancelled
A56: Testing | B56: Active | C56: Development and integration testing | D56: UAT, Blocked, Cancelled
A57: UAT | B57: Active | C57: User acceptance testing phase | D57: Pending CAB, Testing, Blocked, Cancelled
A58: Pending CAB | B58: Gate | C58: Awaiting Change Advisory Board decision | D58: CAB Approved, Deferred, Rejected, Blocked, Cancelled
A59: CAB Approved | B59: Gate | C59: CAB approved, preparing for deployment | D59: Ready, Pending CAB (scope change), Blocked, Cancelled
A60: Ready | B60: Gate | C60: All gates passed, ready for deployment | D60: Deploying, Blocked, Cancelled
A61: Deploying | B61: Execution | C61: Active deployment in progress | D61: Deployed, Rolled Back, Blocked
A62: Deployed | B62: Execution | C62: Successfully deployed to production | D62: Closed, Rolled Back
A63: Closed | B63: Terminal | C63: Release complete - IMMUTABLE | D63: None (Terminal)
A64: Cancelled | B64: Terminal | C64: Release cancelled - IMMUTABLE | D64: None (Terminal)
... A68: Rejected | B68: Special | C68: CAB rejected - requires rework | D68: Planning (rework path)
A69: 7. RISK ASSESSMENT
A70: 7a. Risk Scoring Matrix (Probability × Impact Grid)
A71: Score Range | B71: Severity Level | C71: Color | D71: Required Action | E71: Approval Level
A72: 1-9 | B72: Low | C72: Green | D72: Standard deployment | E72: Release Manager
A73: 10-14 | B73: Medium | C73: Yellow | D73: Enhanced monitoring | E73: Release Manager
A74: 15-19 | B74: High | C74: Orange | D74: CAB review required — Requires Mitigation (VR-27) | E74: CAB
A75: 20-24 | B75: Critical | C75: Red | D75: Executive approval needed | E75: Director
A76: 25+ | B76: Severe | C76: Dark Red | D76: Immediate review required | E76: VP/CIO
A78: 7b. Risk Likelihood Scale (Probability axis)
A79: Level | B79: Score | C79: Description | D79: Probability
A80: Rare | B80: 1 | C80: Unlikely to occur in normal circumstances | D80: < 5%
A81: Unlikely | B81: 2 | C81: Could occur but not expected | D81: 5-25%
A82: Possible | B82: 3 | C82: May occur at some time | D82: 25-50%
A83: Likely | B83: 4 | C83: Will probably occur | D83: 50-75%
A84: Almost Certain | B84: 5 | C84: Expected to occur in most circumstances | D84: > 75%
A86: 7c. Risk Impact Scale (Impact axis)
A87: Level | B87: Score | C87: Description | D87: Business Impact
A88: Negligible | B88: 1 | C88: Minor inconvenience, no service impact | D88: < $10K
A89: Minor | B89: 2 | C89: Limited impact, workarounds available | D89: $10K-$100K
A90: Moderate | B90: 3 | C90: Significant impact, degraded service | D90: $100K-$500K
A91: Major | B91: 4 | C91: Major disruption, critical functions affected | D91: $500K-$1M
A92: Catastrophic | B92: 5 | C92: Complete service failure, regulatory breach | D92: > $1M
A94: 7d. Risk Score Thresholds (Weighted Factor Model)
A95: Risk Level | B95: Score Range | C95: Color Code | D95: Escalation
A96: LOW | B96: < 1.5 | C96: #00B050 | D96: Standard process
A97: MEDIUM | B97: 1.5 - 2.5 | C97: #FFC000 | D97: Enhanced monitoring
A98: HIGH | B98: 2.5 - 3.5 | C98: #FF6600 | D98: Risk mitigation plan required
A99: CRITICAL | B99: 3.5 - 4.0 | C99: #FF0000 | D99: Executive review, CAB escalation
A100: SEVERE | B100: ≥ 4.0 | C100: #7030A0 | D100: Consider postponement
A102: 7e. Risk Factor Weights by Category
A103: Category | B103: Weight % | C103: # Factors | D103: Key Factors
A104: Technical Complexity | B104: 0.18 | C104: 5 factors | D104: New Tech Stack, Code Complexity, DB Changes
A105: Testing Quality | B105: 0.26 | C105: 8 factors | D105: Test Coverage, Env Parity, Automation
A106: Security & Compliance | B106: 0.08 | C106: 3 factors | D106: Vulnerabilities, Pen Test, Compliance Gate
A107: Data Migration | B107: 0.04 | C107: 3 factors | D107: Migration Required, Scripts Tested, Backup
A108: Resource & Schedule | B108: 0.14 | C108: 5 factors | D108: Team Availability, Overlapping Releases
A109: Environment & Dependencies | B109: 0.09 | C109: 4 factors | D109: Upstream/Downstream, Feature Flags
A110: Operational Readiness | B110: 0.1 | C110: 6 factors | D110: Rollback Time, Runbook, Automation Level
A111: Performance & Scalability | B111: 0.04 | C111: 2 factors | D111: Load Test, Performance Regression
A112: Release History | B112: 0.05 | C112: 6 factors | D112: Past Failures, MTBR, MTBF
A113: Business Criticality | B113: 0.02 | C113: 2 factors | D113: Revenue Impact, User Blast Radius
A114: TOTAL | B114: =SUM(B104:B113) -> 1 | C114: 44 factors | D114: Full weighted risk assessment
...

Sheet Status Lifecycles
A1: STATUS LIFECYCLES - All Transactional Entities
A3: RELEASES LIFECYCLE
A4: Status | B4: Description | C4: Next Possible Status | D4: Editable? | E4: Gate Requirements | F4: Enforcement
A5: Draft | B5: Initial creation state | C5: Planning, Cancelled | D5: Yes - all fields | E5: None | F5: Flexible (warn + override)
A6: Planning | B6: Scope and resource planning | C6: Testing, Blocked, Cancelled | D6: Yes - all fields | E6: Owner, Size required (§1-04, §1-06) | F6: Flexible (warn + override)
A7: Testing | B7: Development and integration testing | C7: UAT, Blocked, Cancelled | D7: Yes - all fields | E7: Priority required (§1-05) | F7: Flexible (warn + override)
A8: UAT | B8: User acceptance testing | C8: Pending CAB, Testing, Blocked, Cancelled | D8: Yes - most fields | E8: UAT environment booking | F8: Flexible (warn + override)
A9: Pending CAB | B9: Awaiting CAB decision | C9: CAB Approved, Deferred, Rejected, Blocked, Cancelled | D9: Limited | E9: All sign-offs, Go-Live date, no blockers (VR-14, VR-24) | F9: Flexible (warn + override)
A10: CAB Approved | B10: CAB approved | C10: Ready, Pending CAB (scope change), Blocked, Cancelled | D10: Limited | E10: Scope changes trigger revert (VR-21) | F10: Flexible (warn + override)
A11: Ready | B11: Prepared for deployment | C11: Deploying, Blocked, Cancelled | D11: Limited | E11: Rollback plan, checklist, no blockers (VR-16, VR-27) | F11: Flexible (warn + override)
A12: Deploying | B12: Active deployment | C12: Deployed, Rolled Back, Blocked | D12: Read-only (dates, scope) | E12: Environment booking (VR-19), hard deps met (VR-18) | F12: Required — only Deployed/Rolled Back/Blocked, no override (CFG-06)
A13: Deployed | B13: Successfully deployed | C13: Closed, Rolled Back | D13: Read-only | E13: Post-deployment validation | F13: Required — only Closed/Rolled Back, no override (CFG-06)
A14: Closed | B14: TERMINAL - Complete | C14: None | D14: IMMUTABLE | E14: N/A | F14: Required — terminal, immutable
A15: Cancelled | B15: TERMINAL - Abandoned | C15: None | D15: IMMUTABLE | E15: N/A | F15: Required — terminal, immutable
... A19: Rejected | B19: CAB rejected | C19: Planning | D19: Yes - gates unlocked | E19: Rework required (§4-12) | F19: Flexible (warn + override)
A22: BLOCKERS LIFECYCLE
A23: Status | B23: Description | C23: Next Possible Status | D23: Editable? | E23: Cascade Effect | F23: Enforcement
A24: Open | B24: Newly identified blocker | C24: In Progress, Cancelled | D24: Yes | E24: Blocks release transition to Ready | F24: Flexible (warn + override)
A25: In Progress | B25: Being actively worked | C25: Resolved, Escalated, Cancelled | D25: Yes | E25: Stale alert after 5 days (AV-03) | F25: Flexible (warn + override)
A26: Escalated | B26: Requires management attention | C26: In Progress, Resolved, Cancelled | D26: Yes | E26: Higher visibility | F26: Flexible (warn + override)
A27: Resolved | B27: Issue fixed | C27: Closed, Reopened | D27: Limited | E27: May auto-unblock release (CASC-02) | F27: Flexible (warn + override)
A28: Closed | B28: FINAL - Verified complete | C28: None | D28: Read-only (§3-09) | E28: Release unblocked if all resolved | F28: Required — terminal, immutable
A29: Cancelled | B29: FINAL - No longer relevant | C29: None | D29: Read-only | E29: No cascade | F29: Required — terminal, immutable
A30: Reopened | B30: Issue recurred | C30: In Progress | D30: Yes | E30: May re-block release | F30: Flexible (warn + override)
A33: APPROVALS LIFECYCLE
A34: Status | B34: Description | C34: Next Possible Status | D34: Editable? | E34: Notes | F34: Enforcement
A35: Pending | B35: Awaiting approver action | C35: Approved, Rejected, Deferred | D35: Yes | E35: Standard state after CAB submission | F35: Flexible (warn + override)
A36: Approved | B36: FINAL - Approval granted | C36: None | D36: IMMUTABLE (§3-10) | E36: 30-day expiry if not deployed (AV-22) | F36: Required — terminal, immutable (decision rendered)
A37: Rejected | B37: FINAL - Approval denied | C37: None | D37: IMMUTABLE | E37: Release reverts to Planning | F37: Required — terminal, immutable (decision rendered)
A38: Deferred | B38: FINAL - Postponed | C38: None | D38: Yes | E38: Release status = Deferred | F38: Flexible (warn + override) — no longer terminal
A39: Expired | B39: FINAL - Auto-expired | C39: None | D39: IMMUTABLE | E39: Triggered by AV-22 | F39: Required — terminal, immutable
A40: Withdrawn | B40: FINAL - Requestor cancelled | C40: None | D40: IMMUTABLE | E40: Manual withdrawal | F40: Required — terminal, immutable
A43: SIGN-OFFS LIFECYCLE
A44: Status | B44: Description | C44: Next Possible Status | D44: Editable? | E44: Sign-Off Types | F44: Enforcement
A45: Pending | B45: Awaiting signatory action | C45: Approved, Rejected, Approved with Conditions | D45: Yes | E45: Dev, Test, UAT, Security, Business, Ops (each configurable mandatory/optional per org) | F45: Flexible (warn + override)
A46: Approved | B46: FINAL - Sign-off granted | C46: None | D46: IMMUTABLE | E46: Required for Pending CAB transition | F46: Required — terminal, immutable (decision rendered)
A47: Rejected | B47: FINAL - Sign-off denied | C47: None | D47: IMMUTABLE | E47: Blocks CAB submission | F47: Required — terminal, immutable
A48: Approved with Conditions | B48: FINAL - Conditional approval | C48: None | D48: IMMUTABLE | E48: Conditions must be tracked | F48: Required — terminal, immutable
A49: Withdrawn | B49: FINAL - Request cancelled | C49: None | D49: IMMUTABLE | E49: Manual withdrawal | F49: Required — terminal, immutable
A50: Expired | B50: FINAL - SLA exceeded | C50: None | D50: IMMUTABLE | E50: Auto-expired | F50: Required — terminal, immutable
A53: RISKS LIFECYCLE
A54: Status | B54: Description | C54: Next Possible Status | D54: Editable? | E54: Risk Score Requirements | F54: Enforcement
A55: Identified | B55: Risk logged, needs assessment | C55: Assessing, Closed | D55: Yes | E55: Probability and Impact required (§1-10, §1-11) | F55: Flexible (warn + override)
A56: Assessing | B56: Under evaluation | C56: Mitigating, Accepted, Closed | D56: Yes | E56: Risk Score calculated (§2-08) | F56: Flexible (warn + override)
A57: Mitigating | B57: Mitigation actions in progress | C57: Mitigated, Accepted, Closed | D57: Yes | E57: Mitigation Plan required for High severity (VR-27) | F57: Flexible (warn + override)
A58: Mitigated | B58: Controls implemented | C58: Accepted, Closed | D58: Limited | E58: Residual risk documented | F58: Flexible (warn + override)
A59: Accepted | B59: Risk acknowledged and accepted | C59: Closed | D59: Read-only | E59: Requires documented acceptance | F59: Flexible (warn + override)
A60: Closed | B60: FINAL - Risk resolved/retired | C60: None | D60: Read-only | E60: N/A | F60: Required — terminal, immutable
A61: Escalated | B61: Requires management attention | C61: Mitigating, Accepted | D61: Yes | E61: Auto-escalated after 3 days (AV-02) | F61: Flexible (warn + override)
A64: INCIDENTS LIFECYCLE
A65: Status | B65: Description | C65: Next Possible Status | D65: Editable? | E65: Cascade Effect | F65: Enforcement
A66: Open | B66: Incident reported | C66: Investigating, Closed | D66: Yes | E66: Critical incidents auto-escalate if no owner (VR-13) | F66: Flexible (warn + override)
A67: Investigating | B67: Root cause analysis | C67: Resolving, Escalated, Closed | D67: Yes | E67: Links to release if deployment-related | F67: Flexible (warn + override)
A68: Escalated | B68: Management attention required | C68: Investigating, Resolving, Closed | D68: Yes | E68: High visibility | F68: Flexible (warn + override)
A69: Resolving | B69: Fix in progress | C69: Resolved, Escalated | D69: Yes | E69: May block linked release (AV-06) | F69: Flexible (warn + override)
A70: Resolved | B70: Fix applied, pending verification | C70: Closed, Reopened | D70: Limited | E70: Critical incidents unblock release | F70: Flexible (warn + override)
A71: Closed | B71: FINAL - Verified complete | C71: None | D71: Read-only | E71: N/A | F71: Required — terminal, immutable
A72: Reopened | B72: Issue recurred | C72: Investigating | D72: Yes | E72: May re-trigger blocks | F72: Flexible (warn + override)
A75: DEPENDENCIES LIFECYCLE
A76: Status | B76: Description | C76: Next Possible Status | D76: Editable? | E76: Gate Impact | F76: Enforcement
A77: Pending | B77: Dependency not yet met | C77: At Risk, Met, Waived, Removed | D77: Yes | E77: Hard dependencies block Deploying (VR-18) | F77: Flexible (warn + override)
A78: Met | B78: FINAL - Dependency satisfied | C78: None | D78: Read-only | E78: Auto-updated when dependency deployed (AV-04) | F78: Required — terminal (auto-flagged At Risk + conscious RM alert if predecessor is rolled back, per AV-26; RM resolves via clone/new dependency, no silent auto-revert)
A79: Waived | B79: FINAL - Dependency waived | C79: None | D79: Read-only | E79: Requires documented approval | F79: Required — terminal, immutable
A80: Removed | B80: FINAL - No longer a dependency | C80: None | D80: Read-only | E80: Relationship deleted | F80: Required — terminal, immutable
A81: At Risk | B81: Dependency timeline in jeopardy | C81: Pending, Met, Waived | D81: Yes | E81: Warning indicator | F81: Flexible (warn + override)
A84: CONFLICTS LIFECYCLE
A85: Status | B85: Description | C85: Next Possible Status | D85: Editable? | E85: Conflict Types | F85: Enforcement
A86: Detected | B86: System identified conflict | C86: Under Review, Resolved, Dismissed | D86: Yes | E86: Schedule (same deploy window), Resource (same env), Application (same app) | F86: Flexible (warn + override)
A87: Under Review | B87: Being evaluated | C87: Resolved, Dismissed | D87: Yes | E87: Requires RM assessment | F87: Flexible (warn + override)
A88: Resolved | B88: FINAL - Conflict addressed | C88: None | D88: Read-only | E88: Auto-detected on deploy date save (AV-05) | F88: Required — terminal, immutable
A89: Dismissed | B89: FINAL - False positive or accepted | C89: None | D89: Read-only | E89: Requires justification | F89: Required — terminal, immutable
A92: DRIFT LIFECYCLE (Config Drift Detection)
A93: Status | B93: Description | C93: Next Possible Status | D93: Editable? | E93: Detection Trigger | F93: Enforcement
A94: Detected | B94: Delta found vs baseline | C94: Investigating, Approved, Reverted | D94: Yes | E94: Daily scan job (AV-13) | F94: Flexible (warn + override)
A95: Investigating | B95: Determining cause | C95: Approved, Reverted, Escalated | D95: Yes | E95: Manual review required | F95: Flexible (warn + override)
A96: Approved | B96: FINAL - Drift is intentional | C96: None | D96: Read-only | E96: New baseline established | F96: Required — terminal, immutable
A97: Reverted | B97: FINAL - Config restored | C97: None | D97: Read-only | E97: Baseline re-applied | F97: Required — terminal, immutable
A98: Escalated | B98: Unauthorized change suspected | C98: Investigating, Approved, Reverted | D98: Yes | E98: Security alert triggered (AV-14) | F98: Flexible (warn + override)
A101: ALERTS LIFECYCLE
A102: Status | B102: Description | C102: Next Possible Status | D102: Editable? | E102: Alert Types | F102: Enforcement
A103: Pending | B103: Alert generated, not yet acknowledged | C103: Acknowledged, Dismissed, Expired | D103: Yes | E103: Reminder, Warning, Escalation, Notification | F103: Flexible (warn + override)
A104: Acknowledged | B104: User confirmed receipt | C104: Actioned, Dismissed | D104: Limited | E104: Stops repeat alerts | F104: Flexible (warn + override)
A105: Actioned | B105: FINAL - Action taken | C105: None | D105: Read-only | E105: Audit trail captured | F105: Required — terminal, immutable
A106: Dismissed | B106: FINAL - No action needed | C106: None | D106: Read-only | E106: Reason required | F106: Required — terminal, immutable
A107: Expired | B107: FINAL - Auto-expired | C107: None | D107: Read-only | E107: TTL exceeded | F107: Required — terminal, immutable

Sheet Release Fields
A1: RELEASE FIELDS - COMPREHENSIVE FIELD LOCK MATRIX
A2: This sheet defines all release fields and when they become locked (read-only) during the release lifecycle.
A4: LEGEND: | B4: Editable = Can be modified | C4: Locked = Read-only | D4: Editable* = Editable but triggers status revert
A6: Field Name | B6: Category | C6: Required At | D6: Draft | E6: Planning | F6: Testing | G6: UAT | H6: Pending CAB | I6: CAB Approved | J6: Ready | K6: Deploying | L6: Deployed | M6: Closed/Cancelled | N6: Lock Rule Ref
A7: Release ID | B7: Identity | C7: Auto | D7: Locked | E7: Locked | F7: Locked | G7: Locked | H7: Locked | I7: Locked | J7: Locked | K7: Locked | L7: Locked | M7: Locked | N7: §2-Auto
A8: Release Name | B8: Identity | C8: Draft | D8: Editable | E8: Editable | F8: Editable | G8: Editable | H8: Locked | I8: Locked | J8: Locked | K8: Locked | L8: Locked | M8: Locked | N8: §3-11
A9: Application | B9: Identity | C9: Draft | D9: Editable | E9: Editable | F9: Locked | G9: Locked | H9: Locked | I9: Locked | J9: Locked | K9: Locked | L9: Locked | M9: Locked | N9: §3-12
A10: Release Type | B10: Identity | C10: Planning | D10: Editable | E10: Editable | F10: Editable | G10: Locked | H10: Locked | I10: Locked | J10: Locked | K10: Locked | L10: Locked | M10: Locked | N10: §3-13
A11: Release Owner | B11: Ownership | C11: Planning | D11: Editable | E11: Editable | F11: Editable | G11: Editable | H11: Editable | I11: Editable | J11: Locked | K11: Locked | L11: Locked | M11: Locked | N11: §3-14
A12: Backup Owner | B12: Ownership | C12: Ready | D12: Editable | E12: Editable | F12: Editable | G12: Editable | H12: Editable | I12: Editable | J12: Editable | K12: Locked | L12: Locked | M12: Locked | N12: §3-14
A13: Technical Lead | B13: Ownership | C13: Planning | D13: Editable | E13: Editable | F13: Editable | G13: Editable | H13: Locked | I13: Locked | J13: Locked | K13: Locked | L13: Locked | M13: Locked | N13: §3-15
A14: Business Owner | B14: Ownership | C14: Planning | D14: Editable | E14: Editable | F14: Editable | G14: Editable | H14: Locked | I14: Locked | J14: Locked | K14: Locked | L14: Locked | M14: Locked | N14: §3-15
A15: Size | B15: Scope | C15: Planning | D15: Editable | E15: Editable | F15: Editable | G15: Editable | H15: Locked | I15: Editable* | J15: Locked | K15: Locked | L15: Locked | M15: Locked | N15: §3-04, VR-21
A16: Priority | B16: Scope | C16: Testing | D16: Editable | E16: Editable | F16: Editable | G16: Editable | H16: Locked | I16: Editable* | J16: Locked | K16: Locked | L16: Locked | M16: Locked | N16: §3-04, VR-21
A17: Scope Description | B17: Scope | C17: Planning | D17: Editable | E17: Editable | F17: Editable | G17: Editable | H17: Locked | I17: Editable* | J17: Locked | K17: Locked | L17: Locked | M17: Locked | N17: §3-04, VR-21
... A51: Previous Status | B51: Workflow | C51: Auto | D51: Locked | E51: Locked | F51: Locked | G51: Locked | H51: Locked | I51: Locked | J51: Locked | K51: Locked | L51: Locked | M51: Locked | N51: §2-08
A53: RELATED ENTITY READ-ONLY & LOCK RULES - ALL LINKED ENTITY TYPES (BLOCKERS, APPROVALS, SIGN-OFFS, RISKS, DEPENDENCIES, CONFLICTS, ENVIRONMENT BOOKING, WORK ITEMS, CHECKLIST ITEMS)
A55: Entity | B55: Field/Condition | C55: Lock Rule | D55: Description
A56: Blocker | B56: Blocker Status = Resolved/Closed | C56: §3-09 | D56: Resolved or Closed blockers become read-only; cannot reopen or modify
A57: Blocker | B57: Release Status ≥ Deploying | C57: VR-39, LNK-02 | D57: No separate lock is needed: by Pending CAB every Blocker must already be Resolved/Closed/Cancelled (terminal, and therefore already read-only per §3-09) — see VR-39. If one is somehow still open, the RM unlinks it (LNK-02) rather than the record being silently frozen open.
A58: Blocker | B58: New blockers | C58: VR-35 | D58: Cannot create new blockers once release Status = Deploying or later
A59: Approval | B59: Decision = Approved/Rejected | C59: §3-10 | D59: Granted or rejected approvals become read-only
A60: Approval | B60: Release Status = Cancelled | C60: CASC-13 | D60: All approvals cancelled when release is cancelled (cascade)
A61: Sign-Off | B61: Sign-Off = Yes | C61: §3-21 | D61: Completed sign-offs cannot be changed to No (without rework)
A62: Sign-Off | B62: Release Status ≥ Pending CAB | C62: §3-05 | D62: Sign-off fields locked once release reaches Pending CAB
A63: Risk | B63: Release Status ≥ Ready | C63: §3-22, VR-39 | D63: Risks become read-only once the RISK ITSELF reaches a terminal status (Accepted/Closed) — not a release-status-triggered lock. VR-27 already requires mitigation (or a reasoned reversal) before Ready. See VR-39 for the blanket principle across all impediment/enabler types.
A64: Risk | B64: Mitigation = Complete | C64: VR-27 | D64: A completed Mitigation can be reversed by the Risk Owner/RM with a mandatory reason — flexible (WARN), not a hard lock, since no audit fact prevents reconsideration.
A65: Dependency | B65: Dependency Status = Met | C65: Dependency Lifecycle | D65: Met dependencies are locked; system auto-updates when prerequisite deploys
A66: Dependency | B66: Add/remove dependency when Release Status ≥ Ready | C66: VR-36 | D66: Dependency records cannot be added or removed once release reaches Ready; dependency structure is frozen.
... A72: Checklist Item | B72: Release Status ≥ Deploying | C72: §3-18 | D72: Checklist items locked during deployment
A74: PROGRESSION BLOCKERS - CONDITIONS THAT PREVENT STATUS TRANSITIONS
A76: Target Status | B76: Blocking Condition | C76: Blocker Type | D76: Rule Ref | E76: Error Message | F76: Resolution
A77: Planning | B77: Release Name is blank | C77: Field | D77: §1-02 | E77: Release name is required | F77: Enter release name
A78: Planning | B78: Application is blank | C78: Field | D78: §1-03 | E78: Application must be selected | F78: Select application
A79: Testing | B79: Size not set | C79: Field | D79: §1-04 | E79: Start Date is required before transitioning to Testing (§1-04). | F79: Select Small/Medium/Large
A80: Testing | B80: Start Date is blank | C80: Field | D80: RULE GAP | E80: Start Date is required before Testing, but no explicit rule currently defines this gate. | F80: Enter start date
A81: Testing | B81: End Date < Start Date | C81: Validation | D81: VR-01 | E81: End date cannot be before start date | F81: Correct dates
A82: UAT | B82: Test Sign-Off = No | C82: Enabler | D82: VR-30 | E82: Test sign-off required before UAT | F82: Complete test sign-off
A83: UAT | B83: Open blocker exists (Testing phase) | C83: Impediment | D83: RULE GAP | E83: No direct rule blocks Testing → UAT for an open blocker; AV-01 is a nightly auto-block check. | F83: Resolve all blockers
A84: Pending CAB | B84: Dev Sign-Off = No | C84: Enabler | D84: VR-14 | E84: Development sign-off required | F84: Complete dev sign-off
A85: Pending CAB | B85: Test Sign-Off = No | C85: Enabler | D85: VR-14 | E85: Test sign-off required | F85: Complete test sign-off
A86: Pending CAB | B86: UAT Sign-Off = No | C86: Enabler | D86: VR-14 | E86: UAT sign-off required | F86: Complete UAT sign-off
A87: Pending CAB | B87: Open blocker exists | C87: Impediment | D87: VR-24 | E87: All blockers must be resolved | F87: Resolve all blockers
... A108: Closed | B108: Post-implementation review incomplete | C108: Documentation | D108: VR-34 | E108: PIR required before closure | F108: Complete post-implementation review
A110: ENABLERS - REQUIREMENTS THAT MUST BE MET BEFORE TRANSITIONS
A112: Enabler Type | B112: When Required | C112: Status Value Needed | D112: Rule Ref | E112: Notes
A113: Dev Sign-Off | B113: Before Pending CAB | C113: Yes | D113: VR-14 | E113: Confirms development work complete and unit tested
A114: Test Sign-Off | B114: Before Pending CAB | C114: Yes | D114: VR-14 | E114: Confirms testing complete with passing results
A115: UAT Sign-Off | B115: Before Pending CAB | C115: Yes | D115: VR-14 | E115: Confirms business users accepted the release
A116: Security Sign-Off | B116: Before Pending CAB | C116: Yes (if required) | D116: VR-37 | E116: Required for security-sensitive systems
A117: Business Sign-Off | B117: Before Pending CAB | C117: Yes (if required) | D117: RULE GAP | E117: No current rule makes Business Sign-Off mandatory before Pending CAB.
A118: Ops Sign-Off | B118: Before Ready | C118: Yes | D118: VR-31 | E118: Confirms operations team readiness
A119: Rollback Plan | B119: Before Ready | C119: Ready | D119: VR-16 | E119: Documented procedure to reverse deployment
A120: Deployment Checklist | B120: Before Ready | C120: Complete | D120: VR-16 | E120: All pre-deployment tasks verified
A121: Dress Rehearsal | B121: Before Ready (Large) | C121: Done | D121: VR-26 | E121: Practice deployment (Warning for Large releases)
A122: Environment Booking | B122: Before Deploying | C122: Confirmed | D122: VR-19 | E122: Slot reserved in target environment
A123: Hard Dependencies | B123: Before Deploying | C123: All Met | D123: VR-18 | E123: All prerequisite releases deployed/closed
... A127: Documentation | B127: Before Pending CAB | C127: Rollback + Notes | D127: VR-24 | E127: Minimum documentation requirements met

Sheet LC_Releases
A1: 📋 RELEASES - Status Lifecycle
A2: Category: Release Lifecycle Items
A3: Purpose: The central entity - everything revolves around releases
A5: STATUS LIFECYCLE
A6: Status | B6: Description | C6: Next Possible Status | D6: Editable?
A7: Draft | B7: Initial creation, incomplete details | C7: Planning, Cancelled | D7: Yes
A8: Planning | B8: Being planned, gathering requirements | C8: Testing, Cancelled | D8: Yes
A9: Testing | B9: In test environment | C9: UAT, Blocked, Planning | D9: Yes
A10: UAT | B10: User acceptance testing | C10: Pending CAB, Blocked, Testing | D10: Yes
A11: Pending CAB | B11: Awaiting CAB review and approval | C11: CAB Approved, Rejected, Deferred | D11: Yes
A12: CAB Approved | B12: CAB approved, ready to proceed | C12: Ready, Blocked | D12: Yes
A13: Ready | B13: Ready for production deployment | C13: Deploying, Blocked | D13: Yes
A14: Deploying | B14: Deployment in progress | C14: Deployed, Rolled Back | D14: Yes
A15: Deployed | B15: Successfully released to production | C15: Closed, Rolled Back | D15: Limited
A16: Closed | B16: Release complete, archived | C16: None (FINAL) | D16: No - Immutable
A17: Blocked | B17: Cannot proceed due to issue | C17: Any previous status | D17: Yes
... A19: Rolled Back | B19: Reverted after deployment | C19: Testing, Cancelled | D19: Yes

Sheet LC_Blockers
A1: 🛑 BLOCKERS - Status Lifecycle
A2: Category: Operational Monitoring
A3: Purpose: Release blocker tracking and removal
A5: BLOCKER CATEGORIES
A6: Blocker Type | B6: Description | C6: Typical Cause | D6: Resolution Path
A7: Technical | B7: Code/infrastructure issue | C7: Bug, integration failure | D7: Development fix
A8: Resource | B8: Missing people/skills | C8: Unavailable SME, sick leave | D8: Resource allocation
A9: Dependency | B9: External dependency not met | C9: Upstream release delayed | D9: Dependency management
A10: Approval | B10: Waiting on sign-off | C10: Approver unavailable | D10: Escalation to delegate
A11: Environment | B11: Environment not available | C11: Env conflict, outage | D11: Env booking resolution
A12: Data | B12: Missing or incorrect data | C12: Data not migrated | D12: Data team support
A13: Compliance | B13: Regulatory/audit hold | C13: Pending audit result | D13: Compliance team coordination
A14: Vendor | B14: Third-party dependency | C14: Vendor delivery delayed | D14: Vendor management
A15: KEY PRINCIPLE: Blocker records are IMMUTABLE once Closed - ensures accurate release velocity metrics and blocker trend analysis.
A17: STATUS LIFECYCLE
A18: Status | B18: Description | C18: Next Possible Status | D18: Editable? | E18: Owner
A19: Open | B19: Blocker identified, not yet being worked | C19: Assigned, Escalated | D19: Yes | E19: Release Manager
A20: Assigned | B20: Owner designated to resolve | C20: In Progress | D20: Yes | E20: Blocker Owner
A21: In Progress | B21: Actively being worked | C21: Pending, Resolved, Escalated | D21: Yes | E21: Blocker Owner
A22: Pending | B22: Awaiting external input/action | C22: In Progress, Escalated | D22: Yes | E22: Blocker Owner
A23: Escalated | B23: Requires management intervention | C23: In Progress, Resolved | D23: Yes | E23: Manager
A24: Resolved | B24: Blocker removed | C24: Closed | D24: Yes | E24: Blocker Owner
A25: Closed | B25: Final state, resolution permanent | C25: None (FINAL) | D25: No - Immutable | E25: Release Manager

Sheet LC_Incidents
A1: 🚨 INCIDENTS - Status Lifecycle
A2: Category: Operational Monitoring
A3: Purpose: Release-related incident tracking and resolution
A5: INCIDENT SEVERITY LEVELS
A6: Severity | B6: Description | C6: Response SLA | D6: Resolution SLA | E6: Escalation
A7: P1 - Critical | B7: Production down, major impact | C7: 15 minutes | D7: 4 hours | E7: Immediate to VP
A8: P2 - High | B8: Significant functionality impacted | C8: 30 minutes | D8: 8 hours | E8: Manager within 1 hour
A9: P3 - Medium | B9: Partial impact, workaround exists | C9: 2 hours | D9: 24 hours | E9: Manager within 4 hours
A10: P4 - Low | B10: Minor issue, minimal impact | C10: 4 hours | D10: 72 hours | E10: Team lead if stalled
A11: KEY PRINCIPLE: Incident records are IMMUTABLE once Closed - this ensures audit integrity and accurate resolution metrics.
A13: STATUS LIFECYCLE
A14: Status | B14: Description | C14: Next Possible Status | D14: Editable? | E14: Owner
A15: Active | B15: Incident reported and active | C15: Acknowledged, Investigating | D15: Yes | E15: Service Desk
A16: Acknowledged | B16: Responder confirmed awareness | C16: Investigating, Resolved | D16: Yes | E16: Incident Owner
A17: Investigating | B17: Root cause being determined | C17: Resolved, Escalated | D17: Yes | E17: Incident Owner
A18: Escalated | B18: Higher level involvement needed | C18: Investigating, Resolved | D18: Yes | E18: Escalation Manager
A19: Resolved | B19: Fix applied, issue addressed | C19: Closed | D19: Yes | E19: Incident Owner
A20: Closed | B20: Incident fully resolved and documented | C20: None (FINAL) | D20: No - Immutable | E20: Service Desk

Sheet LC_Approvals
A1: ✅ CAB APPROVALS - Status Lifecycle
A2: Category: Release Lifecycle Items
A3: Purpose: Change Advisory Board approval workflow for release authorization
A5: ⚠️ KEY PRINCIPLE: Approval decisions are IMMUTABLE once recorded. Changes require a new approval request.
A7: APPROVAL TYPES
A8: Approval Type | B8: Description | C8: Required For | D8: Approver Role
A9: CAB Final | B9: Change Advisory Board decision for release | C9: High/Critical releases | D9: CAB Chair / Members
A10: Change Manager | B10: Change Manager authorization | C10: All releases | D10: Change Manager
A11: Executive Approval | B11: Executive authorization for critical changes | C11: Critical releases only | D11: Director/VP
A12: Emergency Approval | B12: Fast-track approval for emergency fixes | C12: Emergency releases | D12: On-call CAB delegate
A15: STATUS LIFECYCLE
A16: Status | B16: Description | C16: Next Possible Status | D16: Editable? | E16: Owner
A17: Pending | B17: Awaiting approver action | C17: Approved, Rejected, Approved with Conditions | D17: Yes | E17: Approver
A18: Approved | B18: Approval granted | C18: None (FINAL) | D18: No - Immutable | E18: N/A
A19: Rejected | B19: Approval denied | C19: None (FINAL) | D19: No - Immutable | E19: N/A
A20: Approved with Conditions | B20: Conditional approval | C20: None (FINAL) | D20: No - Immutable | E20: N/A
A21: Withdrawn | B21: Requestor cancelled request | C21: None (FINAL) | D21: No - Immutable | E21: N/A
A22: Expired | B22: No decision within SLA | C22: None (FINAL) | D22: No - Immutable | E22: N/A

Sheet LC_Sign-Offs
A1: 📝 SIGN-OFFS - Status Lifecycle
A2: Category: Pre-CAB Release Gate Items
A3: Purpose: Stakeholder confirmations required before CAB submission
A5: ⚠️ KEY PRINCIPLE: Sign-off decisions are IMMUTABLE once recorded. Changes require a new sign-off request.
A7: SIGN-OFF TYPES
A8: Sign-Off Type | B8: Description | C8: Required For | D8: Signatory Role
A9: Tech Review | B9: Technical feasibility and code quality assessment | C9: All releases | D9: Development Manager / Tech Lead
A10: Security Review | B10: Security compliance and vulnerability check | C10: All releases | D10: Security Analyst / CISO delegate
A11: Business Review | B11: Business impact and readiness assessment | C11: Medium+ releases | D11: Operations Manager / Product Owner
A12: Operations Review | B12: Infrastructure and operational readiness | C12: High/Critical releases | D12: Infrastructure Manager
A13: QA Sign-Off | B13: Testing completion and quality gate | C13: All releases | D13: QA Manager / Test Lead
A15: STATUS LIFECYCLE
A16: Status | B16: Description | C16: Next Possible Status | D16: Editable? | E16: Owner
A17: Pending | B17: Awaiting signatory action | C17: Approved, Rejected, Approved with Conditions | D17: Yes | E17: Signatory
A18: Approved | B18: Sign-off granted | C18: None (FINAL) | D18: No - Immutable | E18: N/A
A19: Rejected | B19: Sign-off denied | C19: None (FINAL) | D19: No - Immutable | E19: N/A
A20: Approved with Conditions | B20: Conditional sign-off granted | C20: None (FINAL) | D20: No - Immutable | E20: N/A
A21: Withdrawn | B21: Requestor cancelled request | C21: None (FINAL) | D21: No - Immutable | E21: N/A
A22: Expired | B22: No decision within SLA | C22: None (FINAL) | D22: No - Immutable | E22: N/A

Sheet LC_Risk
A1: ⚠️ RISK - Status Lifecycle
A2: Category: Risk & Impact Assessment
A3: Purpose: Risk scoring and mitigation tracking
A5: RISK LEVELS
A6: Risk Level | B6: Score Range | C6: Color | D6: Required Action | E6: Approval Level
A7: Low | B7: 1-9 | C7: Green | D7: Standard deployment | E7: Release Manager
A8: Medium | B8: 10-14 | C8: Yellow | D8: Enhanced monitoring | E8: Release Manager
A9: High | B9: 15-19 | C9: Orange | D9: CAB review required | E9: CAB
A10: Critical | B10: 20-24 | C10: Red | D10: Executive approval needed | E10: Director
A11: Severe | B11: 25+ | C11: Dark Red | D11: Immediate review required | E11: VP/CIO
A13: STATUS LIFECYCLE
A14: Status | B14: Description | C14: Next Possible Status | D14: Owner | E14: Editable?
A15: Open | B15: Risk identified and logged | C15: In Progress, Accepted, Escalated | D15: Risk Owner | E15: Yes
A16: In Progress | B16: Risk being evaluated and assessed | C16: Mitigating, Accepted, Escalated | D16: Risk Owner | E16: Yes
A17: Mitigating | B17: Mitigation actions being implemented | C17: Monitoring, Accepted, Escalated | D17: Risk Owner | E17: Yes
A18: Accepted | B18: Risk accepted, no further mitigation | C18: Monitoring, Closed | D18: Decision Maker | E18: Yes
A19: Escalated | B19: Elevated for executive review | C19: In Progress, Mitigating, Accepted | D19: Escalation Manager | E19: Yes
A20: Monitoring | B20: Risk mitigated, being tracked | C20: Closed, Open (if recurs) | D20: Risk Owner | E20: Yes
A21: Closed | B21: Risk no longer applicable | C21: None (FINAL) | D21: Risk Owner | E21: No - Immutable

Sheet LC_Dependency
A1: 🔗 DEPENDENCY - Status Lifecycle
A2: Category: Risk & Impact Assessment
A3: Purpose: Cross-release and system dependency management
A5: DEPENDENCY TYPES
A6: Dependency Type | B6: Description | C6: Example | D6: Tracking Method
A7: Release-to-Release | B7: One release depends on another | C7: Feature needs API from other release | D7: Linked Release IDs
A8: System | B8: Application/platform dependency | C8: Integration requires SAP upgrade | D8: System Registry
A9: Data | B9: Data migration or prerequisite | C9: Customer data needed first | D9: Data Flow Mapping
A10: Resource | B10: Same team/person required | C10: DBA needed for both releases | D10: Resource Calendar
A11: Environment | B11: Shared environment dependency | C11: Both need UAT slot | D11: Env Booking
A12: External | B12: Third-party or vendor dependency | C12: Vendor patch required | D12: Vendor Tracking
A13: Regulatory | B13: Compliance prerequisite | C13: Audit must complete first | D13: Compliance Calendar
A15: STATUS LIFECYCLE
A16: Status | B16: Description | C16: Next Possible Status | D16: Owner
A17: Identified | B17: Dependency discovered | C17: Pending, Confirmed | D17: Release Manager
A18: Pending | B18: Awaiting confirmation from dependent party | C18: Confirmed, Removed | D18: Release Manager
A19: Confirmed | B19: Both parties acknowledge dependency | C19: In Progress | D19: Both Release Managers
A20: In Progress | B20: Dependent work underway | C20: At Risk, Blocked, Resolved | D20: Dependency Owner
A21: At Risk | B21: Dependency may not be met on time | C21: In Progress, Blocked, Resolved | D21: Release Manager
A22: Blocked | B22: Cannot proceed due to dependency | C22: In Progress, Escalated | D22: Stakeholder
A23: Escalated | B23: Requires management resolution | C23: Blocked, Resolved, Removed | D23: Director
A24: Resolved | B24: Dependency satisfied | C24: Closed | D24: Release Manager
A25: Removed | B25: Dependency no longer applies | C25: Closed | D25: Release Manager
A26: Closed | B26: Final state, release complete | C26: None (Terminal) | D26: Release Manager | E26: No - Immutable

Sheet LC_Conflict
A1: ⚡ CONFLICT - Status Lifecycle
A2: Category: Conflict Resolution
A3: Purpose: Environment and scheduling conflict management
A5: CONFLICT TYPES
A6: Conflict Type | B6: Description | C6: Detection Method | D6: Resolution Options
A7: Environment Booking | B7: Two releases need same environment for overlapping periods | C7: Booking calendar overlap check | D7: Reschedule one release, Negotiate shorter windows, Find alternate env
A8: Maintenance Window | B8: Release deployment overlaps with scheduled infrastructure maintenance | C8: Maintenance calendar cross-check | D8: Reschedule release, Request maintenance reschedule
A9: Freeze Period | B9: Release scheduled during code/change freeze period | C9: Freeze calendar check | D9: Reschedule release, Request freeze exception
A11: KEY PRINCIPLE: Conflict records are IMMUTABLE once Closed - preserves scheduling audit trail and conflict pattern analysis.
A13: STATUS LIFECYCLE
A14: Status | B14: Description | C14: Next Possible Status | D14: Editable?
A15: Open | B15: Conflict identified, needs triage | C15: In Progress, Escalated | D15: Yes
A16: In Progress | B16: Resolution being worked | C16: Pending Review, Escalated | D16: Yes
A17: Pending Review | B17: Solution proposed, awaiting approval | C17: Resolved, In Progress | D17: Yes
A18: Escalated | B18: Requires higher authority decision | C18: In Progress, Resolved | D18: Yes
A19: Resolved | B19: Conflict addressed successfully | C19: Closed | D19: Yes
A20: Closed | B20: Final state, resolution permanent | C20: None (FINAL) | D20: No - Immutable
A22: SYSTEM BEHAVIOR - Auto-Detection Requirements (for Cursor)
A24: Requirement ID | B24: Requirement | C24: Trigger Event | D24: System Action
A25: CNF-REQ-001 | B25: Auto-detect Environment Booking conflicts | C25: User attempts to book an environment | D25: Check booking calendar for overlapping periods with same environment
A26: CNF-REQ-002 | B26: Auto-detect Maintenance Window conflicts | C26: User schedules release deployment date/time | D26: Check maintenance calendar for overlap with deployment window
A27: CNF-REQ-003 | B27: Auto-detect Freeze Period conflicts | C27: User sets release target date | D27: Check freeze period calendar for date overlap
A29: USER PROMPT FLOW
A30: Step | B30: Action | C30: User Options | D30: System Response
A31: 1 | B31: Conflict detected during booking/scheduling | C31: — | D31: Display conflict details (what, when, which release)
A32: 2 | B32: Prompt user for action | C32: Option A: Modify release (change date/env) | D32: Return to booking/scheduling screen with conflict highlighted
C33: Option B: Raise conflict for RM | D33: Create Conflict record with Status='Open', link both releases
A34: 3 | B34: If Option B selected | C34: Add notes (optional) | D34: Save conflict, notify Release Manager, show confirmation
A36: CONFLICT RECORD AUTO-POPULATION
A37: Field | B37: Auto-populated Value | C37: Source
A38: Conflict Type | B38: Based on detection trigger | C38: System
A39: Release 1 | B39: Current release being scheduled | C39: User context
A40: Release 2 | B40: Conflicting release found | C40: Booking/calendar query
A41: Environment | B41: The contested environment (if applicable) | C41: Booking data
A42: Conflict Period | B42: Overlapping date/time range | C42: Calendar comparison
A43: Status | B43: Open | C43: Default
A44: Raised By | B44: Current user | C44: User context
A45: Raised Date | B45: Current timestamp | C45: System

Sheet LC_Alerts
A1: 🔔 ALERTS - Status Lifecycle
A2: Category: Operational Monitoring
A3: Purpose: Notifications and warnings management
A5: ALERT TYPES
A6: Alert Type | B6: Description | C6: Source | D6: Auto-Generated
A7: Schedule | B7: Release timeline approaching/exceeded | C7: Calendar engine | D7: Yes
A8: Approval Pending | B8: Approval awaiting response | C8: Workflow engine | D8: Yes
A9: Environment | B9: Environment status change | C9: Monitoring system | D9: Yes
A10: Conflict | B10: Conflict detected | C10: Booking system | D10: Yes
A11: Risk Threshold | B11: Risk score exceeded threshold | C11: Risk engine | D11: Yes
A12: Dependency | B12: Dependent release status change | C12: Dependency tracker | D12: Yes
A13: Manual | B13: User-generated alert | C13: User | D13: No
A14: System | B14: Platform/infrastructure notification | C14: Platform | D14: Yes
A16: STATUS LIFECYCLE
A17: Status | B17: Description | C17: Next Possible Status | D17: Owner
A18: Active | B18: Alert triggered, needs attention | C18: Acknowledged, Suppressed | D18: Alert Recipient
A19: Acknowledged | B19: Recipient confirmed awareness | C19: Investigating, Resolved | D19: Alert Recipient
A20: Investigating | B20: Being actively investigated | C20: Resolved, Escalated | D20: Alert Recipient
A21: Escalated | B21: Raised to higher level | C21: Investigating, Resolved | D21: Manager
A22: Resolved | B22: Issue addressed | C22: Closed | D22: Alert Recipient
A23: Suppressed | B23: Temporarily disabled | C23: Active, Closed | D23: Admin
A24: Closed | B24: No further action required | C24: None (FINAL) | D24: No - Immutable

Sheet LC_Drift
A1: 📊 DRIFT - Status Lifecycle
A2: Category: Risk & Impact Assessment
A3: Purpose: Timeline and scope deviation tracking and remediation
A5: DRIFT CATEGORIES
A6: Drift Type | B6: Description | C6: Indicators | D6: Threshold
A7: Infrastructure | B7: Infrastructure/hardware configuration differences between environments | C7: Database version mismatch, memory/CPU allocation differences | D7: Any material spec difference from Prod
A8: Configuration | B8: Application or system settings differing between environments | C8: API timeout settings, feature flag mismatches | D8: Any setting differing from Prod
A9: Data | B9: Test/reference data out of sync with production | C9: Stale test data, missing recent records | D9: Data older than defined refresh window
A10: Integration | B10: API or third-party interface version mismatch between environments | C10: Third-party endpoint version differences, contract mismatches | D10: Any version mismatch affecting behavior
A11: Security | B11: Security configuration or certificate drift | C11: Expired/mismatched SSL certificates, security exceptions | D11: Any unresolved security exception
A12: Code | B12: Unauthorized or unexpected code changes vs approved baseline | C12: Unapproved commits, hotfixes outside change process | D12: Any change outside approved baseline
A14: STATUS LIFECYCLE
A15: Status | B15: Description | C15: Next Possible Status | D15: Owner | E15: Editable?
A16: Open | B16: Drift detected, awaiting assessment | C16: In Progress, Scheduled, Escalated | D16: Release Manager | E16: Yes
A17: In Progress | B17: Remediation actions being worked | C17: Scheduled, Resolved, Escalated | D17: Release Manager | E17: Yes
A18: Scheduled | B18: Remediation planned for future date | C18: In Progress, Resolved, Escalated | D18: Release Manager | E18: Yes
A19: Escalated | B19: Requires executive decision | C19: In Progress, Scheduled, Resolved | D19: Director/Executive | E19: Yes
A20: Resolved | B20: Drift addressed, back on track | C20: Closed | D20: Release Manager | E20: Yes
A21: Closed | B21: Drift record finalized | C21: None (FINAL) | D21: Release Manager | E21: No - Immutable

Sheet System Mapping
A1: Enterprise System Integration Map
A3: Legend:
A4: Core ERP/Platform | B4: Central hub systems
A5: Bidirectional Integration | B5: Two-way data flow
A6: Data Feed (Upstream) | B6: Sends data to other systems
A7: Data Feed (Downstream) | B7: Receives data from other systems
A8: Shared Services | B8: Cross-department systems
A10: CORE SYSTEMS HUB
A11: System | B11: Department | C11: Type | D11: Integrates With | E11: Data Flow | F11: Key Data Exchanged
A12: SAP S/4HANA (ERP) | B12: Finance / Manufacturing | C12: Core ERP | D12: All Departments | E12: Bidirectional | F12: GL, AP, AR, Inventory, Orders, Cost Centers
A13: Workday HCM | B13: HR | C13: Core HCM | D13: Finance, IT, Security | E13: Bidirectional | F13: Employee Data, Payroll, Org Structure
A14: ServiceNow ITSM | B14: IT | C14: Service Platform | D14: All Departments | E14: Bidirectional | F14: Incidents, Changes, Assets, CMDB
A15: Salesforce CRM | B15: CRM | C15: Core CRM | D15: Finance, Manufacturing, Logistics | E15: Bidirectional | F15: Customers, Opportunities, Orders, Contracts
A18: DEPARTMENT INTEGRATION MATRIX
A19: From \ To | B19: Finance | C19: HR | D19: IT | E19: CRM | F19: Manufacturing | G19: Logistics | H19: Legal | I19: Security
A20: Finance | B20: — | C20: ● | D20: ● | E20: ● | F20: ● | G20: ● | H20: ● | I20: ○
A21: HR | B21: ● | C21: — | D21: ● | E21: ○ | F21: ○ | G21: ○ | H21: ● | I21: ●
A22: IT | B22: ● | C22: ● | D22: — | E22: ● | F22: ● | G22: ● | H22: ● | I22: ●
A23: CRM | B23: ● | C23: ○ | D23: ● | E23: — | F23: ● | G23: ● | H23: ● | I23: ○
A24: Manufacturing | B24: ● | C24: ○ | D24: ● | E24: ● | F24: — | G24: ● | H24: ○ | I24: ○
A25: Logistics | B25: ● | C25: ○ | D25: ● | E25: ● | F25: ● | G25: — | H25: ○ | I25: ○
A26: Legal | B26: ● | C26: ● | D26: ● | E26: ● | F26: ○ | G26: ○ | H26: — | I26: ●
A27: Security | B27: ○ | C27: ● | D27: ● | E27: ○ | F27: ○ | G27: ○ | H27: ● | I27: —
A29: ● Primary Integration | B29: Critical data exchange, real-time or daily sync
A30: ○ Secondary Integration | B30: Periodic data exchange, reporting or audit
A33: KEY INTEGRATION FLOWS
A34: Flow ID | B34: Source System | C34: Target System | D34: Integration Type | E34: Frequency | F34: Data Elements | G34: Business Purpose
A35: INT-001 | B35: Salesforce CRM | C35: SAP S/4HANA | D35: API / Real-time | E35: Real-time | F35: Sales Orders, Customer Master | G35: Order-to-Cash Process
A36: INT-002 | B36: SAP S/4HANA | C36: Workday HCM | D36: Batch / API | E36: Daily | F36: Cost Centers, GL Accounts | G36: Payroll & Financial Reporting
A37: INT-003 | B37: Workday HCM | C37: Okta Identity | D37: SCIM | E37: Real-time | F37: User Provisioning, Roles | G37: Identity & Access Management
A38: INT-004 | B38: SAP Manufacturing | C38: Blue Yonder WMS | D38: API / Batch | E38: Hourly | F38: Production Orders, BOM | G38: Supply Chain Execution
A39: INT-005 | B39: Blue Yonder WMS | C39: SAP Transportation | D39: API | E39: Real-time | F39: Shipments, Inventory | G39: Logistics Coordination
A40: INT-006 | B40: ServiceNow ITSM | C40: Splunk SIEM | D40: API | E40: Real-time | F40: Incidents, Alerts | G40: Security Operations
A41: INT-007 | B41: CrowdStrike | C41: Microsoft Sentinel | D41: API | E41: Real-time | F41: Threat Intelligence | G41: Security Monitoring
A42: INT-008 | B42: DocuSign CLM | C42: SAP S/4HANA | D42: API | E42: On-demand | F42: Contracts, Vendor Terms | G42: Procurement & Legal
A43: INT-009 | B43: Anaplan | C43: SAP S/4HANA | D43: Batch | E43: Daily | F43: Budgets, Forecasts | G43: Financial Planning
A44: INT-010 | B44: Oracle HCM | C44: ADP Workforce | D44: Batch | E44: Bi-weekly | F44: Payroll Data, Time | G44: Payroll Processing
A45: INT-011 | B45: Salesforce CRM | C45: Zendesk | D45: API | E45: Real-time | F45: Cases, Customer Data | G45: Customer Service
... A49: INT-015 | B49: SAP Concur | C49: SAP S/4HANA | D49: API | E49: Daily | F49: Expenses, T&E | G49: Expense Management
A52: SYSTEM ARCHITECTURE DIAGRAM
A54: ╔══════════════════════════════════════════════════════════════════════════════════════════════════════════════╗
A55: ║ ENTERPRISE INTEGRATION LAYER ║
A56: ║ (API Gateway / ESB / Integration Platform) ║
A57: ╚════════════╦═══════════════╦═══════════════╦═══════════════╦═══════════════╦═══════════════╦═════════════════╝
A58: ║ ║ ║ ║ ║ ║
A59: ▼ ▼ ▼ ▼ ▼ ▼
A60: ┌──────────────┐ ┌──────────────┐ ┌──────────────┐ ┌──────────────┐ ┌──────────────┐ ┌──────────────┐
A61: │ FINANCE │ │ HR │ │ IT │ │ CRM │ │ MANUFACTURING│ │ LOGISTICS │
A62: ├──────────────┤ ├──────────────┤ ├──────────────┤ ├──────────────┤ ├──────────────┤ ├──────────────┤
A63: │ SAP S/4HANA │ │ Workday HCM │ │ ServiceNow │ │ Salesforce │ │ SAP S/4 Manu │ │ SAP TM │
A64: │ Anaplan │ │ SuccessFactors│ │ Splunk │ │ Dynamics 365 │ │ Siemens MES │ │ Blue Yonder │
... A94: SHARED ENVIRONMENT & RESOURCE DEPENDENCIES
A95: Environment | B95: Type | C95: Shared By | D95: Capacity | E95: Booking Required | F95: Conflict Risk
A96: FIN-TEST-01 | B96: Test | C96: Finance, Legal, CRM | D96: Limited (3 concurrent) | E96: Yes - 2 weeks advance | F96: HIGH
A97: FIN-TEST-02 | B97: Test | C97: Finance | D97: Standard | E97: Yes - 1 week advance | F97: Medium
A98: FIN-UAT-01 | B98: UAT | C98: Finance, Legal, Manufacturing | D98: Limited (2 concurrent) | E98: Yes - 3 weeks advance | F98: HIGH
A99: IT-TEST-01 | B99: Test | C99: IT, Security, All Depts | D99: Shared Pool | E99: Yes - 1 week advance | F99: HIGH
A100: IT-UAT-01 | B100: UAT | C100: IT, Security | D100: Limited | E100: Yes - 2 weeks advance | F100: HIGH
A101: CRM-TEST-01 | B101: Test | C101: CRM, Sales Ops | D101: Standard | E101: Recommended | F101: Medium
A102: CRM-UAT-01 | B102: UAT | C102: CRM, Marketing | D102: Standard | E102: Yes - 1 week advance | F102: Medium
A103: MAN-TEST-01 | B103: Test | C103: Manufacturing, Logistics | D103: Limited | E103: Yes - 2 weeks advance | F103: HIGH
A104: LOG-TEST-01 | B104: Test | C104: Logistics, Manufacturing | D104: Standard | E104: Recommended | F104: Medium
A105: SEC-TEST-01 | B105: Test | C105: Security, IT | D105: Restricted | E105: Yes - 2 weeks advance | F105: Medium
A106: HR-TEST-01 | B106: Test | C106: HR, Payroll | D106: Standard | E106: Yes - 1 week advance | F106: Low
A107: INTEG-01 | B107: Integration | C107: ALL DEPARTMENTS | D107: Critical Shared | E107: Mandatory - 4 weeks | F107: CRITICAL
A110: CRITICAL INTEGRATION PATHS (Release Impact Analysis)
A111: Path ID | B111: Integration Path | C111: Upstream Systems | D111: Downstream Systems | E111: Release Coordination | F111: Blackout Windows | G111: Notes
A112: PATH-001 | B112: Order-to-Cash | C112: Salesforce → SAP | D112: SAP → Logistics → Finance | E112: Mandatory joint testing | F112: Month-end, Quarter-end | G112: Revenue impacting - CFO approval required
A113: PATH-002 | B113: Procure-to-Pay | C113: SAP → Coupa → Vendors | D113: AP → Treasury → Banking | E113: Finance sign-off required | F113: Month-end close (Days 1-5) | G113: Payment processing critical
A114: PATH-003 | B114: Hire-to-Retire | C114: Workday → Okta → All Apps | D114: Payroll → Finance → Tax | E114: HR + IT + Security coord | F114: Payroll windows | G114: Employee data sensitive
A115: PATH-004 | B115: Record-to-Report | C115: All Source Systems → SAP | D115: SAP → Cognos → Reporting | E115: Finance freeze periods | F115: Close periods | G115: SOX compliance required
A116: PATH-005 | B116: Plan-to-Produce | C116: SAP → MES → WMS | D116: Production → Inventory → Ship | E116: Manufacturing + Logistics | F116: Production schedules | G116: Supply chain disruption risk
A117: PATH-006 | B117: Security Operations | C117: All Systems → SIEM | D117: SIEM → SOC → Incident | E117: Security team approval | F117: Never (24/7 ops) | G117: Cannot have monitoring gaps
A118: PATH-007 | B118: Identity Lifecycle | C118: Workday → Okta → Apps | D118: Access → Audit → Compliance | E118: HR + IT + Security | F118: Audit periods | G118: Access control critical
A119: PATH-008 | B119: Contract Lifecycle | C119: Legal → DocuSign → SAP | D119: Procurement → Vendors | E119: Legal + Procurement | F119: Contract renewals | G119: Legal/financial obligations
A122: 📋 RELEASE MANAGER NOTES:
A123: 1. Always check Integration Matrix before scheduling cross-department releases
A124: 2. Shared environments (especially FIN-TEST-01, IT-TEST-01, INTEG-01) require advance booking
A125: 3. Critical Integration Paths require coordinated testing across all connected systems
A126: 4. Month-end, Quarter-end, and Year-end are high-risk periods - minimize changes
A127: 5. Security systems (PATH-006, PATH-007) require 24/7 availability - schedule carefully
A128: 6. SAP S/4HANA is the central hub - any SAP changes impact multiple departments
A131: 📖 QUICK REFERENCE: System Integrations (Collapsible Section for Web)
A133: INTEGRATION TYPES: API | File Transfer | Message Queue | Direct DB
A135: BEFORE RELEASE: Filter by your app → Find all connected systems → Notify teams
A137: RULE: Test ALL High criticality integrations before Prod deployment
A139: [▼ Full documentation below]
... A195: If you discover an unlisted integration, ADD IT IMMEDIATELY.

Sheet Applications
A1: Department | B1: Application | C1: Env | D1: Application Owner | E1: Tech Lead | F1: Env Owner
A2: Finance | B2: SAP S/4HANA Finance (FICO) | C2: Dev | D2: Sarah Mitchell | E2: James Wilson | F2: Alex Rivera (Dev Mgr)
B3: SAP S/4HANA Finance (FICO) | C3: Test | F3: Sam Anderson (QA Lead)
B4: SAP S/4HANA Finance (FICO) | C4: UAT | F4: Rachel Green (Bus Analyst)
B5: SAP S/4HANA Finance (FICO) | C5: Pre-prod | F5: Nathan Cole (Release Mgr)
B6: SAP S/4HANA Finance (FICO) | C6: Prod | F6: Victoria Sterling (Ops Mgr)
B7: SAP S/4HANA Finance (FICO) | C7: DR | F7: Robert Shield (Infra Lead)
B8: Anaplan | C8: Dev | D8: David Chen | E8: Emily Zhang | F8: Jordan Lee (Dev Mgr)
B9: Anaplan | C9: Test | F9: Chris Park (QA Lead)
B10: Anaplan | C10: UAT | F10: Monica Geller (Bus Analyst)
B11: Anaplan | C11: Pre-prod | F11: Ethan Black (Release Mgr)
B12: Anaplan | C12: Prod | F12: Elizabeth Crown (Ops Mgr)
B13: Anaplan | C13: DR | F13: William Guard (Infra Lead)
B14: Oracle Hyperion HFM | C14: Dev | D14: Jennifer Walsh | E14: Michael Brown | F14: Casey Chen (Dev Mgr)
B15: Oracle Hyperion HFM | C15: Test | F15: Pat Murphy (QA Lead)
B16: Oracle Hyperion HFM | C16: UAT | F16: Phoebe Buffay (Bus Analyst)
B17: Oracle Hyperion HFM | C17: Pre-prod | F17: Lucas White (Release Mgr)
B18: Oracle Hyperion HFM | C18: Prod | F18: Catherine Royal (Ops Mgr)
B19: Oracle Hyperion HFM | C19: DR | F19: James Fortress (Infra Lead)
B20: Kyriba | C20: Dev | D20: Robert Kim | E20: Priya Sharma | F20: Morgan Taylor (Dev Mgr)
B21: Kyriba | C21: Test | F21: Jesse Garcia (QA Lead)
B22: Kyriba | C22: UAT | F22: Emma Watson (Bus Analyst)
B23: Kyriba | C23: Pre-prod | F23: Mason Gray (Release Mgr)
B24: Kyriba | C24: Prod | F24: Margaret Noble (Ops Mgr)
B25: Kyriba | C25: DR | F25: Michael Bastion (Infra Lead)
B26: Coupa | C26: Dev | D26: Michelle Torres | E26: Christopher Davis | F26: Jamie Patel (Dev Mgr)
B27: Coupa | C27: Test | F27: Robin Chen (QA Lead)
B28: Coupa | C28: UAT | F28: Sophie Turner (Bus Analyst)
B29: Coupa | C29: Pre-prod | F29: Logan Stone (Release Mgr)
B30: Coupa | C30: Prod | F30: Diana Prince (Ops Mgr)
B31: Coupa | C31: DR | F31: David Tower (Infra Lead)
B32: Zuora | C32: Dev | D32: Andrew Patel | E32: Angela Liu | F32: Riley Kim (Dev Mgr)
B33: Zuora | C33: Test | F33: Dana Wilson (QA Lead)
B34: Zuora | C34: UAT | F34: Mia Collins (Bus Analyst)
B35: Zuora | C35: Pre-prod | F35: Jacob Hill (Release Mgr)
B36: Zuora | C36: Prod | F36: Helena Troy (Ops Mgr)
B37: Zuora | C37: DR | F37: Richard Wall (Infra Lead)
B38: RevPro | C38: Dev | D38: Lisa Thompson | E38: Daniel Park | F38: Quinn Johnson (Dev Mgr)
B39: RevPro | C39: Test | F39: Kelly Nguyen (QA Lead)
B40: RevPro | C40: UAT | F40: Isabella Moore (Bus Analyst)
B41: RevPro | C41: Pre-prod | F41: Aiden Clark (Release Mgr)
B42: RevPro | C42: Prod | F42: Sophia Grace (Ops Mgr)
B43: RevPro | C43: DR | F43: Thomas Castle (Infra Lead)
B44: Thomson Reuters ONESOURCE | C44: Dev | D44: Mark Rodriguez | E44: Jessica Nguyen | F44: Avery Williams (Dev Mgr)
B45: Thomson Reuters ONESOURCE | C45: Test | F45: Terry Brooks (QA Lead)
B46: Thomson Reuters ONESOURCE | C46: UAT | F46: Olivia James (Bus Analyst)
B47: Thomson Reuters ONESOURCE | C47: Pre-prod | F47: Jackson Moore (Release Mgr)
B48: Thomson Reuters ONESOURCE | C48: Prod | F48: Alexandra Reid (Ops Mgr)
B49: Thomson Reuters ONESOURCE | C49: DR | F49: Charles Vault (Infra Lead)
B50: SAP Concur | C50: Dev | D50: Amanda Foster | E50: Ryan Cooper | F50: Drew Martinez (Dev Mgr)
B51: SAP Concur | C51: Test | F51: Skyler Davis (QA Lead)
B52: SAP Concur | C52: UAT | F52: Ava Mitchell (Bus Analyst)
B53: SAP Concur | C53: Pre-prod | F53: Sebastian Hall (Release Mgr)
B54: SAP Concur | C54: Prod | F54: Christina Vale (Ops Mgr)
B55: SAP Concur | C55: DR | F55: Daniel Bunker (Infra Lead)
B56: Workday Financials | C56: Dev | D56: Kevin O'Brien | E56: Samantha Reed | F56: Cameron Brown (Dev Mgr)
B57: Workday Financials | C57: Test | F57: Jordan Reed (QA Lead)
B58: Workday Financials | C58: UAT | F58: Charlotte Price (Bus Analyst)
B59: Workday Financials | C59: Pre-prod | F59: Caleb Young (Release Mgr)
B60: Workday Financials | C60: Prod | F60: Natasha Roman (Ops Mgr)
B61: Workday Financials | C61: DR | F61: Matthew Haven (Infra Lead)
B62: MetricStream | C62: Dev | D62: Rachel Green | E62: William Chen | F62: Taylor Singh (Dev Mgr)
B63: MetricStream | C63: Test | F63: Alex Foster (QA Lead)
B64: MetricStream | C64: UAT | F64: Amelia Scott (Bus Analyst)
B65: MetricStream | C65: Pre-prod | F65: Owen King (Release Mgr)
B66: MetricStream | C66: Prod | F66: Amanda Cross (Ops Mgr)
B67: MetricStream | C67: DR | F67: Anthony Secure (Infra Lead)
B68: IBM Cognos | C68: Dev | D68: Thomas Wright | E68: Olivia Martinez | F68: Blake Thompson (Dev Mgr)
B69: IBM Cognos | C69: Test | F69: Morgan Hayes (QA Lead)
B70: IBM Cognos | C70: UAT | F70: Harper Lewis (Bus Analyst)
B71: IBM Cognos | C71: Pre-prod | F71: Liam Wright (Release Mgr)
B72: IBM Cognos | C72: Prod | F72: Rebecca Stone (Ops Mgr)
B73: IBM Cognos | C73: DR | F73: Mark Backup (Infra Lead)
B74: HighRadius | C74: Dev | D74: Diana Lee | E74: Nathan Brooks | F74: Alex Rivera (Dev Mgr)
B75: HighRadius | C75: Test | F75: Sam Anderson (QA Lead)
B76: HighRadius | C76: UAT | F76: Rachel Green (Bus Analyst)
B77: HighRadius | C77: Pre-prod | F77: Nathan Cole (Release Mgr)
B78: HighRadius | C78: Prod | F78: Victoria Sterling (Ops Mgr)
B79: HighRadius | C79: DR | F79: Robert Shield (Infra Lead)
B80: Basware | C80: Dev | D80: Steven Martinez | E80: Karen Singh | F80: Jordan Lee (Dev Mgr)
B81: Basware | C81: Test | F81: Chris Park (QA Lead)
B82: Basware | C82: UAT | F82: Monica Geller (Bus Analyst)
B83: Basware | C83: Pre-prod | F83: Ethan Black (Release Mgr)
B84: Basware | C84: Prod | F84: Elizabeth Crown (Ops Mgr)
B85: Basware | C85: DR | F85: William Guard (Infra Lead)
A86: Logistics | B86: SAP Transportation Management (TM) | C86: Dev | D86: Brian Murphy | E86: Marcus Johnson | F86: Alex Rivera (Dev Mgr)
B87: SAP Transportation Management (TM) | C87: Test | F87: Sam Anderson (QA Lead)
B88: SAP Transportation Management (TM) | C88: UAT | F88: Rachel Green (Bus Analyst)
B89: SAP Transportation Management (TM) | C89: Pre-prod | F89: Nathan Cole (Release Mgr)
B90: SAP Transportation Management (TM) | C90: Prod | F90: Victoria Sterling (Ops Mgr)
B91: SAP Transportation Management (TM) | C91: DR | F91: Robert Shield (Infra Lead)
B92: Oracle Transportation Management | C92: Dev | D92: Catherine Hayes | E92: Tina Wang | F92: Jordan Lee (Dev Mgr)
B93: Oracle Transportation Management | C93: Test | F93: Chris Park (QA Lead)
B94: Oracle Transportation Management | C94: UAT | F94: Monica Geller (Bus Analyst)
B95: Oracle Transportation Management | C95: Pre-prod | F95: Ethan Black (Release Mgr)
B96: Oracle Transportation Management | C96: Prod | F96: Elizabeth Crown (Ops Mgr)
B97: Oracle Transportation Management | C97: DR | F97: William Guard (Infra Lead)
B98: Blue Yonder WMS | C98: Dev | D98: Eric Johansson | E98: Alexander Petrov | F98: Casey Chen (Dev Mgr)
B99: Blue Yonder WMS | C99: Test | F99: Pat Murphy (QA Lead)
B100: Blue Yonder WMS | C100: UAT | F100: Phoebe Buffay (Bus Analyst)
...

Sheet Users
A1: User ID | B1: Name | C1: Email | D1: Role | E1: Department | F1: Manager | G1: Access Level | H1: Status | I1: Last Login
A2: USR-001 | B2: Alex Rivera | C2: alex.rivera@company.com | D2: Development Manager | E2: IT | F2: CTO Office | G2: Admin | H2: Active | I2: 46198
A3: USR-002 | B3: Jordan Lee | C3: jordan.lee@company.com | D3: Development Manager | E3: IT | F3: CTO Office | G3: Admin | H3: Active | I3: 46198
A4: USR-003 | B4: Casey Chen | C4: casey.chen@company.com | D4: Development Manager | E4: IT | F4: CTO Office | G4: Admin | H4: Active | I4: 46197
A5: USR-004 | B5: Morgan Taylor | C5: morgan.taylor@company.com | D5: Development Manager | E5: IT | F5: CTO Office | G5: Admin | H5: Active | I5: 46198
A6: USR-005 | B6: Jamie Patel | C6: jamie.patel@company.com | D6: Development Manager | E6: IT | F6: CTO Office | G6: Admin | H6: Active | I6: 46197
A7: USR-006 | B7: Riley Kim | C7: riley.kim@company.com | D7: Development Manager | E7: IT | F7: CTO Office | G7: Admin | H7: Active | I7: 46198
A8: USR-007 | B8: Quinn Johnson | C8: quinn.johnson@company.com | D8: Development Manager | E8: IT | F8: CTO Office | G8: Admin | H8: Active | I8: 46196
A9: USR-008 | B9: Avery Williams | C9: avery.williams@company.com | D9: Development Manager | E9: IT | F9: CTO Office | G9: Admin | H9: Active | I9: 46198
A10: USR-009 | B10: Drew Martinez | C10: drew.martinez@company.com | D10: Development Manager | E10: IT | F10: CTO Office | G10: Admin | H10: Active | I10: 46197
A11: USR-010 | B11: Cameron Brown | C11: cameron.brown@company.com | D11: Development Manager | E11: IT | F11: CTO Office | G11: Admin | H11: Active | I11: 46198
A12: USR-011 | B12: Taylor Singh | C12: taylor.singh@company.com | D12: Development Manager | E12: IT | F12: CTO Office | G12: Admin | H12: Active | I12: 46195
A13: USR-012 | B13: Blake Thompson | C13: blake.thompson@company.com | D13: Development Manager | E13: IT | F13: CTO Office | G13: Admin | H13: Active | I13: 46198
... A105: USR-104 | B105: Kevin Walsh | C105: kevin.walsh@company.com | D105: Conflict Resolution Specialist | E105: IT | F105: Release Director | G105: Standard | H105: Active | I105: 46208

Sheet Super Admins
A1: Admin ID | B1: Name | C1: Email | D1: Title | E1: Department | F1: Access Scope | G1: Granted Date | H1: Granted By | I1: Status | J1: Expiry Date | K1: Notes
A2: SA-001 | B2: Michael Stevens | C2: michael.stevens@company.com | D2: Chief Information Officer | E2: IT | F2: Global - All Systems | G2: 44635 | H2: CEO Office | I2: Active | J2: 46461 | K2: Executive sponsor for all IT initiatives
A3: SA-002 | B3: Jennifer Walsh | C3: jennifer.walsh@company.com | D3: VP of Enterprise Applications | E3: IT | F3: Global - All Systems | G3: 44936 | H3: Michael Stevens | I3: Active | J3: 46397 | K3: Oversight of all enterprise systems
A4: SA-003 | B4: Christopher Blake | C4: christopher.blake@company.com | D4: Director of IT Operations | E4: IT | F4: Global - Infrastructure | G4: 45097 | H4: Jennifer Walsh | I4: Active | J4: 46387 | K4: 24/7 operations oversight
A5: SA-004 | B5: Elizabeth Morgan | C5: elizabeth.morgan@company.com | D5: Head of Cybersecurity | E5: Security | F5: Global - All Systems | G5: 44774 | H5: Michael Stevens | I5: Active | J5: 46600 | K5: Security incident response authority
A6: SA-005 | B6: Robert Chen | C6: robert.chen@company.com | D6: Chief Technology Officer | E6: IT | F6: Global - All Systems | G6: 44326 | H6: CEO Office | I6: Active | J6: 46517 | K6: Technical architecture decisions
A7: SA-006 | B7: Patricia Wong | C7: patricia.wong@company.com | D7: Director of Release Management | E7: IT | F7: Global - Release Systems | G7: 45337 | H7: Jennifer Walsh | I7: Active | J7: 46249 | K7: Emergency release authority
A8: SA-007 | B8: Daniel Crawford | C8: daniel.crawford@company.com | D8: VP of HR Technology | E8: HR | F8: HR Systems - Global | G8: 45170 | H8: Jennifer Walsh | I8: Active | J8: 46266 | K8: HR data governance
A9: SA-008 | B9: Sarah Mitchell | C9: sarah.mitchell@company.com | D9: VP of Finance Systems | E9: Finance | F9: Finance Systems - Global | G9: 45031 | H9: Michael Stevens | I9: Active | J9: 46310 | K9: Financial data authority
A10: SA-009 | B10: Raymond Diaz | C10: raymond.diaz@company.com | D10: Cloud Platform Architect | E10: IT | F10: Global - Cloud Infrastructure | G10: 45296 | H10: Robert Chen | I10: Active | J10: 46208 | K10: AWS/Azure/GCP root access
A11: SA-010 | B11: Margaret Sullivan | C11: margaret.sullivan@company.com | D11: Identity & Access Manager | E11: Security | F11: Global - IAM Systems | G11: 45250 | H11: Elizabeth Morgan | I11: Active | J11: 46346 | K11: Identity management authority
A12: SA-011 | B12: Timothy Foster | C12: timothy.foster@company.com | D12: Disaster Recovery Manager | E12: IT | F12: Global - DR Systems | G12: 45361 | H12: Christopher Blake | I12: Active | J12: 46275 | K12: DR failover authority
A13: SA-012 | B13: Diane Wilson | C13: diane.wilson@company.com | D13: Database Administrator Lead | E13: IT | F13: Global - Databases | G13: 45122 | H13: Christopher Blake | I13: Active | J13: 46218 | K13: DBA root access all environments
A15: ⚠️ RESTRICTED ACCESS: Super Admin privileges require CIO or CEO approval. Access is audited and reviewed quarterly.

Sheet Admin (Release Managers)
A1: ID | B1: Name | C1: Email | D1: Department | E1: Region | F1: Phone | G1: Status | H1: Start Date | I1: Specialization
A2: RM-001 | B2: Nathan Cole | C2: nathan.cole@company.com | D2: IT | E2: North America | F2: +1-555-0101 | G2: Active | H2: 43905 | I2: Finance & HR Systems
A3: RM-002 | B3: Ethan Black | C3: ethan.black@company.com | D3: IT | E3: North America | F3: +1-555-0102 | G3: Active | H3: 43636 | I3: Manufacturing & Logistics
A4: RM-003 | B4: Lucas White | C4: lucas.white@company.com | D4: IT | E4: EMEA | F4: +44-20-5550103 | G4: Active | H4: 44206 | I4: CRM & Sales Systems
A5: RM-004 | B5: Mason Gray | C5: mason.gray@company.com | D5: IT | E5: EMEA | F5: +44-20-5550104 | G5: Active | H5: 43344 | I5: Security & Infrastructure
A6: RM-005 | B6: Logan Stone | C6: logan.stone@company.com | D6: IT | E6: APAC | F6: +61-2-5550105 | G6: Active | H6: 44150 | I6: Legal & Compliance
A7: RM-006 | B7: Jacob Hill | C7: jacob.hill@company.com | D7: IT | E7: APAC | F7: +61-2-5550106 | G7: Active | H7: 44620 | I7: HR & Talent Systems
A8: RM-007 | B8: Aiden Clark | C8: aiden.clark@company.com | D8: IT | E8: North America | F8: +1-555-0107 | G8: Active | H8: 43567 | I8: Integration & Middleware
A9: RM-008 | B9: Jackson Moore | C9: jackson.moore@company.com | D9: IT | E9: EMEA | F9: +44-20-5550108 | G9: Active | H9: 44399 | I9: Data & Analytics
A10: RM-009 | B10: Sebastian Hall | C10: sebastian.hall@company.com | D10: IT | E10: LATAM | F10: +55-11-5550109 | G10: Active | H10: 44048 | I10: ERP Systems
A11: RM-010 | B11: Caleb Young | C11: caleb.young@company.com | D11: IT | E11: North America | F11: +1-555-0110 | G11: Active | H11: 43070 | I11: Cloud & SaaS Platforms
A12: RM-011 | B12: Owen King | C12: owen.king@company.com | D12: IT | E12: APAC | F12: +65-5550111 | G12: Active | H12: 44699 | I12: Manufacturing Execution
A13: RM-012 | B13: Liam Wright | C13: liam.wright@company.com | D13: IT | E13: EMEA | F13: +49-30-5550112 | G13: On Leave | H13: 43768 | I13: Finance Reporting

Sheet Risk Factors
A1: COMPREHENSIVE RELEASE RISK SCORING MODEL
A2: Multi-factor weighted risk assessment for Release Desk Go/No-Go decisions
J3: Total Releases Assessed | K3: =COUNTA($A$68:$A$79) -> 12
A4: Category (Configurable) | B4: Risk Contribution (Configurable) | C4: Factor Name(Configurable) | D4: Weight | E4: Description | F4: Score 1 (Best) | G4: Score 5 (Worst) | H4: Data Source(Configurable) | J4: SEVERE Risk Releases | K4: =COUNTIF($AY$68:$AY$79,"SEVERE") -> 2 | L4: Immediate review required
A5: Technical Complexity | C5: Files Changed | D5: 0.01 | E5: Number of modified files | F5: <10 | G5: ≥100 | H5: Git/SCM | J5: CRITICAL Risk Releases | K5: =COUNTIF($AY$68:$AY$79,"CRITICAL") -> 1 | L5: Executive approval needed
C6: Code Churn (LOC) | D6: 0.02 | E6: Lines of code changed | F6: <200 | G6: ≥3000 | H6: Git/SCM | J6: HIGH Risk Releases | K6: =COUNTIF($AY$68:$AY$79,"HIGH") -> 0 | L6: CAB review required
B7: 8 | C7: DB Schema Changes | D7: 0.02 | E7: Database schema modifications | F7: 0 | G7: ≥5 | H7: Migration Scripts | J7: MEDIUM Risk Releases | K7: =COUNTIF($AY$68:$AY$79,"MEDIUM") -> 5 | L7: Enhanced monitoring
C8: API Contract Changes | D8: 0.02 | E8: Breaking API changes | F8: 0 | G8: ≥4 | H8: API Specs | J8: LOW Risk Releases | K8: =COUNTIF($AY$68:$AY$79,"LOW") -> 4 | L8: Standard deployment
C9: New Technology Stack | D9: 0.01 | E9: Unfamiliar tech introduced | F9: Proven stack | G9: Entirely new | H9: Architecture Review
A10: Testing Quality | C10: Test Coverage % | D10: 0.06 | E10: Code coverage percentage | F10: >90% | G10: <60% | H10: SonarQube | J10: Average Risk Score | K10: =ROUND(AVERAGE($AX$68:$AX$79),2) -> 2.28
C11: Test Execution Days | D11: 0.03 | E11: Testing duration | F11: <3 days | G11: ≥10 days | H11: Test Plan | J11: Highest Risk Release | K11: =INDEX($A$68:$A$79,MATCH(MAX($AX$68:$AX$79),$AX$68:$AX$79,0)) -> REL-0010 | L11: =MAX($AX$68:$AX$79) -> 4.52
C12: Bugs Found (Test) | D12: 0.04 | E12: Defects discovered in testing | F12: <3 | G12: ≥15 | H12: Jira
B13: 40 | C13: Bug Fix Rate % | D13: 0.02 | E13: Defects fixed vs found | F13: >95% | G13: <60% | H13: Jira
C14: UAT Duration Days | D14: 0.03 | E14: UAT testing period | F14: <3 days | G14: ≥10 days | H14: UAT Plan
C15: UAT Defects | D15: 0.04 | E15: Defects found in UAT | F15: <2 | G15: ≥8 | H15: Jira
C16: UAT Sign-off | D16: 0.02 | E16: Business sign-off status | F16: Full sign-off | G16: No sign-off | H16: UAT Tracker
C17: Test Env Parity | D17: 0.02 | E17: Test env match with Prod | F17: ≥95% match | G17: <60% match | H17: Env Config
A18: Security & Compliance | C18: Critical/High Vulns | D18: 0.03 | E18: Open security vulnerabilities | F18: 0 | G18: ≥5 | H18: SAST/DAST
B19: 8 | C19: Pen Test Sign-off | D19: 0.02 | E19: Penetration test status | F19: Passed | G19: Not done | H19: Security Team
C20: Compliance Gate | D20: 0.03 | E20: SOX/GDPR/PCI-DSS status | F20: All passed | G20: Blocked | H20: GRC System
A21: Data Migration | C21: Migration Required | D21: 0.01 | E21: Data migration needed | F21: No | G21: Yes, complex | H21: Release Notes | J21: RISK SCORE THRESHOLDS
C22: Backup Restore Tested | D22: 0.015 | E22: Backup/restore verified | F22: Yes, verified | G22: Not tested | H22: DBA Team | J22: Level | K22: Score Range | L22: Action
C23: Migration Script Tested | D23: 0.015 | E23: Migration scripts validated | F23: Tested in Pre-prod | G23: Not tested | H23: DBA Team | J23: LOW | K23: < 1.5 | L23: Standard deployment
A24: Resource & Schedule | C24: Testers Allocated | D24: 0.02 | E24: QA resource count | F24: >3 | G24: 1 or none | H24: Resource Plan | J24: MEDIUM | K24: 1.5 - 2.5 | L24: Enhanced monitoring
C25: Key Staff Availability | D25: 0.03 | E25: Critical personnel present | F25: All available | G25: Key staff OOO | H25: Leave Calendar | J25: HIGH | K25: 2.5 - 3.5 | L25: CAB review required
C26: Days Until Release | D26: 0.04 | E26: Time to deployment | F26: >30 days | G26: <5 days | H26: Release Schedule | J26: CRITICAL | K26: 3.5 - 4.0 | L26: Executive approval needed
C27: Downstream Releases | D27: 0.03 | E27: Dependent releases count | F27: 0 | G27: ≥4 | H27: Dependencies | J27: SEVERE | K27: ≥ 4.0 | L27: Postpone or major mitigation
C28: Overlapping Releases | D28: 0.02 | E28: Releases in same window | F28: 0 | G28: ≥4 | H28: Release Calendar
A29: Env & Dependencies | C29: Drift Issues | D29: 0.03 | E29: Environment drift count | F29: 0 | G29: ≥4 | H29: Drift Tracker
C30: Dependency Count | D30: 0.02 | E30: External dependencies | F30: 0 | G30: ≥4 | H30: Dependencies
C31: Dependency Health | D31: 0.02 | E31: Upstream system status | F31: All healthy | G31: Critical blocked | H31: Health Dashboard
C32: Feature Flag Cleanup | D32: 0.02 | E32: Stale feature flags | F32: Clean | G32: ≥5 stale flags | H32: Feature Mgmt
A33: Operational Readiness | C33: Rollback Plan | D33: 0.02 | E33: Rollback documented | F33: Full plan tested | G33: No plan | H33: Runbook
C34: Go-Live Checklist % | D34: 0.02 | E34: Checklist completion | F34: >90% | G34: <50% | H34: Checklist
C35: Change Freeze Impact | D35: 0.015 | E35: Freeze window conflict | F35: No conflict | G35: During freeze | H35: Calendar
C36: Vendor Coordination | D36: 0.005 | E36: Vendor readiness | F36: Confirmed | G36: Not coordinated | H36: Vendor Mgmt
C37: Rollback Time RTO | D37: 0.02 | E37: Rollback duration (min) | F37: <15 min | G37: >120 min | H37: Runbook
C38: Deployment Automation % | D38: 0.015 | E38: Automation level | F38: >90% | G38: <50% | H38: CI/CD Pipeline
A39: Performance & Scalability | C39: Load Test Status | D39: 0.02 | E39: Load testing result | F39: Passed | G39: Not done | H39: Perf Team
C40: Perf Regression % | D40: 0.02 | E40: Performance vs baseline | F40: <5% | G40: >25% | H40: APM Tools
A41: Release History | C41: BC Tested | D41: 0.015 | E41: Backward compatibility | F41: Fully tested | G41: Not tested | H41: Test Results
C42: Rollback Flow Tested | D42: 0.015 | E42: Rollback rehearsal done | F42: Tested in Pre-prod | G42: Never tested | H42: Deployment Runbook
C43: Previous Failures | D43: 0.005 | E43: Past failure history | F43: 0 failures (12mo) | G43: ≥3 failures | H43: Incident History
C44: Release Cadence Dev | D44: 0.005 | E44: Deviation from schedule | F44: On schedule | G44: >14 days late | H44: Release Plan
C45: MTBF Days | D45: 0.005 | E45: Mean time between failures | F45: >180 days | G45: <14 days | H45: Incident Metrics
C46: Recent Incidents | D46: 0.005 | E46: Incidents last 30 days | F46: 0 | G46: ≥3 | H46: Incident Mgmt
A47: Business Criticality | C47: Revenue Impact | D47: 0.01 | E47: Revenue risk if failed | F47: Low | G47: High | H47: Business Team
C48: User Blast Radius | D48: 0.01 | E48: Users/customers affected | F48: <100 | G48: >100K or all | H48: Product Team
A50: WEIGHT SUMMARY BY CATEGORY
A51: Category | C51: Weight | D51: Factors
A52: Technical Complexity | C52: 0.18 | D52: 5 factors
A53: Testing Quality | C53: 0.26 | D53: 8 factors
A54: Security & Compliance | C54: 0.08 | D54: 3 factors
A55: Data Migration | C55: 0.04 | D55: 3 factors
A56: Resource & Schedule | C56: 0.14 | D56: 5 factors
A57: Env & Dependencies | C57: 0.09 | D57: 4 factors
A58: Operational Readiness | C58: 0.1 | D58: 6 factors
A59: Performance & Scalability | C59: 0.04 | D59: 2 factors
A60: Release History | C60: 0.05 | D60: 6 factors
A61: Business Criticality | C61: 0.02 | D61: 2 factors
A62: TOTAL | C62: 1 | D62: 44 factors
A63: FORMULA: Weighted Score = Σ (Factor Score × Factor Weight)
A66: RELEASE RISK ASSESSMENT DATA
A67: Release ID | C67: Release Name | D67: Prod Date | E67: Days Out | F67: Files Changed | G67: Code Churn | H67: DB Changes | I67: API Changes | J67: New Tech Stack | K67: Test Coverage % | L67: Test Days | M67: Test Bugs | N67: Bug Fix Rate % | O67: UAT Days | P67: UAT Defects | Q67: UAT Sign-off | R67: Test Env Parity | S67: Crit/High Vulns | T67: Pen Test | U67: Compliance Gate | V67: Migration Req | W67: Backup Tested | X67: Migration Script | Y67: Team Size | Z67: Deploy Window | AA67: Freeze Proximity | AB67: Key Staff Avail | AC67: Overlapping Rels | AD67: Dep Count | AE67: Dep Health | AF67: Vendor Involvement | AG67: Feature Flags | AH67: Rollback Plan | AI67: Docs Complete | AJ67: Monitoring Ready | AK67: Runbook Updated | AL67: Rollback RTO | AM67: Deploy Auto % | AN67: Load Test | AO67: Perf Regression % | AP67: Vendor Patch | AQ67: Cadence Dev | AR67: MTBF Days | AS67: Past Failures | AT67: BC Tested | AU67: Rollback Tested | AV67: Revenue Impact | AW67: Blast Radius | AX67: WEIGHTED SCORE | AY67: RISK LEVEL
A68: REL-0001 | C68: Kyriba UI Tweak v4.5 | D68: 46203 | E68: 5 | F68: 12 | G68: 320 | H68: 0 | I68: 0 | J68: 1 | K68: 85 | L68: 3 | M68: 2 | N68: 100 | O68: 2 | P68: 0 | Q68: 4 | R68: 4 | S68: 0 | T68: 4 | U68: 5 | V68: 0 | W68: 5 | X68: 5 | Y68: 2 | Z68: 2 | AA68: 30 | AB68: 5 | AC68: 1 | AD68: 2 | AE68: 5 | AF68: 0 | AG68: 5 | AH68: 4 | AI68: 4 | AJ68: 4 | AK68: 4 | AL68: 15 | AM68: 90 | AN68: 5 | AO68: 5 | AP68: 5 | AQ68: 0 | AR68: 90 | AS68: 0 | AT68: 5 | AU68: 4 | AV68: 1 | AW68: 500 | AX68: =ROUND((IF(F68<10,1,IF(F68<30,2,IF(F68<60,3,IF(F68<100,4,5))))*0.04)+(IF(G68<200,1,IF(G68<500,2,IF(G68<1500,3,IF(G68<3000,4,5))))*0.03)+(IF(H68=0,1,IF(H68=1,2,IF(H68=2,3,IF(H68<5,4,5))))*0.05)+(IF(I68=0,1,IF(I68=1,2,IF(I68=2,3,IF(I68=3,4,5))))*0.04)+(J68*0.02)+(IF(K68>90,1,IF(K68>80,2,IF(K68>70,3,IF(K68>60,4,5))))*0.06)+(IF(L68<3,1,IF(L68<5,2,IF(L68<7,3,IF(L68<10,4,5))))*0.03)+(IF(M68<3,1,IF(M68<6,2,IF(M68<10,3,IF(M68<15,4,5))))*0.04)+(IF(N68>95,1,IF(N68>85,2,IF(N68>75,3,IF(N68>60,4,5))))*0.02)+(IF(O68<3,1,IF(O68<5,2,IF(O68<7,3,IF(O68<10,4,5))))*0.03)+(IF(P68<2,1,IF(P68<4,2,IF(P68<7,3,IF(P68<10,4,5))))*0.02)+((6-Q68)*0.03)+((6-R68)*0.02)+(IF(S68=0,1,IF(S68<3,2,IF(S68<5,3,IF(S68<10,4,5))))*0.03)+((6-T68)*0.03)+((6-U68)*0.02)+(IF(V68=0,1,3)*0.015)+((6-W68)*0.01)+((6-X68)*0.015)+(IF(Y68<3,1,IF(Y68<6,2,IF(Y68<10,3,IF(Y68<15,4,5))))*0.02)+(IF(Z68<2,1,IF(Z68<4,2,IF(Z68<6,3,IF(Z68<8,4,5))))*0.03)+(IF(AA68>14,1,IF(AA68>7,2,IF(AA68>3,3,IF(AA68>1,4,5))))*0.03)+((6-AB68)*0.03)+(IF(AC68=0,1,IF(AC68=1,2,IF(AC68=2,3,IF(AC68=3,4,5))))*0.03)+(IF(AD68<2,1,IF(AD68<4,2,IF(AD68<6,3,IF(AD68<8,4,5))))*0.03)+((6-AE68)*0.02)+(IF(AF68=0,1,IF(AF68=1,3,5))*0.02)+((6-AG68)*0.02)+((6-AH68)*0.02)+((6-AI68)*0.015)+((6-AJ68)*0.015)+((6-AK68)*0.015)+(IF(AL68<15,1,IF(AL68<30,2,IF(AL68<60,3,IF(AL68<120,4,5))))*0.02)+(IF(AM68>90,1,IF(AM68>75,2,IF(AM68>50,3,IF(AM68>25,4,5))))*0.015)+((6-AN68)*0.02)+(IF(AO68<5,1,IF(AO68<10,2,IF(AO68<15,3,IF(AO68<25,4,5))))*0.02)+((6-AP68)*0.01)+(IF(AQ68<2,1,IF(AQ68<5,2,IF(AQ68<10,3,IF(AQ68<20,4,5))))*0.008)+(IF(AR68>60,1,IF(AR68>30,2,IF(AR68>14,3,IF(AR68>7,4,5))))*0.008)+(IF(AS68=0,1,IF(AS68=1,2,IF(AS68=2,3,IF(AS68=3,4,5))))*0.01)+((6-AT68)*0.008)+((6-AU68)*0.008)+(AV68*0.01)+(IF(AW68<1000,1,IF(AW68<5000,2,IF(AW68<20000,3,IF(AW68<50000,4,5))))*0.01),2) -> 1.45 | AY68: =IF(AX68>=4,"SEVERE",IF(AX68>=3.5,"CRITICAL",IF(AX68>=2.5,"HIGH",IF(AX68>=1.5,"MEDIUM","LOW")))) -> LOW
A69: REL-0002 | C69: Blue Workflow v2.1 | D69: 46207 | E69: 9 | F69: 45 | G69: 1200 | H69: 1 | I69: 1 | J69: 2 | K69: 72 | L69: 5 | M69: 8 | N69: 90 | O69: 4 | P69: 3 | Q69: 3 | R69: 3 | S69: 2 | T69: 3 | U69: 4 | V69: 0 | W69: 4 | X69: 5 | Y69: 5 | Z69: 3 | AA69: 20 | AB69: 4 | AC69: 2 | AD69: 3 | AE69: 4 | AF69: 1 | AG69: 4 | AH69: 3 | AI69: 3 | AJ69: 3 | AK69: 4 | AL69: 30 | AM69: 75 | AN69: 4 | AO69: 10 | AP69: 4 | AQ69: 3 | AR69: 60 | AS69: 1 | AT69: 4 | AU69: 3 | AV69: 2 | AW69: 5000 | AX69: =ROUND((IF(F69<10,1,IF(F69<30,2,IF(F69<60,3,IF(F69<100,4,5))))*0.04)+(IF(G69<200,1,IF(G69<500,2,IF(G69<1500,3,IF(G69<3000,4,5))))*0.03)+(IF(H69=0,1,IF(H69=1,2,IF(H69=2,3,IF(H69<5,4,5))))*0.05)+(IF(I69=0,1,IF(I69=1,2,IF(I69=2,3,IF(I69=3,4,5))))*0.04)+(J69*0.02)+(IF(K69>90,1,IF(K69>80,2,IF(K69>70,3,IF(K69>60,4,5))))*0.06)+(IF(L69<3,1,IF(L69<5,2,IF(L69<7,3,IF(L69<10,4,5))))*0.03)+(IF(M69<3,1,IF(M69<6,2,IF(M69<10,3,IF(M69<15,4,5))))*0.04)+(IF(N69>95,1,IF(N69>85,2,IF(N69>75,3,IF(N69>60,4,5))))*0.02)+(IF(O69<3,1,IF(O69<5,2,IF(O69<7,3,IF(O69<10,4,5))))*0.03)+(IF(P69<2,1,IF(P69<4,2,IF(P69<7,3,IF(P69<10,4,5))))*0.02)+((6-Q69)*0.03)+((6-R69)*0.02)+(IF(S69=0,1,IF(S69<3,2,IF(S69<5,3,IF(S69<10,4,5))))*0.03)+((6-T69)*0.03)+((6-U69)*0.02)+(IF(V69=0,1,3)*0.015)+((6-W69)*0.01)+((6-X69)*0.015)+(IF(Y69<3,1,IF(Y69<6,2,IF(Y69<10,3,IF(Y69<15,4,5))))*0.02)+(IF(Z69<2,1,IF(Z69<4,2,IF(Z69<6,3,IF(Z69<8,4,5))))*0.03)+(IF(AA69>14,1,IF(AA69>7,2,IF(AA69>3,3,IF(AA69>1,4,5))))*0.03)+((6-AB69)*0.03)+(IF(AC69=0,1,IF(AC69=1,2,IF(AC69=2,3,IF(AC69=3,4,5))))*0.03)+(IF(AD69<2,1,IF(AD69<4,2,IF(AD69<6,3,IF(AD69<8,4,5))))*0.03)+((6-AE69)*0.02)+(IF(AF69=0,1,IF(AF69=1,3,5))*0.02)+((6-AG69)*0.02)+((6-AH69)*0.02)+((6-AI69)*0.015)+((6-AJ69)*0.015)+((6-AK69)*0.015)+(IF(AL69<15,1,IF(AL69<30,2,IF(AL69<60,3,IF(AL69<120,4,5))))*0.02)+(IF(AM69>90,1,IF(AM69>75,2,IF(AM69>50,3,IF(AM69>25,4,5))))*0.015)+((6-AN69)*0.02)+(IF(AO69<5,1,IF(AO69<10,2,IF(AO69<15,3,IF(AO69<25,4,5))))*0.02)+((6-AP69)*0.01)+(IF(AQ69<2,1,IF(AQ69<5,2,IF(AQ69<10,3,IF(AQ69<20,4,5))))*0.008)+(IF(AR69>60,1,IF(AR69>30,2,IF(AR69>14,3,IF(AR69>7,4,5))))*0.008)+(IF(AS69=0,1,IF(AS69=1,2,IF(AS69=2,3,IF(AS69=3,4,5))))*0.01)+((6-AT69)*0.008)+((6-AU69)*0.008)+(AV69*0.01)+(IF(AW69<1000,1,IF(AW69<5000,2,IF(AW69<20000,3,IF(AW69<50000,4,5))))*0.01),2) -> 2.38 | AY69: =IF(AX69>=4,"SEVERE",IF(AX69>=3.5,"CRITICAL",IF(AX69>=2.5,"HIGH",IF(AX69>=1.5,"MEDIUM","LOW")))) -> MEDIUM
A70: REL-0003 | C70: Zendesk Minor v4.3 | D70: 46205 | E70: 7 | F70: 5 | G70: 80 | H70: 0 | I70: 0 | J70: 1 | K70: 92 | L70: 2 | M70: 1 | N70: 100 | O70: 1 | P70: 0 | Q70: 5 | R70: 5 | S70: 0 | T70: 5 | U70: 5 | V70: 0 | W70: 5 | X70: 5 | Y70: 2 | Z70: 1 | AA70: 45 | AB70: 5 | AC70: 0 | AD70: 1 | AE70: 5 | AF70: 0 | AG70: 5 | AH70: 5 | AI70: 5 | AJ70: 5 | AK70: 5 | AL70: 10 | AM70: 95 | AN70: 5 | AO70: 2 | AP70: 5 | AQ70: 5 | AR70: 120 | AS70: 0 | AT70: 5 | AU70: 5 | AV70: 1 | AW70: 200 | AX70: =ROUND((IF(F70<10,1,IF(F70<30,2,IF(F70<60,3,IF(F70<100,4,5))))*0.04)+(IF(G70<200,1,IF(G70<500,2,IF(G70<1500,3,IF(G70<3000,4,5))))*0.03)+(IF(H70=0,1,IF(H70=1,2,IF(H70=2,3,IF(H70<5,4,5))))*0.05)+(IF(I70=0,1,IF(I70=1,2,IF(I70=2,3,IF(I70=3,4,5))))*0.04)+(J70*0.02)+(IF(K70>90,1,IF(K70>80,2,IF(K70>70,3,IF(K70>60,4,5))))*0.06)+(IF(L70<3,1,IF(L70<5,2,IF(L70<7,3,IF(L70<10,4,5))))*0.03)+(IF(M70<3,1,IF(M70<6,2,IF(M70<10,3,IF(M70<15,4,5))))*0.04)+(IF(N70>95,1,IF(N70>85,2,IF(N70>75,3,IF(N70>60,4,5))))*0.02)+(IF(O70<3,1,IF(O70<5,2,IF(O70<7,3,IF(O70<10,4,5))))*0.03)+(IF(P70<2,1,IF(P70<4,2,IF(P70<7,3,IF(P70<10,4,5))))*0.02)+((6-Q70)*0.03)+((6-R70)*0.02)+(IF(S70=0,1,IF(S70<3,2,IF(S70<5,3,IF(S70<10,4,5))))*0.03)+((6-T70)*0.03)+((6-U70)*0.02)+(IF(V70=0,1,3)*0.015)+((6-W70)*0.01)+((6-X70)*0.015)+(IF(Y70<3,1,IF(Y70<6,2,IF(Y70<10,3,IF(Y70<15,4,5))))*0.02)+(IF(Z70<2,1,IF(Z70<4,2,IF(Z70<6,3,IF(Z70<8,4,5))))*0.03)+(IF(AA70>14,1,IF(AA70>7,2,IF(AA70>3,3,IF(AA70>1,4,5))))*0.03)+((6-AB70)*0.03)+(IF(AC70=0,1,IF(AC70=1,2,IF(AC70=2,3,IF(AC70=3,4,5))))*0.03)+(IF(AD70<2,1,IF(AD70<4,2,IF(AD70<6,3,IF(AD70<8,4,5))))*0.03)+((6-AE70)*0.02)+(IF(AF70=0,1,IF(AF70=1,3,5))*0.02)+((6-AG70)*0.02)+((6-AH70)*0.02)+((6-AI70)*0.015)+((6-AJ70)*0.015)+((6-AK70)*0.015)+(IF(AL70<15,1,IF(AL70<30,2,IF(AL70<60,3,IF(AL70<120,4,5))))*0.02)+(IF(AM70>90,1,IF(AM70>75,2,IF(AM70>50,3,IF(AM70>25,4,5))))*0.015)+((6-AN70)*0.02)+(IF(AO70<5,1,IF(AO70<10,2,IF(AO70<15,3,IF(AO70<25,4,5))))*0.02)+((6-AP70)*0.01)+(IF(AQ70<2,1,IF(AQ70<5,2,IF(AQ70<10,3,IF(AQ70<20,4,5))))*0.008)+(IF(AR70>60,1,IF(AR70>30,2,IF(AR70>14,3,IF(AR70>7,4,5))))*0.008)+(IF(AS70=0,1,IF(AS70=1,2,IF(AS70=2,3,IF(AS70=3,4,5))))*0.01)+((6-AT70)*0.008)+((6-AU70)*0.008)+(AV70*0.01)+(IF(AW70<1000,1,IF(AW70<5000,2,IF(AW70<20000,3,IF(AW70<50000,4,5))))*0.01),2) -> 1.01 | AY70: =IF(AX70>=4,"SEVERE",IF(AX70>=3.5,"CRITICAL",IF(AX70>=2.5,"HIGH",IF(AX70>=1.5,"MEDIUM","LOW")))) -> LOW
A71: REL-0004 | C71: Oracle HFM Upgrade v12 | D71: 46210 | E71: 12 | F71: 85 | G71: 3200 | H71: 4 | I71: 2 | J71: 3 | K71: 65 | L71: 8 | M71: 15 | N71: 80 | O71: 7 | P71: 8 | Q71: 2 | R71: 2 | S71: 5 | T71: 2 | U71: 3 | V71: 1 | W71: 3 | X71: 3 | Y71: 8 | Z71: 4 | AA71: 10 | AB71: 3 | AC71: 3 | AD71: 5 | AE71: 3 | AF71: 2 | AG71: 3 | AH71: 2 | AI71: 2 | AJ71: 2 | AK71: 3 | AL71: 60 | AM71: 60 | AN71: 3 | AO71: 18 | AP71: 3 | AQ71: 2 | AR71: 45 | AS71: 2 | AT71: 3 | AU71: 2 | AV71: 3 | AW71: 25000 | AX71: =ROUND((IF(F71<10,1,IF(F71<30,2,IF(F71<60,3,IF(F71<100,4,5))))*0.04)+(IF(G71<200,1,IF(G71<500,2,IF(G71<1500,3,IF(G71<3000,4,5))))*0.03)+(IF(H71=0,1,IF(H71=1,2,IF(H71=2,3,IF(H71<5,4,5))))*0.05)+(IF(I71=0,1,IF(I71=1,2,IF(I71=2,3,IF(I71=3,4,5))))*0.04)+(J71*0.02)+(IF(K71>90,1,IF(K71>80,2,IF(K71>70,3,IF(K71>60,4,5))))*0.06)+(IF(L71<3,1,IF(L71<5,2,IF(L71<7,3,IF(L71<10,4,5))))*0.03)+(IF(M71<3,1,IF(M71<6,2,IF(M71<10,3,IF(M71<15,4,5))))*0.04)+(IF(N71>95,1,IF(N71>85,2,IF(N71>75,3,IF(N71>60,4,5))))*0.02)+(IF(O71<3,1,IF(O71<5,2,IF(O71<7,3,IF(O71<10,4,5))))*0.03)+(IF(P71<2,1,IF(P71<4,2,IF(P71<7,3,IF(P71<10,4,5))))*0.02)+((6-Q71)*0.03)+((6-R71)*0.02)+(IF(S71=0,1,IF(S71<3,2,IF(S71<5,3,IF(S71<10,4,5))))*0.03)+((6-T71)*0.03)+((6-U71)*0.02)+(IF(V71=0,1,3)*0.015)+((6-W71)*0.01)+((6-X71)*0.015)+(IF(Y71<3,1,IF(Y71<6,2,IF(Y71<10,3,IF(Y71<15,4,5))))*0.02)+(IF(Z71<2,1,IF(Z71<4,2,IF(Z71<6,3,IF(Z71<8,4,5))))*0.03)+(IF(AA71>14,1,IF(AA71>7,2,IF(AA71>3,3,IF(AA71>1,4,5))))*0.03)+((6-AB71)*0.03)+(IF(AC71=0,1,IF(AC71=1,2,IF(AC71=2,3,IF(AC71=3,4,5))))*0.03)+(IF(AD71<2,1,IF(AD71<4,2,IF(AD71<6,3,IF(AD71<8,4,5))))*0.03)+((6-AE71)*0.02)+(IF(AF71=0,1,IF(AF71=1,3,5))*0.02)+((6-AG71)*0.02)+((6-AH71)*0.02)+((6-AI71)*0.015)+((6-AJ71)*0.015)+((6-AK71)*0.015)+(IF(AL71<15,1,IF(AL71<30,2,IF(AL71<60,3,IF(AL71<120,4,5))))*0.02)+(IF(AM71>90,1,IF(AM71>75,2,IF(AM71>50,3,IF(AM71>25,4,5))))*0.015)+((6-AN71)*0.02)+(IF(AO71<5,1,IF(AO71<10,2,IF(AO71<15,3,IF(AO71<25,4,5))))*0.02)+((6-AP71)*0.01)+(IF(AQ71<2,1,IF(AQ71<5,2,IF(AQ71<10,3,IF(AQ71<20,4,5))))*0.008)+(IF(AR71>60,1,IF(AR71>30,2,IF(AR71>14,3,IF(AR71>7,4,5))))*0.008)+(IF(AS71=0,1,IF(AS71=1,2,IF(AS71=2,3,IF(AS71=3,4,5))))*0.01)+((6-AT71)*0.008)+((6-AU71)*0.008)+(AV71*0.01)+(IF(AW71<1000,1,IF(AW71<5000,2,IF(AW71<20000,3,IF(AW71<50000,4,5))))*0.01),2) -> 3.59 | AY71: =IF(AX71>=4,"SEVERE",IF(AX71>=3.5,"CRITICAL",IF(AX71>=2.5,"HIGH",IF(AX71>=1.5,"MEDIUM","LOW")))) -> CRITICAL
A72: REL-0005 | C72: Coupa Integration v3.0 | D72: 46215 | E72: 17 | F72: 35 | G72: 950 | H72: 1 | I72: 2 | J72: 2 | K72: 78 | L72: 4 | M72: 5 | N72: 95 | O72: 3 | P72: 2 | Q72: 4 | R72: 4 | S72: 1 | T72: 4 | U72: 4 | V72: 0 | W72: 4 | X72: 5 | Y72: 4 | Z72: 3 | AA72: 25 | AB72: 4 | AC72: 1 | AD72: 3 | AE72: 4 | AF72: 1 | AG72: 4 | AH72: 4 | AI72: 4 | AJ72: 4 | AK72: 4 | AL72: 25 | AM72: 80 | AN72: 4 | AO72: 8 | AP72: 4 | AQ72: 4 | AR72: 75 | AS72: 0 | AT72: 4 | AU72: 4 | AV72: 2 | AW72: 8000 | AX72: =ROUND((IF(F72<10,1,IF(F72<30,2,IF(F72<60,3,IF(F72<100,4,5))))*0.04)+(IF(G72<200,1,IF(G72<500,2,IF(G72<1500,3,IF(G72<3000,4,5))))*0.03)+(IF(H72=0,1,IF(H72=1,2,IF(H72=2,3,IF(H72<5,4,5))))*0.05)+(IF(I72=0,1,IF(I72=1,2,IF(I72=2,3,IF(I72=3,4,5))))*0.04)+(J72*0.02)+(IF(K72>90,1,IF(K72>80,2,IF(K72>70,3,IF(K72>60,4,5))))*0.06)+(IF(L72<3,1,IF(L72<5,2,IF(L72<7,3,IF(L72<10,4,5))))*0.03)+(IF(M72<3,1,IF(M72<6,2,IF(M72<10,3,IF(M72<15,4,5))))*0.04)+(IF(N72>95,1,IF(N72>85,2,IF(N72>75,3,IF(N72>60,4,5))))*0.02)+(IF(O72<3,1,IF(O72<5,2,IF(O72<7,3,IF(O72<10,4,5))))*0.03)+(IF(P72<2,1,IF(P72<4,2,IF(P72<7,3,IF(P72<10,4,5))))*0.02)+((6-Q72)*0.03)+((6-R72)*0.02)+(IF(S72=0,1,IF(S72<3,2,IF(S72<5,3,IF(S72<10,4,5))))*0.03)+((6-T72)*0.03)+((6-U72)*0.02)+(IF(V72=0,1,3)*0.015)+((6-W72)*0.01)+((6-X72)*0.015)+(IF(Y72<3,1,IF(Y72<6,2,IF(Y72<10,3,IF(Y72<15,4,5))))*0.02)+(IF(Z72<2,1,IF(Z72<4,2,IF(Z72<6,3,IF(Z72<8,4,5))))*0.03)+(IF(AA72>14,1,IF(AA72>7,2,IF(AA72>3,3,IF(AA72>1,4,5))))*0.03)+((6-AB72)*0.03)+(IF(AC72=0,1,IF(AC72=1,2,IF(AC72=2,3,IF(AC72=3,4,5))))*0.03)+(IF(AD72<2,1,IF(AD72<4,2,IF(AD72<6,3,IF(AD72<8,4,5))))*0.03)+((6-AE72)*0.02)+(IF(AF72=0,1,IF(AF72=1,3,5))*0.02)+((6-AG72)*0.02)+((6-AH72)*0.02)+((6-AI72)*0.015)+((6-AJ72)*0.015)+((6-AK72)*0.015)+(IF(AL72<15,1,IF(AL72<30,2,IF(AL72<60,3,IF(AL72<120,4,5))))*0.02)+(IF(AM72>90,1,IF(AM72>75,2,IF(AM72>50,3,IF(AM72>25,4,5))))*0.015)+((6-AN72)*0.02)+(IF(AO72<5,1,IF(AO72<10,2,IF(AO72<15,3,IF(AO72<25,4,5))))*0.02)+((6-AP72)*0.01)+(IF(AQ72<2,1,IF(AQ72<5,2,IF(AQ72<10,3,IF(AQ72<20,4,5))))*0.008)+(IF(AR72>60,1,IF(AR72>30,2,IF(AR72>14,3,IF(AR72>7,4,5))))*0.008)+(IF(AS72=0,1,IF(AS72=1,2,IF(AS72=2,3,IF(AS72=3,4,5))))*0.01)+((6-AT72)*0.008)+((6-AU72)*0.008)+(AV72*0.01)+(IF(AW72<1000,1,IF(AW72<5000,2,IF(AW72<20000,3,IF(AW72<50000,4,5))))*0.01),2) -> 2.11 | AY72: =IF(AX72>=4,"SEVERE",IF(AX72>=3.5,"CRITICAL",IF(AX72>=2.5,"HIGH",IF(AX72>=1.5,"MEDIUM","LOW")))) -> MEDIUM
A73: REL-0006 | C73: Salesforce Patch v8.2 | D73: 46220 | E73: 22 | F73: 18 | G73: 420 | H73: 0 | I73: 1 | J73: 1 | K73: 88 | L73: 3 | M73: 3 | N73: 100 | O73: 2 | P73: 1 | Q73: 4 | R73: 4 | S73: 0 | T73: 4 | U73: 5 | V73: 0 | W73: 5 | X73: 5 | Y73: 3 | Z73: 2 | AA73: 35 | AB73: 5 | AC73: 0 | AD73: 2 | AE73: 5 | AF73: 0 | AG73: 5 | AH73: 4 | AI73: 4 | AJ73: 4 | AK73: 5 | AL73: 20 | AM73: 85 | AN73: 5 | AO73: 4 | AP73: 5 | AQ73: 5 | AR73: 90 | AS73: 0 | AT73: 5 | AU73: 5 | AV73: 1 | AW73: 1500 | AX73: =ROUND((IF(F73<10,1,IF(F73<30,2,IF(F73<60,3,IF(F73<100,4,5))))*0.04)+(IF(G73<200,1,IF(G73<500,2,IF(G73<1500,3,IF(G73<3000,4,5))))*0.03)+(IF(H73=0,1,IF(H73=1,2,IF(H73=2,3,IF(H73<5,4,5))))*0.05)+(IF(I73=0,1,IF(I73=1,2,IF(I73=2,3,IF(I73=3,4,5))))*0.04)+(J73*0.02)+(IF(K73>90,1,IF(K73>80,2,IF(K73>70,3,IF(K73>60,4,5))))*0.06)+(IF(L73<3,1,IF(L73<5,2,IF(L73<7,3,IF(L73<10,4,5))))*0.03)+(IF(M73<3,1,IF(M73<6,2,IF(M73<10,3,IF(M73<15,4,5))))*0.04)+(IF(N73>95,1,IF(N73>85,2,IF(N73>75,3,IF(N73>60,4,5))))*0.02)+(IF(O73<3,1,IF(O73<5,2,IF(O73<7,3,IF(O73<10,4,5))))*0.03)+(IF(P73<2,1,IF(P73<4,2,IF(P73<7,3,IF(P73<10,4,5))))*0.02)+((6-Q73)*0.03)+((6-R73)*0.02)+(IF(S73=0,1,IF(S73<3,2,IF(S73<5,3,IF(S73<10,4,5))))*0.03)+((6-T73)*0.03)+((6-U73)*0.02)+(IF(V73=0,1,3)*0.015)+((6-W73)*0.01)+((6-X73)*0.015)+(IF(Y73<3,1,IF(Y73<6,2,IF(Y73<10,3,IF(Y73<15,4,5))))*0.02)+(IF(Z73<2,1,IF(Z73<4,2,IF(Z73<6,3,IF(Z73<8,4,5))))*0.03)+(IF(AA73>14,1,IF(AA73>7,2,IF(AA73>3,3,IF(AA73>1,4,5))))*0.03)+((6-AB73)*0.03)+(IF(AC73=0,1,IF(AC73=1,2,IF(AC73=2,3,IF(AC73=3,4,5))))*0.03)+(IF(AD73<2,1,IF(AD73<4,2,IF(AD73<6,3,IF(AD73<8,4,5))))*0.03)+((6-AE73)*0.02)+(IF(AF73=0,1,IF(AF73=1,3,5))*0.02)+((6-AG73)*0.02)+((6-AH73)*0.02)+((6-AI73)*0.015)+((6-AJ73)*0.015)+((6-AK73)*0.015)+(IF(AL73<15,1,IF(AL73<30,2,IF(AL73<60,3,IF(AL73<120,4,5))))*0.02)+(IF(AM73>90,1,IF(AM73>75,2,IF(AM73>50,3,IF(AM73>25,4,5))))*0.015)+((6-AN73)*0.02)+(IF(AO73<5,1,IF(AO73<10,2,IF(AO73<15,3,IF(AO73<25,4,5))))*0.02)+((6-AP73)*0.01)+(IF(AQ73<2,1,IF(AQ73<5,2,IF(AQ73<10,3,IF(AQ73<20,4,5))))*0.008)+(IF(AR73>60,1,IF(AR73>30,2,IF(AR73>14,3,IF(AR73>7,4,5))))*0.008)+(IF(AS73=0,1,IF(AS73=1,2,IF(AS73=2,3,IF(AS73=3,4,5))))*0.01)+((6-AT73)*0.008)+((6-AU73)*0.008)+(AV73*0.01)+(IF(AW73<1000,1,IF(AW73<5000,2,IF(AW73<20000,3,IF(AW73<50000,4,5))))*0.01),2) -> 1.5 | AY73: =IF(AX73>=4,"SEVERE",IF(AX73>=3.5,"CRITICAL",IF(AX73>=2.5,"HIGH",IF(AX73>=1.5,"MEDIUM","LOW")))) -> MEDIUM
A74: REL-0007 | C74: SAP S4 Finance v2.0 | D74: 46225 | E74: 27 | F74: 150 | G74: 8500 | H74: 5 | I74: 4 | J74: 4 | K74: 58 | L74: 12 | M74: 25 | N74: 75 | O74: 10 | P74: 12 | Q74: 2 | R74: 2 | S74: 8 | T74: 2 | U74: 2 | V74: 1 | W74: 2 | X74: 2 | Y74: 12 | Z74: 5 | AA74: 7 | AB74: 2 | AC74: 4 | AD74: 6 | AE74: 2 | AF74: 3 | AG74: 4 | AH74: 2 | AI74: 2 | AJ74: 2 | AK74: 2 | AL74: 90 | AM74: 50 | AN74: 2 | AO74: 22 | AP74: 2 | AQ74: 2 | AR74: 30 | AS74: 3 | AT74: 2 | AU74: 2 | AV74: 5 | AW74: 50000 | AX74: =ROUND((IF(F74<10,1,IF(F74<30,2,IF(F74<60,3,IF(F74<100,4,5))))*0.04)+(IF(G74<200,1,IF(G74<500,2,IF(G74<1500,3,IF(G74<3000,4,5))))*0.03)+(IF(H74=0,1,IF(H74=1,2,IF(H74=2,3,IF(H74<5,4,5))))*0.05)+(IF(I74=0,1,IF(I74=1,2,IF(I74=2,3,IF(I74=3,4,5))))*0.04)+(J74*0.02)+(IF(K74>90,1,IF(K74>80,2,IF(K74>70,3,IF(K74>60,4,5))))*0.06)+(IF(L74<3,1,IF(L74<5,2,IF(L74<7,3,IF(L74<10,4,5))))*0.03)+(IF(M74<3,1,IF(M74<6,2,IF(M74<10,3,IF(M74<15,4,5))))*0.04)+(IF(N74>95,1,IF(N74>85,2,IF(N74>75,3,IF(N74>60,4,5))))*0.02)+(IF(O74<3,1,IF(O74<5,2,IF(O74<7,3,IF(O74<10,4,5))))*0.03)+(IF(P74<2,1,IF(P74<4,2,IF(P74<7,3,IF(P74<10,4,5))))*0.02)+((6-Q74)*0.03)+((6-R74)*0.02)+(IF(S74=0,1,IF(S74<3,2,IF(S74<5,3,IF(S74<10,4,5))))*0.03)+((6-T74)*0.03)+((6-U74)*0.02)+(IF(V74=0,1,3)*0.015)+((6-W74)*0.01)+((6-X74)*0.015)+(IF(Y74<3,1,IF(Y74<6,2,IF(Y74<10,3,IF(Y74<15,4,5))))*0.02)+(IF(Z74<2,1,IF(Z74<4,2,IF(Z74<6,3,IF(Z74<8,4,5))))*0.03)+(IF(AA74>14,1,IF(AA74>7,2,IF(AA74>3,3,IF(AA74>1,4,5))))*0.03)+((6-AB74)*0.03)+(IF(AC74=0,1,IF(AC74=1,2,IF(AC74=2,3,IF(AC74=3,4,5))))*0.03)+(IF(AD74<2,1,IF(AD74<4,2,IF(AD74<6,3,IF(AD74<8,4,5))))*0.03)+((6-AE74)*0.02)+(IF(AF74=0,1,IF(AF74=1,3,5))*0.02)+((6-AG74)*0.02)+((6-AH74)*0.02)+((6-AI74)*0.015)+((6-AJ74)*0.015)+((6-AK74)*0.015)+(IF(AL74<15,1,IF(AL74<30,2,IF(AL74<60,3,IF(AL74<120,4,5))))*0.02)+(IF(AM74>90,1,IF(AM74>75,2,IF(AM74>50,3,IF(AM74>25,4,5))))*0.015)+((6-AN74)*0.02)+(IF(AO74<5,1,IF(AO74<10,2,IF(AO74<15,3,IF(AO74<25,4,5))))*0.02)+((6-AP74)*0.01)+(IF(AQ74<2,1,IF(AQ74<5,2,IF(AQ74<10,3,IF(AQ74<20,4,5))))*0.008)+(IF(AR74>60,1,IF(AR74>30,2,IF(AR74>14,3,IF(AR74>7,4,5))))*0.008)+(IF(AS74=0,1,IF(AS74=1,2,IF(AS74=2,3,IF(AS74=3,4,5))))*0.01)+((6-AT74)*0.008)+((6-AU74)*0.008)+(AV74*0.01)+(IF(AW74<1000,1,IF(AW74<5000,2,IF(AW74<20000,3,IF(AW74<50000,4,5))))*0.01),2) -> 4.24 | AY74: =IF(AX74>=4,"SEVERE",IF(AX74>=3.5,"CRITICAL",IF(AX74>=2.5,"HIGH",IF(AX74>=1.5,"MEDIUM","LOW")))) -> SEVERE
A75: REL-0008 | C75: Workday HR Update v5.1 | D75: 46230 | E75: 32 | F75: 42 | G75: 1100 | H75: 2 | I75: 1 | J75: 2 | K75: 75 | L75: 5 | M75: 6 | N75: 92 | O75: 4 | P75: 3 | Q75: 3 | R75: 3 | S75: 1 | T75: 3 | U75: 4 | V75: 0 | W75: 4 | X75: 5 | Y75: 5 | Z75: 3 | AA75: 28 | AB75: 4 | AC75: 2 | AD75: 3 | AE75: 4 | AF75: 1 | AG75: 4 | AH75: 3 | AI75: 3 | AJ75: 4 | AK75: 4 | AL75: 35 | AM75: 70 | AN75: 4 | AO75: 12 | AP75: 4 | AQ75: 3 | AR75: 55 | AS75: 1 | AT75: 4 | AU75: 3 | AV75: 2 | AW75: 12000 | AX75: =ROUND((IF(F75<10,1,IF(F75<30,2,IF(F75<60,3,IF(F75<100,4,5))))*0.04)+(IF(G75<200,1,IF(G75<500,2,IF(G75<1500,3,IF(G75<3000,4,5))))*0.03)+(IF(H75=0,1,IF(H75=1,2,IF(H75=2,3,IF(H75<5,4,5))))*0.05)+(IF(I75=0,1,IF(I75=1,2,IF(I75=2,3,IF(I75=3,4,5))))*0.04)+(J75*0.02)+(IF(K75>90,1,IF(K75>80,2,IF(K75>70,3,IF(K75>60,4,5))))*0.06)+(IF(L75<3,1,IF(L75<5,2,IF(L75<7,3,IF(L75<10,4,5))))*0.03)+(IF(M75<3,1,IF(M75<6,2,IF(M75<10,3,IF(M75<15,4,5))))*0.04)+(IF(N75>95,1,IF(N75>85,2,IF(N75>75,3,IF(N75>60,4,5))))*0.02)+(IF(O75<3,1,IF(O75<5,2,IF(O75<7,3,IF(O75<10,4,5))))*0.03)+(IF(P75<2,1,IF(P75<4,2,IF(P75<7,3,IF(P75<10,4,5))))*0.02)+((6-Q75)*0.03)+((6-R75)*0.02)+(IF(S75=0,1,IF(S75<3,2,IF(S75<5,3,IF(S75<10,4,5))))*0.03)+((6-T75)*0.03)+((6-U75)*0.02)+(IF(V75=0,1,3)*0.015)+((6-W75)*0.01)+((6-X75)*0.015)+(IF(Y75<3,1,IF(Y75<6,2,IF(Y75<10,3,IF(Y75<15,4,5))))*0.02)+(IF(Z75<2,1,IF(Z75<4,2,IF(Z75<6,3,IF(Z75<8,4,5))))*0.03)+(IF(AA75>14,1,IF(AA75>7,2,IF(AA75>3,3,IF(AA75>1,4,5))))*0.03)+((6-AB75)*0.03)+(IF(AC75=0,1,IF(AC75=1,2,IF(AC75=2,3,IF(AC75=3,4,5))))*0.03)+(IF(AD75<2,1,IF(AD75<4,2,IF(AD75<6,3,IF(AD75<8,4,5))))*0.03)+((6-AE75)*0.02)+(IF(AF75=0,1,IF(AF75=1,3,5))*0.02)+((6-AG75)*0.02)+((6-AH75)*0.02)+((6-AI75)*0.015)+((6-AJ75)*0.015)+((6-AK75)*0.015)+(IF(AL75<15,1,IF(AL75<30,2,IF(AL75<60,3,IF(AL75<120,4,5))))*0.02)+(IF(AM75>90,1,IF(AM75>75,2,IF(AM75>50,3,IF(AM75>25,4,5))))*0.015)+((6-AN75)*0.02)+(IF(AO75<5,1,IF(AO75<10,2,IF(AO75<15,3,IF(AO75<25,4,5))))*0.02)+((6-AP75)*0.01)+(IF(AQ75<2,1,IF(AQ75<5,2,IF(AQ75<10,3,IF(AQ75<20,4,5))))*0.008)+(IF(AR75>60,1,IF(AR75>30,2,IF(AR75>14,3,IF(AR75>7,4,5))))*0.008)+(IF(AS75=0,1,IF(AS75=1,2,IF(AS75=2,3,IF(AS75=3,4,5))))*0.01)+((6-AT75)*0.008)+((6-AU75)*0.008)+(AV75*0.01)+(IF(AW75<1000,1,IF(AW75<5000,2,IF(AW75<20000,3,IF(AW75<50000,4,5))))*0.01),2) -> 2.41 | AY75: =IF(AX75>=4,"SEVERE",IF(AX75>=3.5,"CRITICAL",IF(AX75>=2.5,"HIGH",IF(AX75>=1.5,"MEDIUM","LOW")))) -> MEDIUM
